Workbook
Name cad: [1]Cad_Sku!$1:$1048576
Name Plan5: #REF!
Name SegmentaçãodeDados_DATA_ENVASE: #N/A
Name semana: #REF!
Name semana: #REF!

Sheet Dinâmica
A3: DATA ENVASE | B3: LINHA | C3: CÓDIGO2 | D3: DESCRIÇÃO P.A | E3: Soma de QTD Programada (CX)
A4: 46156 | B4: L40 | C4: 17107-7 | D4: MONANGE DES ANTI SENSIVEL 12X90G NVF | E4: 14866
A5: 46156 | C5: 20257-4 | D5: MONANGE DES ANTIT INVISL 12X89G MT | E5: 22539
A6: 46156 | B6: L57 | C6: 27214-0 | D6: BOZZANO DES ANTI EXTREME SPORT 12X200ML | E6: 16725
A7: 46156 | B7: (vazio) | C7: (vazio) | D7: (vazio)
A8: 46157 | B8: L40 | C8: 20257-4 | D8: MONANGE DES ANTIT INVISL 12X89G MT | E8: 22539
A9: 46157 | C9: 25004-1 | D9: BOZZANO DES ANTI CARVAO 12X90G NVF | E9: 14866
A10: 46157 | C10: 25503-1 | D10: MONANGE DES ANTIT ESPORTE AERO 12X90G MT | E10: 21246
A11: 46157 | B11: L57 | C11: 29555-1 | D11: MONANGE DES ANTIT PROT SEC 12X200ML MT | E11: 11150
A12: 46157 | B12: (vazio) | C12: (vazio) | D12: (vazio)
A13: 46158 | B13: L40 | C13: 17111-7 | D13: MONANGE DES ANTIT HIDR INTEN 12X90G MT | E13: 22299
A14: 46158 | B14: L57 | C14: 27212-1 | D14: MONANGE DES ANTIT FR VM 12X200ML MT | E14: 11150
A15: 46158 | B15: (vazio) | C15: (vazio) | D15: (vazio)
A16: 46160 | B16: 0 | C16: 25503-1 | D16: MONANGE DES ANTIT ESPORTE AERO 12X90G MT | E16: 21246
A17: 46160 | B17: L40 | C17: 25004-1 | D17: BOZZANO DES ANTI CARVAO 12X90G NVF | E17: 14866
A18: 46160 | B18: L57 | C18: 29554-0 | D18: BOZZANO DES ANTIT ANTIBAC FRESH 12X200ML | E18: 11150
A19: 46160 | B19: (vazio) | C19: (vazio) | D19: (vazio)
A20: 46161 | B20: L40 | C20: 13441-6 | D20: BOZZANO DES ANTI S PERF SENS 12X90G NVF | E20: 21237
A21: 46161 | C21: 17111-7 | D21: MONANGE DES ANTIT HIDR INTEN 12X90G MT | E21: 22299
A22: 46161 | B22: L57 | C22: 29554-0 | D22: BOZZANO DES ANTIT ANTIBAC FRESH 12X200ML | E22: 11150
A23: 46161 | B23: (vazio) | C23: (vazio) | D23: (vazio)
A24: 46162 | B24: 0 | C24: 29554-0 | D24: BOZZANO DES ANTIT ANTIBAC FRESH 12X200ML | E24: 11150
A25: 46162 | B25: L40 | C25: 17110-8 | D25: MONANGE DES ANTIT FRTS VM 12X90G MT | E25: 22299
A26: 46162 | B26: (vazio) | C26: 20257-3 | D26: MONANGE DES ANTI INVISIVEL 12X89G NVF
A27: 46162 | C27: (vazio) | D27: (vazio)
A28: 46163 | B28: 0 | C28: 25003-1 | D28: BOZZANO DES ANTI DRY 12X90G NVF | E28: 7433
A29: 46163 | B29: L40 | C29: 17109-7 | D29: MONANGE DES ANTIT FL LAV 12X90G MT | E29: 22299
A30: 46163 | C30: 17110-8 | D30: MONANGE DES ANTIT FRTS VM 12X90G MT | E30: 22299
A31: 46163 | B31: L57 | C31: 27213-1 | D31: MONANGE DES ANTIT INVIS 12X200ML MT | E31: 11238
A32: 46163 | B32: (vazio) | C32: (vazio) | D32: (vazio)
A33: 46164 | B33: L40 | C33: 25645-0 | D33: BOZZANO CLINIC ULTRA COOL AERO 12X94G | E33: 8488
A34: 46164 | B34: (vazio) | C34: (vazio) | D34: (vazio)
A35: 46165 | B35: 0 | C35: 17111-7 | D35: MONANGE DES ANTIT HIDR INTEN 12X90G MT | E35: 14866
A36: 46165 | B36: L40 | C36: 17109-7 | D36: MONANGE DES ANTIT FL LAV 12X90G MT | E36: 22299
A37: 46165 | C37: 17110-8 | D37: MONANGE DES ANTIT FRTS VM 12X90G MT | E37: 22299
A38: 46165 | B38: (vazio) | C38: (vazio) | D38: (vazio)
A39: 46167 | B39: 0 | C39: 17109-7 | D39: MONANGE DES ANTIT FL LAV 12X90G MT | E39: 14866
A40: 46167 | C40: 17111-7 | D40: MONANGE DES ANTIT HIDR INTEN 12X90G MT | E40: 14866
A41: 46167 | B41: L40 | C41: 17110-8 | D41: MONANGE DES ANTIT FRTS VM 12X90G MT | E41: 22299
A42: 46167 | B42: L57 | C42: 29552-0 | D42: BOZZANO DES ANTIT CARVAO ATIV 12X200ML | E42: 16725
A43: 46167 | B43: (vazio) | C43: (vazio) | D43: (vazio)
A44: 46168 | B44: L40 | C44: 17109-7 | D44: MONANGE DES ANTIT FL LAV 12X90G MT | E44: 22299
A45: 46168 | C45: 17110-8 | D45: MONANGE DES ANTIT FRTS VM 12X90G MT | E45: 22299
A46: 46168 | C46: 23209-5 | D46: ADIDAS DES ANTI PRO INVISIBLE MASC 150ML | E46: 15026
A47: 46168 | B47: (vazio) | C47: (vazio) | D47: (vazio)
A48: 46169 | B48: L57 | C48: 29552-0 | D48: BOZZANO DES ANTIT CARVAO ATIV 12X200ML | E48: 16725
A49: 46169 | B49: (vazio) | C49: (vazio) | D49: (vazio)
A50: 46170 | B50: L40 | C50: 17109-7 | D50: MONANGE DES ANTIT FL LAV 12X90G MT | E50: 22299
A51: 46170 | C51: 17110-8 | D51: MONANGE DES ANTIT FRTS VM 12X90G MT | E51: 22299
A52: 46170 | C52: 23208-4 | D52: ADIDAS DES ANTI CONTR INVISIBLE FEM 150M | E52: 14310
A53: 46170 | B53: L57 | C53: 27215-0 | D53: BOZZANO DES ANTI INVISIBLE 12X200ML | E53: 11244
A54: 46170 | B54: (vazio) | C54: (vazio) | D54: (vazio)
A55: 46171 | B55: L40 | C55: 17110-8 | D55: MONANGE DES ANTIT FRTS VM 12X90G MT | E55: 14866
A56: 46171 | C56: 27172-0 | D56: ADIDAS DES ANTI POWER BOOSTER MASC 150ML | E56: 7433
A57: 46171 | B57: L57 | C57: 27215-0 | D57: BOZZANO DES ANTI INVISIBLE 12X200ML | E57: 11244
A58: 46171 | B58: (vazio) | C58: (vazio) | D58: (vazio)
A59: 46172 | B59: 0 | C59: 27215-0 | D59: BOZZANO DES ANTI INVISIBLE 12X200ML | E59: 11244
A60: 46172 | B60: L40 | C60: 17109-7 | D60: MONANGE DES ANTIT FL LAV 12X90G MT | E60: 14866
A61: 46172 | C61: 17110-8 | D61: MONANGE DES ANTIT FRTS VM 12X90G MT | E61: 14866
A62: 46172 | C62: 29030-0 | D62: ADIDAS DES ANTI CLINICAL CARE FEM 150ML | E62: 4244
A63: 46172 | B63: (vazio) | C63: (vazio) | D63: (vazio)
A64: 46174 | B64: L40 | C64: 17109-7 | D64: MONANGE DES ANTIT FL LAV 12X90G MT | E64: 14866
A65: 46174 | B65: L57 | C65: 27213-0 | D65: MONANGE DES ANTI INVISIVEL 12X200ML | E65: 5619
A66: 46174 | B66: (vazio) | C66: (vazio) | D66: (vazio)
A67: Total Geral | E67: 738503

Sheet INDICADOR DE RENDIMENTO MENSAL
R1: RESUMO MENSAL POR SKU
A2: LINHA | B2: CÓDIGO | C2: DESCRIÇÃO P.A | D2: ORDEM | E2: Data Início | F2: Data Fim | G2: QTD OP | H2: QTD REALIZADA | I2: RENDIMENTO | L2: CÓDIGO | M2: DESCRIÇÃO P.A | N2: Soma de QTD OP | O2: Soma de QTD REALIZADA | P2: Rendimento Geral | R2: CÓDIGO | S2: DESCRIÇÃO P.A | T2: Soma de QTD OP | U2: Soma de QTD REALIZADA | V2: RENDIMENTO GERAL
A3: L40 | B3: 25643-2 | C3: MONANGE CLIN REVIG AERO 12X94G MT | D3: 1960517 | E3: =_xlfn.XLOOKUP(D3,'COHVPI DATAS REALIZADAS'!C:C,'COHVPI DATAS REALIZADAS'!N:N,0,0,1) -> 0 | F3: =_xlfn.XLOOKUP(D3,'COHVPI DATAS REALIZADAS'!C:C,'COHVPI DATAS REALIZADAS'!O:O,0,0,1) -> 0 | G3: =_xlfn.XLOOKUP(D3,COHVPI!A:A,COHVPI!E:E,0,0,1) -> 0 | H3: =_xlfn.XLOOKUP(D3,COHVPI!A:A,COHVPI!F:F,0,0,1) -> 0 | I3: =H3/G3 -> #DIV/0! | L3: 10909-3 | M3: BOZZANO ESPUMA BARBA REFRES 6X193G CIN | N3: 13330 | O3: 12971 | P3: =O3/N3 -> 0.97306827 | R3: 8627-4 | S3: TRES MARCHAND DES ANTI CLASS 12X90G NVF | T3: 6457 | U3: 7132 | V3: 1.1045377
A4: L40 | B4: 25644-0 | C4: BOZZANO CLINICAL CLEAN AERO 12X94G | D4: 1960536 | E4: =_xlfn.XLOOKUP(D4,'COHVPI DATAS REALIZADAS'!C:C,'COHVPI DATAS REALIZADAS'!N:N,0,0,1) -> 46143 | F4: =_xlfn.XLOOKUP(D4,'COHVPI DATAS REALIZADAS'!C:C,'COHVPI DATAS REALIZADAS'!O:O,0,0,1) -> 46144 | G4: =_xlfn.XLOOKUP(D4,COHVPI!A:A,COHVPI!E:E,0,0,1) -> 8488 | H4: =_xlfn.XLOOKUP(D4,COHVPI!A:A,COHVPI!F:F,0,0,1) -> 8160 | I4: =H4/G4 -> 0.96135721 | L4: 13441-6 | M4: BOZZANO DES ANTI S PERF SENS 12X90G NVF | N4: 42474 | O4: 43802 | P4: =O4/N4 -> 1.0312662 | R4: 25643-2 | S4: MONANGE CLIN REVIG AERO 12X94G MT | T4: 8488 | U4: 9248 | V4: 1.0895382
A5: L40 | B5: 8627-4 | C5: TRES MARCHAND DES ANTI CLASS 12X90G NVF | D5: 1959059 | E5: =_xlfn.XLOOKUP(D5,'COHVPI DATAS REALIZADAS'!C:C,'COHVPI DATAS REALIZADAS'!N:N,0,0,1) -> 46146 | F5: =_xlfn.XLOOKUP(D5,'COHVPI DATAS REALIZADAS'!C:C,'COHVPI DATAS REALIZADAS'!O:O,0,0,1) -> 46146 | G5: =_xlfn.XLOOKUP(D5,COHVPI!A:A,COHVPI!E:E,0,0,1) -> 6457 | H5: =_xlfn.XLOOKUP(D5,COHVPI!A:A,COHVPI!F:F,0,0,1) -> 7132 | I5: =H5/G5 -> 1.1045377 | L5: 17107-7 | M5: MONANGE DES ANTI SENSIVEL 12X90G NVF | N5: 14866 | O5: 14553 | P5: =O5/N5 -> 0.97894524 | R5: 13441-6 | S5: BOZZANO DES ANTI S PERF SENS 12X90G NVF | T5: 42474 | U5: 43802 | V5: 1.0312662
A6: L40 | B6: 24631-2 | C6: MONANGE DES ANTIT PROT SEC 12X90G MT | D6: 1960792 | E6: =_xlfn.XLOOKUP(D6,'COHVPI DATAS REALIZADAS'!C:C,'COHVPI DATAS REALIZADAS'!N:N,0,0,1) -> 46147 | F6: =_xlfn.XLOOKUP(D6,'COHVPI DATAS REALIZADAS'!C:C,'COHVPI DATAS REALIZADAS'!O:O,0,0,1) -> 46149 | G6: =_xlfn.XLOOKUP(D6,COHVPI!A:A,COHVPI!E:E,0,0,1) -> 22299 | H6: =_xlfn.XLOOKUP(D6,COHVPI!A:A,COHVPI!F:F,0,0,1) -> 21600 | I6: =H6/G6 -> 0.9686533 | L6: 17109-6 | M6: MONANGE DES ANTI FLOR LAV 12X90G NVF | N6: 14866 | O6: 14628 | P6: =O6/N6 -> 0.98399031 | R6: 27213-1 | S6: MONANGE DES ANTIT INVIS 12X200ML MT | T6: 11238 | U6: 11560 | V6: 1.0286528
A7: L40 | B7: 24631-2 | C7: MONANGE DES ANTIT PROT SEC 12X90G MT | D7: 1960789 | E7: =_xlfn.XLOOKUP(D7,'COHVPI DATAS REALIZADAS'!C:C,'COHVPI DATAS REALIZADAS'!N:N,0,0,1) -> 46148 | F7: =_xlfn.XLOOKUP(D7,'COHVPI DATAS REALIZADAS'!C:C,'COHVPI DATAS REALIZADAS'!O:O,0,0,1) -> 46150 | G7: =_xlfn.XLOOKUP(D7,COHVPI!A:A,COHVPI!E:E,0,0,1) -> 14866 | H7: =_xlfn.XLOOKUP(D7,COHVPI!A:A,COHVPI!F:F,0,0,1) -> 14160 | I7: =H7/G7 -> 0.95250908 | L7: 17109-7 | M7: MONANGE DES ANTIT FL LAV 12X90G MT | N7: 104062 | O7: 101766 | P7: =O7/N7 -> 0.97793623 | R7: 20257-4 | S7: MONANGE DES ANTIT INVISL 12X89G MT | T7: 90156 | U7: 92605 | V7: 1.027164
A8: L40 | B8: 24631-2 | C8: MONANGE DES ANTIT PROT SEC 12X90G MT | D8: 1960790 | E8: =_xlfn.XLOOKUP(D8,'COHVPI DATAS REALIZADAS'!C:C,'COHVPI DATAS REALIZADAS'!N:N,0,0,1) -> 46150 | F8: =_xlfn.XLOOKUP(D8,'COHVPI DATAS REALIZADAS'!C:C,'COHVPI DATAS REALIZADAS'!O:O,0,0,1) -> 46151 | G8: =_xlfn.XLOOKUP(D8,COHVPI!A:A,COHVPI!E:E,0,0,1) -> 14866 | H8: =_xlfn.XLOOKUP(D8,COHVPI!A:A,COHVPI!F:F,0,0,1) -> 14640 | I8: =H8/G8 -> 0.98479752 | L8: 17110-8 | M8: MONANGE DES ANTIT FRTS VM 12X90G MT | N8: 163526 | O8: 164733 | P8: =O8/N8 -> 1.0073811 | R8: 25503-1 | S8: MONANGE DES ANTIT ESPORTE AERO 12X90G MT | T8: 35410 | U8: 36177 | V8: 1.0216605
A9: L40 | B9: 24631-2 | C9: MONANGE DES ANTIT PROT SEC 12X90G MT | D9: 1960791 | E9: =_xlfn.XLOOKUP(D9,'COHVPI DATAS REALIZADAS'!C:C,'COHVPI DATAS REALIZADAS'!N:N,0,0,1) -> 46151 | F9: =_xlfn.XLOOKUP(D9,'COHVPI DATAS REALIZADAS'!C:C,'COHVPI DATAS REALIZADAS'!O:O,0,0,1) -> 46153 | G9: =_xlfn.XLOOKUP(D9,COHVPI!A:A,COHVPI!E:E,0,0,1) -> 14866 | H9: =_xlfn.XLOOKUP(D9,COHVPI!A:A,COHVPI!F:F,0,0,1) -> 14721 | I9: =H9/G9 -> 0.9902462 | L9: 17111-6 | M9: MONANGE DES ANTI HIDR INTEN 12X90G NVF | N9: 14866 | O9: 14517 | P9: =O9/N9 -> 0.97652361 | R9: 27211-0 | S9: MONANGE DES ANTI HIDR INTENSIVA 12X200ML | T9: 5309 | U9: 5370 | V9: 1.0114899
A10: L40 | B10: 17109-6 | C10: MONANGE DES ANTI FLOR LAV 12X90G NVF | D10: 1962558 | E10: =_xlfn.XLOOKUP(D10,'COHVPI DATAS REALIZADAS'!C:C,'COHVPI DATAS REALIZADAS'!N:N,0,0,1) -> 46153 | F10: =_xlfn.XLOOKUP(D10,'COHVPI DATAS REALIZADAS'!C:C,'COHVPI DATAS REALIZADAS'!O:O,0,0,1) -> 46155 | G10: =_xlfn.XLOOKUP(D10,COHVPI!A:A,COHVPI!E:E,0,0,1) -> 14866 | H10: =_xlfn.XLOOKUP(D10,COHVPI!A:A,COHVPI!F:F,0,0,1) -> 14628 | I10: =H10/G10 -> 0.98399031 | L10: 17111-7 | M10: MONANGE DES ANTIT HIDR INTEN 12X90G MT | N10: 163526 | O10: 164237 | P10: =O10/N10 -> 1.0043479 | R10: 17110-8 | S10: MONANGE DES ANTIT FRTS VM 12X90G MT | T10: 163526 | U10: 164733 | V10: 1.0073811
A11: L40 | B11: 17111-6 | C11: MONANGE DES ANTI HIDR INTEN 12X90G NVF | D11: 1962536 | E11: =_xlfn.XLOOKUP(D11,'COHVPI DATAS REALIZADAS'!C:C,'COHVPI DATAS REALIZADAS'!N:N,0,0,1) -> 46155 | F11: =_xlfn.XLOOKUP(D11,'COHVPI DATAS REALIZADAS'!C:C,'COHVPI DATAS REALIZADAS'!O:O,0,0,1) -> 46156 | G11: =_xlfn.XLOOKUP(D11,COHVPI!A:A,COHVPI!E:E,0,0,1) -> 14866 | H11: =_xlfn.XLOOKUP(D11,COHVPI!A:A,COHVPI!F:F,0,0,1) -> 14517 | I11: =H11/G11 -> 0.97652361 | L11: 17425-5 | M11: BOZZANO DES ANTI ANTBAC FRESH 12X90G NVF | N11: 52031 | O11: 51444 | P11: =O11/N11 -> 0.98871826 | R11: 17111-7 | S11: MONANGE DES ANTIT HIDR INTEN 12X90G MT | T11: 163526 | U11: 164237 | V11: 1.0043479
A12: L40 | B12: 17107-7 | C12: MONANGE DES ANTI SENSIVEL 12X90G NVF | D12: 1962321 | E12: =_xlfn.XLOOKUP(D12,'COHVPI DATAS REALIZADAS'!C:C,'COHVPI DATAS REALIZADAS'!N:N,0,0,1) -> 46156 | F12: =_xlfn.XLOOKUP(D12,'COHVPI DATAS REALIZADAS'!C:C,'COHVPI DATAS REALIZADAS'!O:O,0,0,1) -> 46157 | G12: =_xlfn.XLOOKUP(D12,COHVPI!A:A,COHVPI!E:E,0,0,1) -> 14866 | H12: =_xlfn.XLOOKUP(D12,COHVPI!A:A,COHVPI!F:F,0,0,1) -> 14553 | I12: =H12/G12 -> 0.97894524 | L12: 18998-5 | M12: BOZZANO DES ANTI EXTREM SPORT 12X90G NVF | N12: 44598 | O12: 43926 | P12: =O12/N12 -> 0.98493206 | R12: 23209-5 | S12: ADIDAS DES ANTI PRO INVISIBLE MASC 150ML | T12: 15026 | U12: 14980 | V12: 0.99693864
A13: L40 | B13: 20257-3 | C13: MONANGE DES ANTI INVISIVEL 12X89G NVF | D13: 1963047 | E13: =_xlfn.XLOOKUP(D13,'COHVPI DATAS REALIZADAS'!C:C,'COHVPI DATAS REALIZADAS'!N:N,0,0,1) -> 46157 | F13: =_xlfn.XLOOKUP(D13,'COHVPI DATAS REALIZADAS'!C:C,'COHVPI DATAS REALIZADAS'!O:O,0,0,1) -> 46158 | G13: =_xlfn.XLOOKUP(D13,COHVPI!A:A,COHVPI!E:E,0,0,1) -> 7513 | H13: =_xlfn.XLOOKUP(D13,COHVPI!A:A,COHVPI!F:F,0,0,1) -> 7473 | I13: =H13/G13 -> 0.9946759 | L13: 20257-3 | M13: MONANGE DES ANTI INVISIVEL 12X89G NVF | N13: 7513 | O13: 7473 | P13: =O13/N13 -> 0.9946759 | R13: 29554-0 | S13: BOZZANO DES ANTIT ANTIBAC FRESH 12X200ML | T13: 44600 | U13: 44460 | V13: 0.99686099
A14: L40 | B14: 25503-1 | C14: MONANGE DES ANTIT ESPORTE AERO 12X90G MT | D14: 1962322 | E14: =_xlfn.XLOOKUP(D14,'COHVPI DATAS REALIZADAS'!C:C,'COHVPI DATAS REALIZADAS'!N:N,0,0,1) -> 46158 | F14: =_xlfn.XLOOKUP(D14,'COHVPI DATAS REALIZADAS'!C:C,'COHVPI DATAS REALIZADAS'!O:O,0,0,1) -> 46161 | G14: =_xlfn.XLOOKUP(D14,COHVPI!A:A,COHVPI!E:E,0,0,1) -> 21246 | H14: =_xlfn.XLOOKUP(D14,COHVPI!A:A,COHVPI!F:F,0,0,1) -> 21575 | I14: =H14/G14 -> 1.0154853 | L14: 20257-4 | M14: MONANGE DES ANTIT INVISL 12X89G MT | N14: 90156 | O14: 92605 | P14: =O14/N14 -> 1.027164 | R14: 27212-0 | S14: MONANGE DES ANTI FR VERMELHAS 12X200ML | T14: 5574.5 | U14: 5555 | V14: 0.99650193
... A20: L40 | B20: 17109-7 | C20: MONANGE DES ANTIT FL LAV 12X90G MT | D20: 1962329 | E20: =_xlfn.XLOOKUP(D20,'COHVPI DATAS REALIZADAS'!C:C,'COHVPI DATAS REALIZADAS'!N:N,0,0,1) -> 46171 | F20: =_xlfn.XLOOKUP(D20,'COHVPI DATAS REALIZADAS'!C:C,'COHVPI DATAS REALIZADAS'!O:O,0,0,1) -> 46172 | G20: =_xlfn.XLOOKUP(D20,COHVPI!A:A,COHVPI!E:E,0,0,1) -> 14866 | H20: =_xlfn.XLOOKUP(D20,COHVPI!A:A,COHVPI!F:F,0,0,1) -> 14640 | I20: =H20/G20 -> 0.98479752 | L20: 25503-1 | M20: MONANGE DES ANTIT ESPORTE AERO 12X90G MT | N20: 35410 | O20: 36177 | P20: =O20/N20 -> 1.0216605 | R20: 27211-1 | S20: MONANGE DES ANTIT HIDR INTEN 12X200ML MT | T20: 50175 | U20: 49477 | V20: 0.98608869
A21: TOTAL L40 | G21: =SUM(G3:G20) -> 273425 | H21: =SUM(H3:H20) -> 269527 | I21: =H21/G21 -> 0.98574381 | L21: 25643-2 | M21: MONANGE CLIN REVIG AERO 12X94G MT | N21: 8488 | O21: 9248 | P21: =O21/N21 -> 1.0895382 | R21: 27214-0 | S21: BOZZANO DES ANTI EXTREME SPORT 12X200ML | T21: 33450 | U21: 32974 | V21: 0.98576981
A22: L53 | B22: 13441-6 | C22: BOZZANO DES ANTI S PERF SENS 12X90G NVF | D22: 1960532 | E22: =_xlfn.XLOOKUP(D22,'COHVPI DATAS REALIZADAS'!C:C,'COHVPI DATAS REALIZADAS'!N:N,0,0,1) -> 0 | F22: =_xlfn.XLOOKUP(D22,'COHVPI DATAS REALIZADAS'!C:C,'COHVPI DATAS REALIZADAS'!O:O,0,0,1) -> 0 | G22: =_xlfn.XLOOKUP(D22,COHVPI!A:A,COHVPI!E:E,0,0,1) -> 0 | H22: =_xlfn.XLOOKUP(D22,COHVPI!A:A,COHVPI!F:F,0,0,1) -> 0 | I22: =H22/G22 -> #DIV/0! | L22: 25644-0 | M22: BOZZANO CLINICAL CLEAN AERO 12X94G | N22: 8488 | O22: 8160 | P22: =O22/N22 -> 0.96135721 | R22: 18998-5 | S22: BOZZANO DES ANTI EXTREM SPORT 12X90G NVF | T22: 44598 | U22: 43926 | V22: 0.98493206
A23: L53 | B23: 13441-6 | C23: BOZZANO DES ANTI S PERF SENS 12X90G NVF | D23: 1960534 | E23: =_xlfn.XLOOKUP(D23,'COHVPI DATAS REALIZADAS'!C:C,'COHVPI DATAS REALIZADAS'!N:N,0,0,1) -> 46144 | F23: =_xlfn.XLOOKUP(D23,'COHVPI DATAS REALIZADAS'!C:C,'COHVPI DATAS REALIZADAS'!O:O,0,0,1) -> 46146 | G23: =_xlfn.XLOOKUP(D23,COHVPI!A:A,COHVPI!E:E,0,0,1) -> 7079 | H23: =_xlfn.XLOOKUP(D23,COHVPI!A:A,COHVPI!F:F,0,0,1) -> 7392 | I23: =H23/G23 -> 1.0442153 | L23: 25645-0 | M23: BOZZANO CLINIC ULTRA COOL AERO 12X94G | N23: 8488 | O23: 8457 | P23: =O23/N23 -> 0.99634779 | R23: 29553-0 | S23: BOZZANO DES ANTIT DRY 12X200ML | T23: 33450 | U23: 32935 | V23: 0.98460389
A24: L53 | B24: 18998-5 | C24: BOZZANO DES ANTI EXTREM SPORT 12X90G NVF | D24: 1960535 | E24: =_xlfn.XLOOKUP(D24,'COHVPI DATAS REALIZADAS'!C:C,'COHVPI DATAS REALIZADAS'!N:N,0,0,1) -> 46146 | F24: =_xlfn.XLOOKUP(D24,'COHVPI DATAS REALIZADAS'!C:C,'COHVPI DATAS REALIZADAS'!O:O,0,0,1) -> 46148 | G24: =_xlfn.XLOOKUP(D24,COHVPI!A:A,COHVPI!E:E,0,0,1) -> 14866 | H24: =_xlfn.XLOOKUP(D24,COHVPI!A:A,COHVPI!F:F,0,0,1) -> 14160 | I24: =H24/G24 -> 0.95250908 | L24: 27211-0 | M24: MONANGE DES ANTI HIDR INTENSIVA 12X200ML | N24: 5309 | O24: 5370 | P24: =O24/N24 -> 1.0114899 | R24: 17109-6 | S24: MONANGE DES ANTI FLOR LAV 12X90G NVF | T24: 14866 | U24: 14628 | V24: 0.98399031
A25: L53 | B25: 18998-5 | C25: BOZZANO DES ANTI EXTREM SPORT 12X90G NVF | D25: 1960537 | E25: =_xlfn.XLOOKUP(D25,'COHVPI DATAS REALIZADAS'!C:C,'COHVPI DATAS REALIZADAS'!N:N,0,0,1) -> 46148 | F25: =_xlfn.XLOOKUP(D25,'COHVPI DATAS REALIZADAS'!C:C,'COHVPI DATAS REALIZADAS'!O:O,0,0,1) -> 46149 | G25: =_xlfn.XLOOKUP(D25,COHVPI!A:A,COHVPI!E:E,0,0,1) -> 14866 | H25: =_xlfn.XLOOKUP(D25,COHVPI!A:A,COHVPI!F:F,0,0,1) -> 14640 | I25: =H25/G25 -> 0.98479752 | L25: 27211-1 | M25: MONANGE DES ANTIT HIDR INTEN 12X200ML MT | N25: 50175 | O25: 49477 | P25: =O25/N25 -> 0.98608869 | R25: 29555-1 | S25: MONANGE DES ANTIT PROT SEC 12X200ML MT | T25: 11150 | U25: 10931 | V25: 0.98035874
A26: L53 | B26: 18998-5 | C26: BOZZANO DES ANTI EXTREM SPORT 12X90G NVF | D26: 1960538 | E26: =_xlfn.XLOOKUP(D26,'COHVPI DATAS REALIZADAS'!C:C,'COHVPI DATAS REALIZADAS'!N:N,0,0,1) -> 46149 | F26: =_xlfn.XLOOKUP(D26,'COHVPI DATAS REALIZADAS'!C:C,'COHVPI DATAS REALIZADAS'!O:O,0,0,1) -> 46151 | G26: =_xlfn.XLOOKUP(D26,COHVPI!A:A,COHVPI!E:E,0,0,1) -> 14866 | H26: =_xlfn.XLOOKUP(D26,COHVPI!A:A,COHVPI!F:F,0,0,1) -> 15126 | I26: =H26/G26 -> 1.0174896 | L26: 27212-0 | M26: MONANGE DES ANTI FR VERMELHAS 12X200ML | N26: 5574.5 | O26: 5555 | P26: =O26/N26 -> 0.99650193 | R26: 17107-7 | S26: MONANGE DES ANTI SENSIVEL 12X90G NVF | T26: 14866 | U26: 14553 | V26: 0.97894524
A27: L53 | B27: 17425-5 | C27: BOZZANO DES ANTI ANTBAC FRESH 12X90G NVF | D27: 1960539 | E27: =_xlfn.XLOOKUP(D27,'COHVPI DATAS REALIZADAS'!C:C,'COHVPI DATAS REALIZADAS'!N:N,0,0,1) -> 46150 | F27: =_xlfn.XLOOKUP(D27,'COHVPI DATAS REALIZADAS'!C:C,'COHVPI DATAS REALIZADAS'!O:O,0,0,1) -> 46151 | G27: =_xlfn.XLOOKUP(D27,COHVPI!A:A,COHVPI!E:E,0,0,1) -> 14866 | H27: =_xlfn.XLOOKUP(D27,COHVPI!A:A,COHVPI!F:F,0,0,1) -> 14640 | I27: =H27/G27 -> 0.98479752 | L27: 27212-1 | M27: MONANGE DES ANTIT FR VM 12X200ML MT | N27: 27875 | O27: 27245 | P27: =O27/N27 -> 0.9773991 | R27: 17109-7 | S27: MONANGE DES ANTIT FL LAV 12X90G MT | T27: 104062 | U27: 101766 | V27: 0.97793623
A28: L53 | B28: 17425-5 | C28: BOZZANO DES ANTI ANTBAC FRESH 12X90G NVF | D28: 1962331 | E28: =_xlfn.XLOOKUP(D28,'COHVPI DATAS REALIZADAS'!C:C,'COHVPI DATAS REALIZADAS'!N:N,0,0,1) -> 46151 | F28: =_xlfn.XLOOKUP(D28,'COHVPI DATAS REALIZADAS'!C:C,'COHVPI DATAS REALIZADAS'!O:O,0,0,1) -> 46155 | G28: =_xlfn.XLOOKUP(D28,COHVPI!A:A,COHVPI!E:E,0,0,1) -> 22299 | H28: =_xlfn.XLOOKUP(D28,COHVPI!A:A,COHVPI!F:F,0,0,1) -> 21952 | I28: =H28/G28 -> 0.98443876 | L28: 27213-1 | M28: MONANGE DES ANTIT INVIS 12X200ML MT | N28: 11238 | O28: 11560 | P28: =O28/N28 -> 1.0286528 | R28: 27212-1 | S28: MONANGE DES ANTIT FR VM 12X200ML MT | T28: 27875 | U28: 27245 | V28: 0.9773991
A29: L53 | B29: 17425-5 | C29: BOZZANO DES ANTI ANTBAC FRESH 12X90G NVF | D29: 1962332 | E29: =_xlfn.XLOOKUP(D29,'COHVPI DATAS REALIZADAS'!C:C,'COHVPI DATAS REALIZADAS'!N:N,0,0,1) -> 46154 | F29: =_xlfn.XLOOKUP(D29,'COHVPI DATAS REALIZADAS'!C:C,'COHVPI DATAS REALIZADAS'!O:O,0,0,1) -> 46156 | G29: =_xlfn.XLOOKUP(D29,COHVPI!A:A,COHVPI!E:E,0,0,1) -> 14866 | H29: =_xlfn.XLOOKUP(D29,COHVPI!A:A,COHVPI!F:F,0,0,1) -> 14852 | I29: =H29/G29 -> 0.99905825 | L29: 27214-0 | M29: BOZZANO DES ANTI EXTREME SPORT 12X200ML | N29: 33450 | O29: 32974 | P29: =O29/N29 -> 0.98576981 | R29: 17111-6 | S29: MONANGE DES ANTI HIDR INTEN 12X90G NVF | T29: 14866 | U29: 14517 | V29: 0.97652361
A30: L53 | B30: 25004-1 | C30: BOZZANO DES ANTI CARVAO 12X90G NVF | D30: 1962333 | E30: =_xlfn.XLOOKUP(D30,'COHVPI DATAS REALIZADAS'!C:C,'COHVPI DATAS REALIZADAS'!N:N,0,0,1) -> 46156 | F30: =_xlfn.XLOOKUP(D30,'COHVPI DATAS REALIZADAS'!C:C,'COHVPI DATAS REALIZADAS'!O:O,0,0,1) -> 46157 | G30: =_xlfn.XLOOKUP(D30,COHVPI!A:A,COHVPI!E:E,0,0,1) -> 22299 | H30: =_xlfn.XLOOKUP(D30,COHVPI!A:A,COHVPI!F:F,0,0,1) -> 22080 | I30: =H30/G30 -> 0.99017893 | L30: 29553-0 | M30: BOZZANO DES ANTIT DRY 12X200ML | N30: 33450 | O30: 32935 | P30: =O30/N30 -> 0.98460389 | R30: 24631-2 | S30: MONANGE DES ANTIT PROT SEC 12X90G MT | T30: 66897 | U30: 65121 | V30: 0.97345172
A31: L53 | B31: 25004-1 | C31: BOZZANO DES ANTI CARVAO 12X90G NVF | D31: 1962334 | E31: =_xlfn.XLOOKUP(D31,'COHVPI DATAS REALIZADAS'!C:C,'COHVPI DATAS REALIZADAS'!N:N,0,0,1) -> 46157 | F31: =_xlfn.XLOOKUP(D31,'COHVPI DATAS REALIZADAS'!C:C,'COHVPI DATAS REALIZADAS'!O:O,0,0,1) -> 46159 | G31: =_xlfn.XLOOKUP(D31,COHVPI!A:A,COHVPI!E:E,0,0,1) -> 14866 | H31: =_xlfn.XLOOKUP(D31,COHVPI!A:A,COHVPI!F:F,0,0,1) -> 14400 | I31: =H31/G31 -> 0.9686533 | L31: 29554-0 | M31: BOZZANO DES ANTIT ANTIBAC FRESH 12X200ML | N31: 44600 | O31: 44460 | P31: =O31/N31 -> 0.99686099 | R31: 10909-3 | S31: BOZZANO ESPUMA BARBA REFRES 6X193G CIN | T31: 13330 | U31: 12971 | V31: 0.97306827
A32: L53 | B32: 25004-1 | C32: BOZZANO DES ANTI CARVAO 12X90G NVF | D32: 1962335 | E32: =_xlfn.XLOOKUP(D32,'COHVPI DATAS REALIZADAS'!C:C,'COHVPI DATAS REALIZADAS'!N:N,0,0,1) -> 46159 | F32: =_xlfn.XLOOKUP(D32,'COHVPI DATAS REALIZADAS'!C:C,'COHVPI DATAS REALIZADAS'!O:O,0,0,1) -> 46161 | G32: =_xlfn.XLOOKUP(D32,COHVPI!A:A,COHVPI!E:E,0,0,1) -> 14866 | H32: =_xlfn.XLOOKUP(D32,COHVPI!A:A,COHVPI!F:F,0,0,1) -> 14842 | I32: =H32/G32 -> 0.99838558 | L32: 29555-1 | M32: MONANGE DES ANTIT PROT SEC 12X200ML MT | N32: 11150 | O32: 10931 | P32: =O32/N32 -> 0.98035874 | R32: 25003-1 | S32: BOZZANO DES ANTI DRY 12X90G NVF | T32: 7433 | U32: 7229 | V32: 0.97255482
A33: L53 | B33: 13441-6 | C33: BOZZANO DES ANTI S PERF SENS 12X90G NVF | D33: 1962336 | E33: =_xlfn.XLOOKUP(D33,'COHVPI DATAS REALIZADAS'!C:C,'COHVPI DATAS REALIZADAS'!N:N,0,0,1) -> 46161 | F33: =_xlfn.XLOOKUP(D33,'COHVPI DATAS REALIZADAS'!C:C,'COHVPI DATAS REALIZADAS'!O:O,0,0,1) -> 46163 | G33: =_xlfn.XLOOKUP(D33,COHVPI!A:A,COHVPI!E:E,0,0,1) -> 21237 | H33: =_xlfn.XLOOKUP(D33,COHVPI!A:A,COHVPI!F:F,0,0,1) -> 22010 | I33: =H33/G33 -> 1.0363987 | L33: 8627-4 | M33: TRES MARCHAND DES ANTI CLASS 12X90G NVF | N33: 6457 | O33: 7132 | P33: =O33/N33 -> 1.1045377 | R33: 25644-0 | S33: BOZZANO CLINICAL CLEAN AERO 12X94G | T33: 8488 | U33: 8160 | V33: 0.96135721
A34: L53 | B34: 25003-1 | C34: BOZZANO DES ANTI DRY 12X90G NVF | D34: 1962770 | E34: =_xlfn.XLOOKUP(D34,'COHVPI DATAS REALIZADAS'!C:C,'COHVPI DATAS REALIZADAS'!N:N,0,0,1) -> 46163 | F34: =_xlfn.XLOOKUP(D34,'COHVPI DATAS REALIZADAS'!C:C,'COHVPI DATAS REALIZADAS'!O:O,0,0,1) -> 46164 | G34: =_xlfn.XLOOKUP(D34,COHVPI!A:A,COHVPI!E:E,0,0,1) -> 7433 | H34: =_xlfn.XLOOKUP(D34,COHVPI!A:A,COHVPI!F:F,0,0,1) -> 7229 | I34: =H34/G34 -> 0.97255482 | L34: Total Geral | N34: 1209384.5 | O34: 1206754 | P34: =O34/N34 -> 0.99782493 | R34: Total Geral | T34: 1209384.5 | U34: 1206754 | V34: 0.99782493
A35: L53 | B35: 25645-0 | C35: BOZZANO CLINIC ULTRA COOL AERO 12X94G | D35: 1962340 | E35: =_xlfn.XLOOKUP(D35,'COHVPI DATAS REALIZADAS'!C:C,'COHVPI DATAS REALIZADAS'!N:N,0,0,1) -> 46164 | F35: =_xlfn.XLOOKUP(D35,'COHVPI DATAS REALIZADAS'!C:C,'COHVPI DATAS REALIZADAS'!O:O,0,0,1) -> 46165 | G35: =_xlfn.XLOOKUP(D35,COHVPI!A:A,COHVPI!E:E,0,0,1) -> 8488 | H35: =_xlfn.XLOOKUP(D35,COHVPI!A:A,COHVPI!F:F,0,0,1) -> 8457 | I35: =H35/G35 -> 0.99634779
A36: L53 | B36: 17111-7 | C36: MONANGE DES ANTIT HIDR INTEN 12X90G MT | D36: 1962764 | E36: =_xlfn.XLOOKUP(D36,'COHVPI DATAS REALIZADAS'!C:C,'COHVPI DATAS REALIZADAS'!N:N,0,0,1) -> 46165 | F36: =_xlfn.XLOOKUP(D36,'COHVPI DATAS REALIZADAS'!C:C,'COHVPI DATAS REALIZADAS'!O:O,0,0,1) -> 46168 | G36: =_xlfn.XLOOKUP(D36,COHVPI!A:A,COHVPI!E:E,0,0,1) -> 14866 | H36: =_xlfn.XLOOKUP(D36,COHVPI!A:A,COHVPI!F:F,0,0,1) -> 14321 | I36: =H36/G36 -> 0.96333916
A37: L53 | B37: 17111-7 | C37: MONANGE DES ANTIT HIDR INTEN 12X90G MT | D37: 1962765 | E37: =_xlfn.XLOOKUP(D37,'COHVPI DATAS REALIZADAS'!C:C,'COHVPI DATAS REALIZADAS'!N:N,0,0,1) -> 46168 | F37: =_xlfn.XLOOKUP(D37,'COHVPI DATAS REALIZADAS'!C:C,'COHVPI DATAS REALIZADAS'!O:O,0,0,1) -> 46169 | G37: =_xlfn.XLOOKUP(D37,COHVPI!A:A,COHVPI!E:E,0,0,1) -> 14866 | H37: =_xlfn.XLOOKUP(D37,COHVPI!A:A,COHVPI!F:F,0,0,1) -> 14584 | I37: =H37/G37 -> 0.98103054
A38: L53 | B38: 24630-2 | C38: MONANGE DES ANTIT DETOX FRESH 12X90G MT | D38: 1963817 | E38: =_xlfn.XLOOKUP(D38,'COHVPI DATAS REALIZADAS'!C:C,'COHVPI DATAS REALIZADAS'!N:N,0,0,1) -> 46169 | F38: =_xlfn.XLOOKUP(D38,'COHVPI DATAS REALIZADAS'!C:C,'COHVPI DATAS REALIZADAS'!O:O,0,0,1) -> 46170 | G38: =_xlfn.XLOOKUP(D38,COHVPI!A:A,COHVPI!E:E,0,0,1) -> 7433 | H38: =_xlfn.XLOOKUP(D38,COHVPI!A:A,COHVPI!F:F,0,0,1) -> 7311 | I38: =H38/G38 -> 0.98358671
A39: L53 | B39: 23209-5 | C39: ADIDAS DES ANTI PRO INVISIBLE MASC 150ML | D39: 1962342 | E39: =_xlfn.XLOOKUP(D39,'COHVPI DATAS REALIZADAS'!C:C,'COHVPI DATAS REALIZADAS'!N:N,0,0,1) -> 46170 | F39: =_xlfn.XLOOKUP(D39,'COHVPI DATAS REALIZADAS'!C:C,'COHVPI DATAS REALIZADAS'!O:O,0,0,1) -> 46172 | G39: =_xlfn.XLOOKUP(D39,COHVPI!A:A,COHVPI!E:E,0,0,1) -> 15026 | H39: =_xlfn.XLOOKUP(D39,COHVPI!A:A,COHVPI!F:F,0,0,1) -> 14980 | I39: =H39/G39 -> 0.99693864
A40: TOTAL L53 | G40: =SUM(G22:G39) -> 245088 | H40: =SUM(H22:H39) -> 242976 | I40: =H40/G40 -> 0.99138269
A41: L57 | B41: 29554-0 | C41: BOZZANO DES ANTIT ANTIBAC FRESH 12X200ML | D41: 1957946 | E41: =_xlfn.XLOOKUP(D41,'COHVPI DATAS REALIZADAS'!C:C,'COHVPI DATAS REALIZADAS'!N:N,0,0,1) -> 0 | F41: =_xlfn.XLOOKUP(D41,'COHVPI DATAS REALIZADAS'!C:C,'COHVPI DATAS REALIZADAS'!O:O,0,0,1) -> 0 | G41: =_xlfn.XLOOKUP(D41,COHVPI!A:A,COHVPI!E:E,0,0,1) -> 0 | H41: =_xlfn.XLOOKUP(D41,COHVPI!A:A,COHVPI!F:F,0,0,1) -> 0 | I41: =H41/G41 -> #DIV/0!
A42: L57 | B42: 29553-0 | C42: BOZZANO DES ANTIT DRY 12X200ML | D42: 1957965 | E42: =_xlfn.XLOOKUP(D42,'COHVPI DATAS REALIZADAS'!C:C,'COHVPI DATAS REALIZADAS'!N:N,0,0,1) -> 46143 | F42: =_xlfn.XLOOKUP(D42,'COHVPI DATAS REALIZADAS'!C:C,'COHVPI DATAS REALIZADAS'!O:O,0,0,1) -> 46146 | G42: =_xlfn.XLOOKUP(D42,COHVPI!A:A,COHVPI!E:E,0,0,1) -> 11150 | H42: =_xlfn.XLOOKUP(D42,COHVPI!A:A,COHVPI!F:F,0,0,1) -> 11160 | I42: =H42/G42 -> 1.0008969
A43: L57 | B43: 27211-1 | C43: MONANGE DES ANTIT HIDR INTEN 12X200ML MT | D43: 1957949 | E43: =_xlfn.XLOOKUP(D43,'COHVPI DATAS REALIZADAS'!C:C,'COHVPI DATAS REALIZADAS'!N:N,0,0,1) -> 46146 | F43: =_xlfn.XLOOKUP(D43,'COHVPI DATAS REALIZADAS'!C:C,'COHVPI DATAS REALIZADAS'!O:O,0,0,1) -> 46147 | G43: =_xlfn.XLOOKUP(D43,COHVPI!A:A,COHVPI!E:E,0,0,1) -> 11150 | H43: =_xlfn.XLOOKUP(D43,COHVPI!A:A,COHVPI!F:F,0,0,1) -> 11000 | I43: =H43/G43 -> 0.98654709
A44: L57 | B44: 27211-1 | C44: MONANGE DES ANTIT HIDR INTEN 12X200ML MT | D44: 1957953 | E44: =_xlfn.XLOOKUP(D44,'COHVPI DATAS REALIZADAS'!C:C,'COHVPI DATAS REALIZADAS'!N:N,0,0,1) -> 46147 | F44: =_xlfn.XLOOKUP(D44,'COHVPI DATAS REALIZADAS'!C:C,'COHVPI DATAS REALIZADAS'!O:O,0,0,1) -> 46148 | G44: =_xlfn.XLOOKUP(D44,COHVPI!A:A,COHVPI!E:E,0,0,1) -> 11150 | H44: =_xlfn.XLOOKUP(D44,COHVPI!A:A,COHVPI!F:F,0,0,1) -> 11400 | I44: =H44/G44 -> 1.0224215
A45: L57 | B45: 27211-1 | C45: MONANGE DES ANTIT HIDR INTEN 12X200ML MT | D45: 1960551 | E45: =_xlfn.XLOOKUP(D45,'COHVPI DATAS REALIZADAS'!C:C,'COHVPI DATAS REALIZADAS'!N:N,0,0,1) -> 46148 | F45: =_xlfn.XLOOKUP(D45,'COHVPI DATAS REALIZADAS'!C:C,'COHVPI DATAS REALIZADAS'!O:O,0,0,1) -> 46150 | G45: =_xlfn.XLOOKUP(D45,COHVPI!A:A,COHVPI!E:E,0,0,1) -> 16725 | H45: =_xlfn.XLOOKUP(D45,COHVPI!A:A,COHVPI!F:F,0,0,1) -> 15800 | I45: =H45/G45 -> 0.94469357
A46: L57 | B46: 27211-1 | C46: MONANGE DES ANTIT HIDR INTEN 12X200ML MT | D46: 1960552 | E46: =_xlfn.XLOOKUP(D46,'COHVPI DATAS REALIZADAS'!C:C,'COHVPI DATAS REALIZADAS'!N:N,0,0,1) -> 46150 | F46: =_xlfn.XLOOKUP(D46,'COHVPI DATAS REALIZADAS'!C:C,'COHVPI DATAS REALIZADAS'!O:O,0,0,1) -> 46151 | G46: =_xlfn.XLOOKUP(D46,COHVPI!A:A,COHVPI!E:E,0,0,1) -> 11150 | H46: =_xlfn.XLOOKUP(D46,COHVPI!A:A,COHVPI!F:F,0,0,1) -> 11277 | I46: =H46/G46 -> 1.0113901
A47: L57 | B47: 27214-0 | C47: BOZZANO DES ANTI EXTREME SPORT 12X200ML | D47: 1960554 | E47: =_xlfn.XLOOKUP(D47,'COHVPI DATAS REALIZADAS'!C:C,'COHVPI DATAS REALIZADAS'!N:N,0,0,1) -> 46151 | F47: =_xlfn.XLOOKUP(D47,'COHVPI DATAS REALIZADAS'!C:C,'COHVPI DATAS REALIZADAS'!O:O,0,0,1) -> 46153 | G47: =_xlfn.XLOOKUP(D47,COHVPI!A:A,COHVPI!E:E,0,0,1) -> 16725 | H47: =_xlfn.XLOOKUP(D47,COHVPI!A:A,COHVPI!F:F,0,0,1) -> 16519 | I47: =H47/G47 -> 0.98768311
A48: L57 | B48: 27211-0 | C48: MONANGE DES ANTI HIDR INTENSIVA 12X200ML | D48: 1962534 | E48: =_xlfn.XLOOKUP(D48,'COHVPI DATAS REALIZADAS'!C:C,'COHVPI DATAS REALIZADAS'!N:N,0,0,1) -> 46153 | F48: =_xlfn.XLOOKUP(D48,'COHVPI DATAS REALIZADAS'!C:C,'COHVPI DATAS REALIZADAS'!O:O,0,0,1) -> 46154 | G48: =_xlfn.XLOOKUP(D48,COHVPI!A:A,COHVPI!E:E,0,0,1) -> 5309 | H48: =_xlfn.XLOOKUP(D48,COHVPI!A:A,COHVPI!F:F,0,0,1) -> 5370 | I48: =H48/G48 -> 1.0114899
A49: L57 | B49: 27212-0 | C49: MONANGE DES ANTI FR VERMELHAS 12X200ML | D49: 1962350 | E49: =_xlfn.XLOOKUP(D49,'COHVPI DATAS REALIZADAS'!C:C,'COHVPI DATAS REALIZADAS'!N:N,0,0,1) -> 46154 | F49: =_xlfn.XLOOKUP(D49,'COHVPI DATAS REALIZADAS'!C:C,'COHVPI DATAS REALIZADAS'!O:O,0,0,1) -> 46155 | G49: =_xlfn.XLOOKUP(D49,COHVPI!A:A,COHVPI!E:E,0,0,1) -> 5574.5 | H49: =_xlfn.XLOOKUP(D49,COHVPI!A:A,COHVPI!F:F,0,0,1) -> 5555 | I49: =H49/G49 -> 0.99650193
A50: L57 | B50: 29553-0 | C50: BOZZANO DES ANTIT DRY 12X200ML | D50: 1960562 | E50: =_xlfn.XLOOKUP(D50,'COHVPI DATAS REALIZADAS'!C:C,'COHVPI DATAS REALIZADAS'!N:N,0,0,1) -> 46154 | F50: =_xlfn.XLOOKUP(D50,'COHVPI DATAS REALIZADAS'!C:C,'COHVPI DATAS REALIZADAS'!O:O,0,0,1) -> 46155 | G50: =_xlfn.XLOOKUP(D50,COHVPI!A:A,COHVPI!E:E,0,0,1) -> 11150 | H50: =_xlfn.XLOOKUP(D50,COHVPI!A:A,COHVPI!F:F,0,0,1) -> 11000 | I50: =H50/G50 -> 0.98654709
A51: L57 | B51: 29553-0 | C51: BOZZANO DES ANTIT DRY 12X200ML | D51: 1960563 | E51: =_xlfn.XLOOKUP(D51,'COHVPI DATAS REALIZADAS'!C:C,'COHVPI DATAS REALIZADAS'!N:N,0,0,1) -> 46155 | F51: =_xlfn.XLOOKUP(D51,'COHVPI DATAS REALIZADAS'!C:C,'COHVPI DATAS REALIZADAS'!O:O,0,0,1) -> 46156 | G51: =_xlfn.XLOOKUP(D51,COHVPI!A:A,COHVPI!E:E,0,0,1) -> 11150 | H51: =_xlfn.XLOOKUP(D51,COHVPI!A:A,COHVPI!F:F,0,0,1) -> 10775 | I51: =H51/G51 -> 0.96636771
A52: L57 | B52: 27214-0 | C52: BOZZANO DES ANTI EXTREME SPORT 12X200ML | D52: 1960555 | E52: =_xlfn.XLOOKUP(D52,'COHVPI DATAS REALIZADAS'!C:C,'COHVPI DATAS REALIZADAS'!N:N,0,0,1) -> 46156 | F52: =_xlfn.XLOOKUP(D52,'COHVPI DATAS REALIZADAS'!C:C,'COHVPI DATAS REALIZADAS'!O:O,0,0,1) -> 46158 | G52: =_xlfn.XLOOKUP(D52,COHVPI!A:A,COHVPI!E:E,0,0,1) -> 16725 | H52: =_xlfn.XLOOKUP(D52,COHVPI!A:A,COHVPI!F:F,0,0,1) -> 16455 | I52: =H52/G52 -> 0.9838565
... A61: L57 | B61: 10909-3 | C61: BOZZANO ESPUMA BARBA REFRES 6X193G CIN | D61: 1962782 | E61: =_xlfn.XLOOKUP(D61,'COHVPI DATAS REALIZADAS'!C:C,'COHVPI DATAS REALIZADAS'!N:N,0,0,1) -> 46171 | F61: =_xlfn.XLOOKUP(D61,'COHVPI DATAS REALIZADAS'!C:C,'COHVPI DATAS REALIZADAS'!O:O,0,0,1) -> 46173 | G61: =_xlfn.XLOOKUP(D61,COHVPI!A:A,COHVPI!E:E,0,0,1) -> 5332 | H61: =_xlfn.XLOOKUP(D61,COHVPI!A:A,COHVPI!F:F,0,0,1) -> 5478 | I61: =H61/G61 -> 1.0273818
A62: TOTAL L57 | G62: =SUM(G41:G61) -> 225001.5 | H62: =SUM(H41:H61) -> 222158 | I62: =H62/G62 -> 0.98736231
A63: L58 | B63: 24630-2 | C63: MONANGE DES ANTIT DETOX FRESH 12X90G MT | D63: 1959443 | E63: =_xlfn.XLOOKUP(D63,'COHVPI DATAS REALIZADAS'!C:C,'COHVPI DATAS REALIZADAS'!N:N,0,0,1) -> 0 | F63: =_xlfn.XLOOKUP(D63,'COHVPI DATAS REALIZADAS'!C:C,'COHVPI DATAS REALIZADAS'!O:O,0,0,1) -> 0 | G63: =_xlfn.XLOOKUP(D63,COHVPI!A:A,COHVPI!E:E,0,0,1) -> 0 | H63: =_xlfn.XLOOKUP(D63,COHVPI!A:A,COHVPI!F:F,0,0,1) -> 0 | I63: =H63/G63 -> #DIV/0!
A64: L58 | B64: 24630-2 | C64: MONANGE DES ANTIT DETOX FRESH 12X90G MT | D64: 1960798 | E64: =_xlfn.XLOOKUP(D64,'COHVPI DATAS REALIZADAS'!C:C,'COHVPI DATAS REALIZADAS'!N:N,0,0,1) -> 46144 | F64: =_xlfn.XLOOKUP(D64,'COHVPI DATAS REALIZADAS'!C:C,'COHVPI DATAS REALIZADAS'!O:O,0,0,1) -> 46147 | G64: =_xlfn.XLOOKUP(D64,COHVPI!A:A,COHVPI!E:E,0,0,1) -> 22299 | H64: =_xlfn.XLOOKUP(D64,COHVPI!A:A,COHVPI!F:F,0,0,1) -> 22138 | I64: =H64/G64 -> 0.99277995
A65: L58 | B65: 17111-7 | C65: MONANGE DES ANTIT HIDR INTEN 12X90G MT | D65: 1960572 | E65: =_xlfn.XLOOKUP(D65,'COHVPI DATAS REALIZADAS'!C:C,'COHVPI DATAS REALIZADAS'!N:N,0,0,1) -> 46147 | F65: =_xlfn.XLOOKUP(D65,'COHVPI DATAS REALIZADAS'!C:C,'COHVPI DATAS REALIZADAS'!O:O,0,0,1) -> 46148 | G65: =_xlfn.XLOOKUP(D65,COHVPI!A:A,COHVPI!E:E,0,0,1) -> 22299 | H65: =_xlfn.XLOOKUP(D65,COHVPI!A:A,COHVPI!F:F,0,0,1) -> 22320 | I65: =H65/G65 -> 1.0009417
A66: L58 | B66: 17111-7 | C66: MONANGE DES ANTIT HIDR INTEN 12X90G MT | D66: 1960573 | E66: =_xlfn.XLOOKUP(D66,'COHVPI DATAS REALIZADAS'!C:C,'COHVPI DATAS REALIZADAS'!N:N,0,0,1) -> 46148 | F66: =_xlfn.XLOOKUP(D66,'COHVPI DATAS REALIZADAS'!C:C,'COHVPI DATAS REALIZADAS'!O:O,0,0,1) -> 46149 | G66: =_xlfn.XLOOKUP(D66,COHVPI!A:A,COHVPI!E:E,0,0,1) -> 22299 | H66: =_xlfn.XLOOKUP(D66,COHVPI!A:A,COHVPI!F:F,0,0,1) -> 22080 | I66: =H66/G66 -> 0.99017893
A67: L58 | B67: 17111-7 | C67: MONANGE DES ANTIT HIDR INTEN 12X90G MT | D67: 1960574 | E67: =_xlfn.XLOOKUP(D67,'COHVPI DATAS REALIZADAS'!C:C,'COHVPI DATAS REALIZADAS'!N:N,0,0,1) -> 46149 | F67: =_xlfn.XLOOKUP(D67,'COHVPI DATAS REALIZADAS'!C:C,'COHVPI DATAS REALIZADAS'!O:O,0,0,1) -> 46151 | G67: =_xlfn.XLOOKUP(D67,COHVPI!A:A,COHVPI!E:E,0,0,1) -> 22299 | H67: =_xlfn.XLOOKUP(D67,COHVPI!A:A,COHVPI!F:F,0,0,1) -> 22703 | I67: =H67/G67 -> 1.0181174
A68: L58 | B68: 17111-7 | C68: MONANGE DES ANTIT HIDR INTEN 12X90G MT | D68: 1960575 | E68: =_xlfn.XLOOKUP(D68,'COHVPI DATAS REALIZADAS'!C:C,'COHVPI DATAS REALIZADAS'!N:N,0,0,1) -> 46151 | F68: =_xlfn.XLOOKUP(D68,'COHVPI DATAS REALIZADAS'!C:C,'COHVPI DATAS REALIZADAS'!O:O,0,0,1) -> 46154 | G68: =_xlfn.XLOOKUP(D68,COHVPI!A:A,COHVPI!E:E,0,0,1) -> 22299 | H68: =_xlfn.XLOOKUP(D68,COHVPI!A:A,COHVPI!F:F,0,0,1) -> 22985 | I68: =H68/G68 -> 1.0307637
A69: L58 | B69: 20257-4 | C69: MONANGE DES ANTIT INVISL 12X89G MT | D69: 1962363 | E69: =_xlfn.XLOOKUP(D69,'COHVPI DATAS REALIZADAS'!C:C,'COHVPI DATAS REALIZADAS'!N:N,0,0,1) -> 46153 | F69: =_xlfn.XLOOKUP(D69,'COHVPI DATAS REALIZADAS'!C:C,'COHVPI DATAS REALIZADAS'!O:O,0,0,1) -> 46155 | G69: =_xlfn.XLOOKUP(D69,COHVPI!A:A,COHVPI!E:E,0,0,1) -> 22539 | H69: =_xlfn.XLOOKUP(D69,COHVPI!A:A,COHVPI!F:F,0,0,1) -> 23040 | I69: =H69/G69 -> 1.0222281
A70: L58 | B70: 20257-4 | C70: MONANGE DES ANTIT INVISL 12X89G MT | D70: 1962364 | E70: =_xlfn.XLOOKUP(D70,'COHVPI DATAS REALIZADAS'!C:C,'COHVPI DATAS REALIZADAS'!N:N,0,0,1) -> 46155 | F70: =_xlfn.XLOOKUP(D70,'COHVPI DATAS REALIZADAS'!C:C,'COHVPI DATAS REALIZADAS'!O:O,0,0,1) -> 46156 | G70: =_xlfn.XLOOKUP(D70,COHVPI!A:A,COHVPI!E:E,0,0,1) -> 22539 | H70: =_xlfn.XLOOKUP(D70,COHVPI!A:A,COHVPI!F:F,0,0,1) -> 23040 | I70: =H70/G70 -> 1.0222281
A71: L58 | B71: 20257-4 | C71: MONANGE DES ANTIT INVISL 12X89G MT | D71: 1962365 | E71: =_xlfn.XLOOKUP(D71,'COHVPI DATAS REALIZADAS'!C:C,'COHVPI DATAS REALIZADAS'!N:N,0,0,1) -> 46156 | F71: =_xlfn.XLOOKUP(D71,'COHVPI DATAS REALIZADAS'!C:C,'COHVPI DATAS REALIZADAS'!O:O,0,0,1) -> 46157 | G71: =_xlfn.XLOOKUP(D71,COHVPI!A:A,COHVPI!E:E,0,0,1) -> 22539 | H71: =_xlfn.XLOOKUP(D71,COHVPI!A:A,COHVPI!F:F,0,0,1) -> 23040 | I71: =H71/G71 -> 1.0222281
A72: L58 | B72: 20257-4 | C72: MONANGE DES ANTIT INVISL 12X89G MT | D72: 1962366 | E72: =_xlfn.XLOOKUP(D72,'COHVPI DATAS REALIZADAS'!C:C,'COHVPI DATAS REALIZADAS'!N:N,0,0,1) -> 46157 | F72: =_xlfn.XLOOKUP(D72,'COHVPI DATAS REALIZADAS'!C:C,'COHVPI DATAS REALIZADAS'!O:O,0,0,1) -> 46158 | G72: =_xlfn.XLOOKUP(D72,COHVPI!A:A,COHVPI!E:E,0,0,1) -> 22539 | H72: =_xlfn.XLOOKUP(D72,COHVPI!A:A,COHVPI!F:F,0,0,1) -> 23485 | I72: =H72/G72 -> 1.0419717
A73: L58 | B73: 17111-7 | C73: MONANGE DES ANTIT HIDR INTEN 12X90G MT | D73: 1962367 | E73: =_xlfn.XLOOKUP(D73,'COHVPI DATAS REALIZADAS'!C:C,'COHVPI DATAS REALIZADAS'!N:N,0,0,1) -> 46158 | F73: =_xlfn.XLOOKUP(D73,'COHVPI DATAS REALIZADAS'!C:C,'COHVPI DATAS REALIZADAS'!O:O,0,0,1) -> 46161 | G73: =_xlfn.XLOOKUP(D73,COHVPI!A:A,COHVPI!E:E,0,0,1) -> 22299 | H73: =_xlfn.XLOOKUP(D73,COHVPI!A:A,COHVPI!F:F,0,0,1) -> 22414 | I73: =H73/G73 -> 1.0051572
A74: L58 | B74: 17111-7 | C74: MONANGE DES ANTIT HIDR INTEN 12X90G MT | D74: 1962368 | E74: =_xlfn.XLOOKUP(D74,'COHVPI DATAS REALIZADAS'!C:C,'COHVPI DATAS REALIZADAS'!N:N,0,0,1) -> 46161 | F74: =_xlfn.XLOOKUP(D74,'COHVPI DATAS REALIZADAS'!C:C,'COHVPI DATAS REALIZADAS'!O:O,0,0,1) -> 46162 | G74: =_xlfn.XLOOKUP(D74,COHVPI!A:A,COHVPI!E:E,0,0,1) -> 22299 | H74: =_xlfn.XLOOKUP(D74,COHVPI!A:A,COHVPI!F:F,0,0,1) -> 22830 | I74: =H74/G74 -> 1.0238127
... A82: L58 | B82: 17110-8 | C82: MONANGE DES ANTIT FRTS VM 12X90G MT | D82: 1962376 | E82: =_xlfn.XLOOKUP(D82,'COHVPI DATAS REALIZADAS'!C:C,'COHVPI DATAS REALIZADAS'!N:N,0,0,1) -> 46172 | F82: =_xlfn.XLOOKUP(D82,'COHVPI DATAS REALIZADAS'!C:C,'COHVPI DATAS REALIZADAS'!O:O,0,0,1) -> 46173 | G82: =_xlfn.XLOOKUP(D82,COHVPI!A:A,COHVPI!E:E,0,0,1) -> 14866 | H82: =_xlfn.XLOOKUP(D82,COHVPI!A:A,COHVPI!F:F,0,0,1) -> 15120 | I82: =H82/G82 -> 1.017086
A83: TOTAL L58 | G83: =SUM(G63:G82) -> 409775 | H83: =SUM(H63:H82) -> 414808 | I83: =H83/G83 -> 1.0122824

Sheet Envase
B2: LINHA 40 AEROSSOL (FABRICAÇÃO 1000KG a 1200KG) | O2: =_xlfn.XLOOKUP(R2,PROCX!A:A,PROCX!H:H,"-",0,1) -> - | P2: LINHA 40 ENVASE AEROSSOL
B3: ORDEM | C3: LOTE | D3: QTD (KG) | E3: QTD | F3: CÓDIGO | G3: DESCRIÇÃO S.A | H3: Data Congelada | I3: DATA ENVASE | J3: A | K3: B | L3: C | M3: STATUS | O3: =_xlfn.XLOOKUP(R3,PROCX!A:A,PROCX!H:H,"-",0,1) -> UM básica (=EINHEIT) | P3: CÓDIGO | Q3: DESCRIÇÃO P.A | R3: ORDEM | S3: LINHA | T3: QTD Produzida (CX) | U3: QTD Programada (CX) | V3: QTD SAP (CX) | W3: RENDIMENTO (%) | X3: QTD (UN) | Y3: Obs
B4: 1957843 | C4: T26C1875 | D4: 1200 | F4: 466770 | G4: SA MONANGE DES ANTI INVISIVEL FRAG RET | I4: 46127 | M4: - | O4: =_xlfn.XLOOKUP(R4,PROCX!A:A,PROCX!H:H,"-",0,1) -> - | P4: 20257-3 | Q4: MONANGE DES ANTI INVISIVEL 12X89G NVF | R4: 1957943 | S4: =_xlfn.XLOOKUP(R4,'VERSÃO DE PROD'!B:B,'VERSÃO DE PROD'!A:A,0,0,1) -> 0 | T4: =SUMIF(COHVPI!A:A,Envase!R4,COHVPI!F:F) -> 0 | U4: =X4/12 -> 15026 | W4: =T4/U4 -> 0 | X4: =90156*2 -> 180312 | Y4: OK
B5: 1957845 | C5: T26C1877 | D5: 1200 | F5: 466770 | G5: SA MONANGE DES ANTI INVISIVEL FRAG RET | I5: 46128 | M5: - | O5: =_xlfn.XLOOKUP(R5,PROCX!A:A,PROCX!H:H,"-",0,1) -> 0
B6: 1957813 | C6: T26C1845 | D6: 1200 | F6: 462830 | G6: SA MONANGE DES ANTI ESPORTE NVF | I6: 46128 | M6: FALTA VÁLVULA 468257 | O6: =_xlfn.XLOOKUP(R6,PROCX!A:A,PROCX!H:H,"-",0,1) -> - | P6: 25503-0 | Q6: MONANGE DES ANTI ESPORTE AERO 12X90G | R6: 1957928 | S6: =_xlfn.XLOOKUP(R6,'VERSÃO DE PROD'!B:B,'VERSÃO DE PROD'!A:A,0,0,1) -> 0 | T6: =SUMIF(COHVPI!A:A,Envase!R6,COHVPI!F:F) -> 0 | U6: =X6/12 -> 14158 | W6: =T6/U6 -> 0 | X6: =84948*2 -> 169896 | Y6: OK
B7: 1957814 | C7: T26C1846 | D7: 1200 | F7: 462830 | G7: SA MONANGE DES ANTI ESPORTE NVF | I7: 46129 | M7: FALTA VÁLVULA 468257 | O7: =_xlfn.XLOOKUP(R7,PROCX!A:A,PROCX!H:H,"-",0,1) -> 0
B8: 1957815 | C8: T26C1847 | D8: 1200 | F8: 462830 | G8: SA MONANGE DES ANTI ESPORTE NVF | I8: 46129 | M8: FALTA VÁLVULA 468257 | O8: =_xlfn.XLOOKUP(R8,PROCX!A:A,PROCX!H:H,"-",0,1) -> - | P8: 25503-0 | Q8: MONANGE DES ANTI ESPORTE AERO 12X90G | R8: 1957933 | S8: =_xlfn.XLOOKUP(R8,'VERSÃO DE PROD'!B:B,'VERSÃO DE PROD'!A:A,0,0,1) -> 0 | T8: =SUMIF(COHVPI!A:A,Envase!R8,COHVPI!F:F) -> 0 | U8: =X8/12 -> 14158 | W8: =T8/U8 -> 0 | X8: =84948*2 -> 169896 | Y8: OK
B9: 1957816 | C9: T26C1848 | D9: 1200 | F9: 462830 | G9: SA MONANGE DES ANTI ESPORTE NVF | I9: 46132 | M9: FALTA VÁLVULA 468257 E CAIXA 465371 | O9: =_xlfn.XLOOKUP(R9,PROCX!A:A,PROCX!H:H,"-",0,1) -> 0
B10: 1957817 | C10: T26C1849 | D10: 1200 | F10: 462830 | G10: SA MONANGE DES ANTI ESPORTE NVF | I10: 46132 | M10: FALTA VÁLVULA 468257 + CAIXA 465371 + TAMPA 453598 | O10: =_xlfn.XLOOKUP(R10,PROCX!A:A,PROCX!H:H,"-",0,1) -> - | P10: 25503-0 | Q10: MONANGE DES ANTI ESPORTE AERO 12X90G | R10: 1959151 | S10: =_xlfn.XLOOKUP(R10,'VERSÃO DE PROD'!B:B,'VERSÃO DE PROD'!A:A,0,0,1) -> 0 | T10: =SUMIF(COHVPI!A:A,Envase!R10,COHVPI!F:F) -> 0 | U10: =X10/12 -> 14158 | W10: =T10/U10 -> 0 | X10: =84948*2 -> 169896 | Y10: OK
B11: 1957818 | C11: T26C1850 | D11: 1200 | F11: 462830 | G11: SA MONANGE DES ANTI ESPORTE NVF | I11: 46133 | M11: FALTA VÁLVULA 468257 + CAIXA 465371 + TAMPA 453598 | O11: =_xlfn.XLOOKUP(R11,PROCX!A:A,PROCX!H:H,"-",0,1) -> 0
B12: 1957485 | C12: T26C1631 | D12: 1200 | F12: 462828 | G12: SA MONANGE DES ANTI DETOX FRESH NVF | I12: 46133 | M12: - | O12: =_xlfn.XLOOKUP(R12,PROCX!A:A,PROCX!H:H,"-",0,1) -> - | P12: 24630-1 | Q12: MONANGE DES ANTI DETOX FRESH 12X90G NVF | R12: 1957469 | S12: =_xlfn.XLOOKUP(R12,'VERSÃO DE PROD'!B:B,'VERSÃO DE PROD'!A:A,0,0,1) -> 0 | T12: =SUMIF(COHVPI!A:A,Envase!R12,COHVPI!F:F) -> 0 | U12: =X12/12 -> 22299 | W12: =T12/U12 -> 0 | X12: =89196*3 -> 267588 | Y12: OK
B13: 1957486 | C13: T26C1632 | D13: 1200 | F13: 462828 | G13: SA MONANGE DES ANTI DETOX FRESH NVF | I13: 46133 | M13: - | O13: =_xlfn.XLOOKUP(R13,PROCX!A:A,PROCX!H:H,"-",0,1) -> 0
B14: 1957487 | C14: T26C1633 | D14: 1200 | F14: 462828 | G14: SA MONANGE DES ANTI DETOX FRESH NVF | I14: 46135 | M14: - | O14: =_xlfn.XLOOKUP(R14,PROCX!A:A,PROCX!H:H,"-",0,1) -> 0
B15: 1957807 | C15: T26C1839 | D15: 1200 | F15: 462828 | G15: SA MONANGE DES ANTI DETOX FRESH NVF | I15: 46135 | M15: - | O15: =_xlfn.XLOOKUP(R15,PROCX!A:A,PROCX!H:H,"-",0,1) -> - | P15: 24630-1 | Q15: MONANGE DES ANTI DETOX FRESH 12X90G NVF | R15: 1957951 | S15: =_xlfn.XLOOKUP(R15,'VERSÃO DE PROD'!B:B,'VERSÃO DE PROD'!A:A,0,0,1) -> 0 | T15: =SUMIF(COHVPI!A:A,Envase!R15,COHVPI!F:F) -> 0 | U15: =X15/12 -> 14866 | W15: =T15/U15 -> 0 | X15: =89196*2 -> 178392 | Y15: OK
B16: 1957809 | C16: T26C1841 | D16: 1200 | F16: 462828 | G16: SA MONANGE DES ANTI DETOX FRESH NVF | I16: 46136 | M16: - | O16: =_xlfn.XLOOKUP(R16,PROCX!A:A,PROCX!H:H,"-",0,1) -> 0
B17: 1957810 | C17: T26C1842 | D17: 1200 | F17: 462828 | G17: SA MONANGE DES ANTI DETOX FRESH NVF | I17: 46136 | M17: - | O17: =_xlfn.XLOOKUP(R17,PROCX!A:A,PROCX!H:H,"-",0,1) -> - | P17: 24630-1 | Q17: MONANGE DES ANTI DETOX FRESH 12X90G NVF | R17: 1957956 | S17: =_xlfn.XLOOKUP(R17,'VERSÃO DE PROD'!B:B,'VERSÃO DE PROD'!A:A,0,0,1) -> 0 | T17: =SUMIF(COHVPI!A:A,Envase!R17,COHVPI!F:F) -> 0 | U17: =X17/12 -> 14866 | W17: =T17/U17 -> 0 | X17: =89196*2 -> 178392 | Y17: OK
B18: 1957811 | C18: T26C1843 | D18: 1200 | F18: 462828 | G18: SA MONANGE DES ANTI DETOX FRESH NVF | H18: 46139 | I18: 46139 | M18: - | O18: =_xlfn.XLOOKUP(R18,PROCX!A:A,PROCX!H:H,"-",0,1) -> 0
B19: SETUP | O19: =_xlfn.XLOOKUP(R19,PROCX!A:A,PROCX!H:H,"-",0,1) -> 0 | P19: SETUP
B20: RISCO DE PARADA - FALTA DE TAMPA 453598 | O20: =_xlfn.XLOOKUP(R20,PROCX!A:A,PROCX!H:H,"-",0,1) -> 0 | P20: RISCO DE PARADA - FALTA DE TAMPA 453598
B21: 1957895 | C21: T26C1927 | D21: 1200 | F21: 469970 | G21: SA MONANGE DES ANTIT INVISIVEL TCP | H21: 46139 | I21: 46139 | M21: - | O21: =_xlfn.XLOOKUP(R21,PROCX!A:A,PROCX!H:H,"-",0,1) -> - | P21: 20257-4 | Q21: MONANGE DES ANTIT INVISL 12X89G MT | R21: 1957961 | S21: =_xlfn.XLOOKUP(R21,'VERSÃO DE PROD'!B:B,'VERSÃO DE PROD'!A:A,0,0,1) -> 0 | T21: =SUMIF(COHVPI!A:A,Envase!R21,COHVPI!F:F) -> 0 | U21: =X21/12 -> 15026 | W21: =T21/U21 -> 0 | X21: =90156*2 -> 180312 | Y21: PHASE IN - PROJETO MONTANA
B22: 1957896 | C22: T26C1928 | D22: 1200 | F22: 469970 | G22: SA MONANGE DES ANTIT INVISIVEL TCP | H22: 46140 | I22: 46139 | M22: - | O22: =_xlfn.XLOOKUP(R22,PROCX!A:A,PROCX!H:H,"-",0,1) -> 0
B23: 1957897 | C23: T26C1929 | D23: 1200 | E23: =_xlfn.XLOOKUP(B23,'VERSÃO DE PROD'!B:B,'VERSÃO DE PROD'!H:H,0,0,1) -> 0 | F23: 469970 | G23: SA MONANGE DES ANTIT INVISIVEL TCP | H23: 46140 | I23: 46140 | M23: - | O23: =_xlfn.XLOOKUP(R23,PROCX!A:A,PROCX!H:H,"-",0,1) -> - | P23: 20257-4 | Q23: MONANGE DES ANTIT INVISL 12X89G MT | R23: 1957967 | S23: =_xlfn.XLOOKUP(R23,'VERSÃO DE PROD'!B:B,'VERSÃO DE PROD'!A:A,0,0,1) -> 0 | T23: =SUMIF(COHVPI!A:A,Envase!R23,COHVPI!F:F) -> 0 | U23: =X23/12 -> 15026 | W23: =T23/U23 -> 0 | X23: =90156*2 -> 180312 | Y23: PHASE IN - PROJETO MONTANA
B24: 1957898 | C24: T26C1930 | D24: 1200 | E24: =_xlfn.XLOOKUP(B24,'VERSÃO DE PROD'!B:B,'VERSÃO DE PROD'!H:H,0,0,1) -> 0 | F24: 469970 | G24: SA MONANGE DES ANTIT INVISIVEL TCP | H24: 46141 | I24: 46142 | M24: - | O24: =_xlfn.XLOOKUP(R24,PROCX!A:A,PROCX!H:H,"-",0,1) -> 0
B25: 1960328 | C25: T26D0859 | D25: 1000 | E25: =_xlfn.XLOOKUP(B25,'VERSÃO DE PROD'!B:B,'VERSÃO DE PROD'!H:H,0,0,1) -> 0 | F25: 469964 | G25: SA MONANGE CLINICAL REVIGORANTE TCP | H25: 46141 | I25: 46142 | M25: OP FABRICAÇÃO COM 1200KG -> FALTA TUBO 470229 (EXTERNO) | O25: =_xlfn.XLOOKUP(R25,PROCX!A:A,PROCX!H:H,"-",0,1) -> - | P25: 25643-2 | Q25: MONANGE CLIN REVIG AERO 12X94G MT | R25: 1960517 | S25: =_xlfn.XLOOKUP(R25,'VERSÃO DE PROD'!B:B,'VERSÃO DE PROD'!A:A,0,0,1) -> 0 | T25: =SUMIF(COHVPI!A:A,Envase!R25,COHVPI!F:F) -> 0 | U25: =X25/12 -> 8488 | W25: =T25/U25 -> 0 | X25: 101856 | Y25: DEMANDA BAIXA E ALTA COBERTURA (MAIS DE 60 DIAS)
B26: 1961051 | C26: T26D1324 | D26: 1000 | E26: =_xlfn.XLOOKUP(B26,'VERSÃO DE PROD'!B:B,'VERSÃO DE PROD'!H:H,0,0,1) -> 0 | F26: 469964 | G26: SA MONANGE CLINICAL REVIGORANTE TCP | H26: 46141 | I26: 46142 | M26: OP FABRICAÇÃO COM 1200KG -> FALTA TUBO 470229 (EXTERNO) | O26: =_xlfn.XLOOKUP(R26,PROCX!A:A,PROCX!H:H,"-",0,1) -> 0
B27: 1960360 | C27: T26D0887 | D27: 1000 | E27: =_xlfn.XLOOKUP(B27,'VERSÃO DE PROD'!B:B,'VERSÃO DE PROD'!H:H,0,0,1) -> 0 | F27: 461828 | G27: SA BOZZANO CLINICAL CLEAN AERO | H27: 46142 | I27: 46142 | M27: - | O27: =_xlfn.XLOOKUP(R27,PROCX!A:A,PROCX!H:H,"-",0,1) -> - | P27: 25644-0 | Q27: BOZZANO CLINICAL CLEAN AERO 12X94G | R27: 1960536 | S27: =_xlfn.XLOOKUP(R27,'VERSÃO DE PROD'!B:B,'VERSÃO DE PROD'!A:A,0,0,1) -> 0 | T27: =SUMIF(COHVPI!A:A,Envase!R27,COHVPI!F:F) -> 8160 | U27: =X27/12 -> 8488 | W27: =T27/U27 -> 0.96135721 | X27: =50928*2 -> 101856 | Y27: DEMANDA BAIXA E ALTA COBERTURA (MAIS DE 60 DIAS)
B28: 1960361 | C28: T26D0888 | D28: 1000 | E28: =_xlfn.XLOOKUP(B28,'VERSÃO DE PROD'!B:B,'VERSÃO DE PROD'!H:H,0,0,1) -> 0 | F28: 461828 | G28: SA BOZZANO CLINICAL CLEAN AERO | H28: 46143 | I28: 46143 | M28: - | O28: =_xlfn.XLOOKUP(R28,PROCX!A:A,PROCX!H:H,"-",0,1) -> 0
B29: 1959062 | C29: T26C2686 | D29: 1200 | E29: =_xlfn.XLOOKUP(B29,'VERSÃO DE PROD'!B:B,'VERSÃO DE PROD'!H:H,0,0,1) -> 0 | F29: 462834 | G29: SA TRES MARCHAND DES ANTI CLASS NVF | H29: 46143 | I29: 46146 | M29: - | O29: =_xlfn.XLOOKUP(R29,PROCX!A:A,PROCX!H:H,"-",0,1) -> - | P29: 8627-4 | Q29: TRES MARCHAND DES ANTI CLASS 12X90G NVF | R29: 1959059 | S29: =_xlfn.XLOOKUP(R29,'VERSÃO DE PROD'!B:B,'VERSÃO DE PROD'!A:A,0,0,1) -> 0 | T29: =SUMIF(COHVPI!A:A,Envase!R29,COHVPI!F:F) -> 7132 | U29: =X29/12 -> 6457 | W29: =T29/U29 -> 1.1045377 | X29: 77484 | Y29: DEMANDA BAIXA E ALTA COBERTURA (MAIS DE 60 DIAS)
B30: 1960325 | C30: T26D0857 | D30: 1200 | E30: =_xlfn.XLOOKUP(B30,'VERSÃO DE PROD'!B:B,'VERSÃO DE PROD'!H:H,0,0,1) -> 0 | F30: 469971 | G30: SA MONANGE DES ANTIT PROT SECA TCP | H30: 46146 | I30: 46146 | M30: - | O30: =_xlfn.XLOOKUP(R30,PROCX!A:A,PROCX!H:H,"-",0,1) -> - | P30: 24631-2 | Q30: MONANGE DES ANTIT PROT SEC 12X90G MT | R30: 1960792 | S30: =_xlfn.XLOOKUP(R30,'VERSÃO DE PROD'!B:B,'VERSÃO DE PROD'!A:A,0,0,1) -> 0 | T30: =SUMIF(COHVPI!A:A,Envase!R30,COHVPI!F:F) -> 21600 | U30: =X30/12 -> 22299 | W30: =T30/U30 -> 0.9686533 | X30: =89196*3 -> 267588 | Y30: OK
B31: 1960793 | C31: T26D1155 | D31: 1200 | E31: =_xlfn.XLOOKUP(B31,'VERSÃO DE PROD'!B:B,'VERSÃO DE PROD'!H:H,0,0,1) -> 0 | F31: 469971 | G31: SA MONANGE DES ANTIT PROT SECA TCP | H31: 46146 | I31: 46146 | M31: - | O31: =_xlfn.XLOOKUP(R31,PROCX!A:A,PROCX!H:H,"-",0,1) -> 0
B32: 1960794 | C32: T26D1156 | D32: 1200 | E32: =_xlfn.XLOOKUP(B32,'VERSÃO DE PROD'!B:B,'VERSÃO DE PROD'!H:H,0,0,1) -> 0 | F32: 469971 | G32: SA MONANGE DES ANTIT PROT SECA TCP | H32: 46148 | I32: 46148 | M32: - | O32: =_xlfn.XLOOKUP(R32,PROCX!A:A,PROCX!H:H,"-",0,1) -> 0
B33: 1960319 | C33: T26D0851 | D33: 1200 | E33: =_xlfn.XLOOKUP(B33,'VERSÃO DE PROD'!B:B,'VERSÃO DE PROD'!H:H,0,0,1) -> 0 | F33: 469971 | G33: SA MONANGE DES ANTIT PROT SECA TCP | H33: 46148 | I33: 46148 | M33: - | O33: =_xlfn.XLOOKUP(R33,PROCX!A:A,PROCX!H:H,"-",0,1) -> - | P33: 24631-2 | Q33: MONANGE DES ANTIT PROT SEC 12X90G MT | R33: 1960789 | S33: =_xlfn.XLOOKUP(R33,'VERSÃO DE PROD'!B:B,'VERSÃO DE PROD'!A:A,0,0,1) -> 0 | T33: =SUMIF(COHVPI!A:A,Envase!R33,COHVPI!F:F) -> 14160 | U33: =X33/12 -> 14866 | W33: =T33/U33 -> 0.95250908 | X33: =89196*2 -> 178392 | Y33: OK
B34: 1960320 | C34: T26D0852 | D34: 1200 | E34: =_xlfn.XLOOKUP(B34,'VERSÃO DE PROD'!B:B,'VERSÃO DE PROD'!H:H,0,0,1) -> 0 | F34: 469971 | G34: SA MONANGE DES ANTIT PROT SECA TCP | H34: 46149 | I34: 46150 | M34: - | O34: =_xlfn.XLOOKUP(R34,PROCX!A:A,PROCX!H:H,"-",0,1) -> 0
B35: 1960321 | C35: T26D0853 | D35: 1200 | E35: =_xlfn.XLOOKUP(B35,'VERSÃO DE PROD'!B:B,'VERSÃO DE PROD'!H:H,0,0,1) -> 0 | F35: 469971 | G35: SA MONANGE DES ANTIT PROT SECA TCP | H35: 46149 | I35: 46150 | M35: - | O35: =_xlfn.XLOOKUP(R35,PROCX!A:A,PROCX!H:H,"-",0,1) -> - | P35: 24631-2 | Q35: MONANGE DES ANTIT PROT SEC 12X90G MT | R35: 1960790 | S35: =_xlfn.XLOOKUP(R35,'VERSÃO DE PROD'!B:B,'VERSÃO DE PROD'!A:A,0,0,1) -> 0 | T35: =SUMIF(COHVPI!A:A,Envase!R35,COHVPI!F:F) -> 14640 | U35: =X35/12 -> 14866 | W35: =T35/U35 -> 0.98479752 | X35: =89196*2 -> 178392 | Y35: OK
B36: 1960322 | C36: T26D0854 | D36: 1200 | E36: =_xlfn.XLOOKUP(B36,'VERSÃO DE PROD'!B:B,'VERSÃO DE PROD'!H:H,0,0,1) -> 0 | F36: 469971 | G36: SA MONANGE DES ANTIT PROT SECA TCP | H36: 46150 | I36: 46151 | M36: - | O36: =_xlfn.XLOOKUP(R36,PROCX!A:A,PROCX!H:H,"-",0,1) -> 0
B37: 1960323 | C37: T26D0855 | D37: 1200 | E37: =_xlfn.XLOOKUP(B37,'VERSÃO DE PROD'!B:B,'VERSÃO DE PROD'!H:H,0,0,1) -> 0 | F37: 469971 | G37: SA MONANGE DES ANTIT PROT SECA TCP | H37: 46150 | I37: 46151 | M37: - | O37: =_xlfn.XLOOKUP(R37,PROCX!A:A,PROCX!H:H,"-",0,1) -> - | P37: 24631-2 | Q37: MONANGE DES ANTIT PROT SEC 12X90G MT | R37: 1960791 | S37: =_xlfn.XLOOKUP(R37,'VERSÃO DE PROD'!B:B,'VERSÃO DE PROD'!A:A,0,0,1) -> 0 | T37: =SUMIF(COHVPI!A:A,Envase!R37,COHVPI!F:F) -> 14721 | U37: =X37/12 -> 14866 | W37: =T37/U37 -> 0.9902462 | X37: =89196*2 -> 178392 | Y37: OK
B38: 1960324 | C38: T26D0856 | D38: 1200 | E38: =_xlfn.XLOOKUP(B38,'VERSÃO DE PROD'!B:B,'VERSÃO DE PROD'!H:H,0,0,1) -> 0 | F38: 469971 | G38: SA MONANGE DES ANTIT PROT SECA TCP | H38: 46153 | I38: 46153 | M38: - | O38: =_xlfn.XLOOKUP(R38,PROCX!A:A,PROCX!H:H,"-",0,1) -> 0
B39: SETUP | O39: =_xlfn.XLOOKUP(R39,PROCX!A:A,PROCX!H:H,"-",0,1) -> 0 | P39: SETUP
B40: 1962559 | C40: T26E0344 | D40: 1200 | E40: =_xlfn.XLOOKUP(B40,COHVPI!A:A,COHVPI!E:E,0,0,1) -> 1200 | F40: 462824 | G40: SA MONANGE DES ANTI FLOR LAV NVF | I40: 46153 | M40: - | O40: =_xlfn.XLOOKUP(R40,PROCX!A:A,PROCX!H:H,"-",0,1) -> - | P40: 17109-6 | Q40: MONANGE DES ANTI FLOR LAV 12X90G NVF | R40: 1962558 | S40: =_xlfn.XLOOKUP(R40,'VERSÃO DE PROD'!B:B,'VERSÃO DE PROD'!A:A,0,0,1) -> 0 | T40: =SUMIF(COHVPI!A:A,Envase!R40,COHVPI!F:F) -> 14628 | U40: =X40/12 -> 14866 | W40: =T40/U40 -> 0.98399031 | X40: 178392 | Y40: ESGOTAMENTO (PHASE OUT) - PROJETO MONTANA
B41: 1962560 | C41: T26E0345 | D41: 1200 | E41: =_xlfn.XLOOKUP(B41,COHVPI!A:A,COHVPI!E:E,0,0,1) -> 1200 | F41: 462824 | G41: SA MONANGE DES ANTI FLOR LAV NVF | I41: 46154 | M41: - | N41: 17107-7 | O41: =_xlfn.XLOOKUP(R41,PROCX!A:A,PROCX!H:H,"-",0,1) -> 0
B42: 1962537 | C42: T26E0331 | D42: 1200 | E42: =_xlfn.XLOOKUP(B42,COHVPI!A:A,COHVPI!E:E,0,0,1) -> 1200 | F42: 465672 | G42: SA MONANGE DES AP HID INT NF IFRA EXT NV | I42: 46154 | M42: - | O42: =_xlfn.XLOOKUP(R42,PROCX!A:A,PROCX!H:H,"-",0,1) -> - | P42: 17111-6 | Q42: MONANGE DES ANTI HIDR INTEN 12X90G NVF | R42: 1962536 | S42: =_xlfn.XLOOKUP(R42,'VERSÃO DE PROD'!B:B,'VERSÃO DE PROD'!A:A,0,0,1) -> 0 | T42: =SUMIF(COHVPI!A:A,Envase!R42,COHVPI!F:F) -> 14517 | U42: =X42/12 -> 14866 | W42: =T42/U42 -> 0.97652361 | X42: 178392 | Y42: ESGOTAMENTO (PHASE OUT) - PROJETO MONTANA
B43: 1962538 | C43: T26E0332 | D43: 1200 | E43: =_xlfn.XLOOKUP(B43,COHVPI!A:A,COHVPI!E:E,0,0,1) -> 1200 | F43: 465672 | G43: SA MONANGE DES AP HID INT NF IFRA EXT NV | I43: 46156 | M43: - | O43: =_xlfn.XLOOKUP(R43,PROCX!A:A,PROCX!H:H,"-",0,1) -> 0
B44: 1959056 | C44: T26C2683 | D44: 1200 | E44: =_xlfn.XLOOKUP(B44,COHVPI!A:A,COHVPI!E:E,0,0,1) -> 1200 | F44: 462823 | G44: SA MONANGE DES ANTI SENSIVEL NVF | I44: 46156 | M44: - | O44: =_xlfn.XLOOKUP(R44,PROCX!A:A,PROCX!H:H,"-",0,1) -> - | P44: 17107-7 | Q44: MONANGE DES ANTI SENSIVEL 12X90G NVF | R44: 1962321 | S44: =_xlfn.XLOOKUP(R44,'VERSÃO DE PROD'!B:B,'VERSÃO DE PROD'!A:A,0,0,1) -> 0 | T44: =SUMIF(COHVPI!A:A,Envase!R44,COHVPI!F:F) -> 14553 | U44: =X44/12 -> 14866 | W44: =T44/U44 -> 0.97894524 | X44: 178392 | Y44: ESGOTAMENTO (PHASE OUT) - PROJETO MONTANA
B45: 1959057 | C45: T26C2684 | D45: 1200 | E45: =_xlfn.XLOOKUP(B45,COHVPI!A:A,COHVPI!E:E,0,0,1) -> 1200 | F45: 462823 | G45: SA MONANGE DES ANTI SENSIVEL NVF | I45: 46157 | M45: - | N45: 17107-7 | O45: =_xlfn.XLOOKUP(R45,PROCX!A:A,PROCX!H:H,"-",0,1) -> 0
B46: 1963043 | C46: T26E0610 | D46: 1200 | F46: 466770 | G46: SA MONANGE DES ANTI INVISIVEL FRAG RET | I46: 46157 | M46: - | O46: =_xlfn.XLOOKUP(R46,PROCX!A:A,PROCX!H:H,"-",0,1) -> - | P46: 20257-3 | Q46: MONANGE DES ANTI INVISIVEL 12X89G NVF | R46: 1963047 | S46: =_xlfn.XLOOKUP(R46,'VERSÃO DE PROD'!B:B,'VERSÃO DE PROD'!A:A,0,0,1) -> 0 | T46: =SUMIF(COHVPI!A:A,Envase!R46,COHVPI!F:F) -> 7473 | U46: =X46/12 -> 7513 | W46: =T46/U46 -> 0.9946759 | X46: =7513*12 -> 90156 | Y46: RUPTURA EM VENDAS
B47: SETUP | O47: =_xlfn.XLOOKUP(R47,PROCX!A:A,PROCX!H:H,"-",0,1) -> 0 | P47: SETUP
B48: 1962425 | C48: T26E0195 | D48: 1200 | E48: =_xlfn.XLOOKUP(B48,COHVPI!A:A,COHVPI!E:E,0,0,1) -> 1200 | F48: 469966 | G48: SA MONANGE DES ANTIT ESPORTE TCP | I48: 46158 | M48: - | O48: =_xlfn.XLOOKUP(R48,PROCX!A:A,PROCX!H:H,"-",0,1) -> - | P48: 25503-1 | Q48: MONANGE DES ANTIT ESPORTE AERO 12X90G MT | R48: 1962322 | S48: =_xlfn.XLOOKUP(R48,'VERSÃO DE PROD'!B:B,'VERSÃO DE PROD'!A:A,0,0,1) -> 0 | T48: =SUMIF(COHVPI!A:A,Envase!R48,COHVPI!F:F) -> 21575 | U48: =X48/12 -> 21246 | W48: =T48/U48 -> 1.0154853 | X48: 254952 | Y48: OK
B49: 1962426 | C49: T26E0196 | D49: 1200 | E49: =_xlfn.XLOOKUP(B49,COHVPI!A:A,COHVPI!E:E,0,0,1) -> 1200 | F49: 469966 | G49: SA MONANGE DES ANTIT ESPORTE TCP | I49: 46158 | M49: - | O49: =_xlfn.XLOOKUP(R49,PROCX!A:A,PROCX!H:H,"-",0,1) -> 0
B50: 1962427 | C50: T26E0197 | D50: 1200 | E50: =_xlfn.XLOOKUP(B50,COHVPI!A:A,COHVPI!E:E,0,0,1) -> 1200 | F50: 469966 | G50: SA MONANGE DES ANTIT ESPORTE TCP | I50: 46161 | M50: - | O50: =_xlfn.XLOOKUP(R50,PROCX!A:A,PROCX!H:H,"-",0,1) -> 0
B51: 1963044 | C51: T26E0611 | D51: 1200 | E51: =_xlfn.XLOOKUP(B51,COHVPI!A:A,COHVPI!E:E,0,0,1) -> 1200 | F51: 469966 | G51: SA MONANGE DES ANTIT ESPORTE TCP | I51: 46161 | M51: - | O51: =_xlfn.XLOOKUP(R51,PROCX!A:A,PROCX!H:H,"-",0,1) -> - | P51: 25503-1 | Q51: MONANGE DES ANTIT ESPORTE AERO 12X90G MT | R51: =R46+1 -> 1963048 | S51: =_xlfn.XLOOKUP(R51,'VERSÃO DE PROD'!B:B,'VERSÃO DE PROD'!A:A,0,0,1) -> 0 | T51: =SUMIF(COHVPI!A:A,Envase!R51,COHVPI!F:F) -> 14602 | U51: =X51/12 -> 14164 | W51: =T51/U51 -> 1.0309235 | X51: 169968 | Y51: OK
B52: 1963045 | C52: T26E0612 | D52: 1200 | E52: =_xlfn.XLOOKUP(B52,COHVPI!A:A,COHVPI!E:E,0,0,1) -> 1200 | F52: 469966 | G52: SA MONANGE DES ANTIT ESPORTE TCP | I52: 46163 | M52: - | O52: =_xlfn.XLOOKUP(R52,PROCX!A:A,PROCX!H:H,"-",0,1) -> 0
A53: =_xlfn.XLOOKUP(B53,'VERSÃO DE PROD'!B:B,'VERSÃO DE PROD'!R:R,0,0,1) -> 0 | B53: 1960462 | C53: T26D0977 | D53: 1200 | E53: =_xlfn.XLOOKUP(B53,COHVPI!A:A,COHVPI!E:E,0,0,1) -> 1200 | F53: 469967 | G53: SA MONANGE DES ANTIT FLOR DE LAV TCP | I53: 46162 | M53: - | O53: =_xlfn.XLOOKUP(R53,PROCX!A:A,PROCX!H:H,"-",0,1) -> - | P53: 17109-7 | Q53: MONANGE DES ANTIT FL LAV 12X90G MT | R53: 1962325 | S53: =_xlfn.XLOOKUP(R53,'VERSÃO DE PROD'!B:B,'VERSÃO DE PROD'!A:A,0,0,1) -> L40 | T53: =SUMIF(COHVPI!A:A,Envase!R53,COHVPI!F:F) -> 22040 | U53: =X53/12 -> 22299 | V53: =_xlfn.XLOOKUP(R53,'VERSÃO DE PROD'!B:B,'VERSÃO DE PROD'!H:H,0,0,1) -> 22299 | W53: =T53/U53 -> 0.98838513 | X53: 267588 | Y53: OK
A54: =_xlfn.XLOOKUP(B54,'VERSÃO DE PROD'!B:B,'VERSÃO DE PROD'!R:R,0,0,1) -> 0 | B54: 1960463 | C54: T26D0978 | D54: 1200 | E54: =_xlfn.XLOOKUP(B54,COHVPI!A:A,COHVPI!E:E,0,0,1) -> 1200 | F54: 469967 | G54: SA MONANGE DES ANTIT FLOR DE LAV TCP | I54: 46162 | M54: - | O54: =_xlfn.XLOOKUP(R54,PROCX!A:A,PROCX!H:H,"-",0,1) -> 0
A55: =_xlfn.XLOOKUP(B55,'VERSÃO DE PROD'!B:B,'VERSÃO DE PROD'!R:R,0,0,1) -> 0 | B55: 1960464 | C55: T26D0979 | D55: 1200 | E55: =_xlfn.XLOOKUP(B55,COHVPI!A:A,COHVPI!E:E,0,0,1) -> 1200 | F55: 469967 | G55: SA MONANGE DES ANTIT FLOR DE LAV TCP | I55: 46164 | M55: - | O55: =_xlfn.XLOOKUP(R55,PROCX!A:A,PROCX!H:H,"-",0,1) -> 0
A56: =_xlfn.XLOOKUP(B56,'VERSÃO DE PROD'!B:B,'VERSÃO DE PROD'!R:R,0,0,1) -> 0 | B56: 1960465 | C56: T26D0980 | D56: 1200 | E56: =_xlfn.XLOOKUP(B56,COHVPI!A:A,COHVPI!E:E,0,0,1) -> 1200 | F56: 469967 | G56: SA MONANGE DES ANTIT FLOR DE LAV TCP | I56: 46164 | M56: - | O56: =_xlfn.XLOOKUP(R56,PROCX!A:A,PROCX!H:H,"-",0,1) -> - | P56: 17109-7 | Q56: MONANGE DES ANTIT FL LAV 12X90G MT | R56: 1962326 | S56: =_xlfn.XLOOKUP(R56,'VERSÃO DE PROD'!B:B,'VERSÃO DE PROD'!A:A,0,0,1) -> L40 | T56: =SUMIF(COHVPI!A:A,Envase!R56,COHVPI!F:F) -> 21406 | U56: =X56/12 -> 22299 | V56: =_xlfn.XLOOKUP(R56,'VERSÃO DE PROD'!B:B,'VERSÃO DE PROD'!H:H,0,0,1) -> 22299 | W56: =T56/U56 -> 0.95995336 | X56: 267588 | Y56: OK
A57: =_xlfn.XLOOKUP(B57,'VERSÃO DE PROD'!B:B,'VERSÃO DE PROD'!R:R,0,0,1) -> LIB IMPR CNPA FORN CAPC CPRE DMNV LOAT* | B57: 1960466 | C57: T26D0981 | D57: 1200 | E57: =_xlfn.XLOOKUP(B57,COHVPI!A:A,COHVPI!E:E,0,0,1) -> 1200 | F57: 469967 | G57: SA MONANGE DES ANTIT FLOR DE LAV TCP | I57: 46164 | M57: - | O57: =_xlfn.XLOOKUP(R57,PROCX!A:A,PROCX!H:H,"-",0,1) -> 0
A58: =_xlfn.XLOOKUP(B58,'VERSÃO DE PROD'!B:B,'VERSÃO DE PROD'!R:R,0,0,1) -> LIB IMPR CAPC CPRE DMNV LOAT MOME NOLQ* | B58: 1960467 | C58: T26D0982 | D58: 1200 | E58: =_xlfn.XLOOKUP(B58,COHVPI!A:A,COHVPI!E:E,0,0,1) -> 1200 | F58: 469967 | G58: SA MONANGE DES ANTIT FLOR DE LAV TCP | I58: 46167 | M58: - | O58: =_xlfn.XLOOKUP(R58,PROCX!A:A,PROCX!H:H,"-",0,1) -> 0
A59: =_xlfn.XLOOKUP(B59,'VERSÃO DE PROD'!B:B,'VERSÃO DE PROD'!R:R,0,0,1) -> LIB IMPR CAPC CPRE DMNV LOAT MOME NOLQ* | B59: 1960468 | C59: T26D0983 | D59: 1200 | E59: =_xlfn.XLOOKUP(B59,COHVPI!A:A,COHVPI!E:E,0,0,1) -> 1200 | F59: 469967 | G59: SA MONANGE DES ANTIT FLOR DE LAV TCP | I59: 46167 | M59: - | O59: =_xlfn.XLOOKUP(R59,PROCX!A:A,PROCX!H:H,"-",0,1) -> - | P59: 17109-7 | Q59: MONANGE DES ANTIT FL LAV 12X90G MT | R59: 1962327 | S59: =_xlfn.XLOOKUP(R59,'VERSÃO DE PROD'!B:B,'VERSÃO DE PROD'!A:A,0,0,1) -> L40 | T59: =SUMIF(COHVPI!A:A,Envase!R59,COHVPI!F:F) -> 22320 | U59: =X59/12 -> 22299 | V59: =_xlfn.XLOOKUP(R59,'VERSÃO DE PROD'!B:B,'VERSÃO DE PROD'!H:H,0,0,1) -> 22299 | W59: =T59/U59 -> 1.0009417 | X59: 267588 | Y59: OK
A60: =_xlfn.XLOOKUP(B60,'VERSÃO DE PROD'!B:B,'VERSÃO DE PROD'!R:R,0,0,1) -> LIB CAPC CPRE DMNV LOAT NOLQ ORSL | B60: 1960469 | C60: T26D0984 | D60: 1200 | E60: =_xlfn.XLOOKUP(B60,COHVPI!A:A,COHVPI!E:E,0,0,1) -> 1200 | F60: 469967 | G60: SA MONANGE DES ANTIT FLOR DE LAV TCP | I60: 46167 | M60: - | O60: =_xlfn.XLOOKUP(R60,PROCX!A:A,PROCX!H:H,"-",0,1) -> 0
A61: =_xlfn.XLOOKUP(B61,'VERSÃO DE PROD'!B:B,'VERSÃO DE PROD'!R:R,0,0,1) -> LIB CAPC CPRE DMNV LOAT NOLQ ORSL | B61: 1960470 | C61: T26D0985 | D61: 1200 | E61: =_xlfn.XLOOKUP(B61,COHVPI!A:A,COHVPI!E:E,0,0,1) -> 1200 | F61: 469967 | G61: SA MONANGE DES ANTIT FLOR DE LAV TCP | I61: 46169 | M61: - | O61: =_xlfn.XLOOKUP(R61,PROCX!A:A,PROCX!H:H,"-",0,1) -> 0
A62: =_xlfn.XLOOKUP(B62,'VERSÃO DE PROD'!B:B,'VERSÃO DE PROD'!R:R,0,0,1) -> LIB CAPC CPRE DMNV LOAT NOLQ ORSL | B62: 1960471 | C62: T26D0986 | D62: 1200 | E62: =_xlfn.XLOOKUP(B62,COHVPI!A:A,COHVPI!E:E,0,0,1) -> 1200 | F62: 469967 | G62: SA MONANGE DES ANTIT FLOR DE LAV TCP | I62: 46169 | M62: - | O62: =_xlfn.XLOOKUP(R62,PROCX!A:A,PROCX!H:H,"-",0,1) -> - | P62: 17109-7 | Q62: MONANGE DES ANTIT FL LAV 12X90G MT | R62: 1962328 | S62: =_xlfn.XLOOKUP(R62,'VERSÃO DE PROD'!B:B,'VERSÃO DE PROD'!A:A,0,0,1) -> L40 | T62: =SUMIF(COHVPI!A:A,Envase!R62,COHVPI!F:F) -> 21360 | U62: =X62/12 -> 22299 | V62: =_xlfn.XLOOKUP(R62,'VERSÃO DE PROD'!B:B,'VERSÃO DE PROD'!H:H,0,0,1) -> 22299 | W62: =T62/U62 -> 0.95789049 | X62: 267588 | Y62: OK
A63: =_xlfn.XLOOKUP(B63,'VERSÃO DE PROD'!B:B,'VERSÃO DE PROD'!R:R,0,0,1) -> LIB CAPC CPRE DMNV LOAT NOLQ ORSL | B63: 1960472 | C63: T26D0987 | D63: 1200 | E63: =_xlfn.XLOOKUP(B63,COHVPI!A:A,COHVPI!E:E,0,0,1) -> 1200 | F63: 469967 | G63: SA MONANGE DES ANTIT FLOR DE LAV TCP | I63: 46169 | M63: - | O63: =_xlfn.XLOOKUP(R63,PROCX!A:A,PROCX!H:H,"-",0,1) -> 0
A64: =_xlfn.XLOOKUP(B64,'VERSÃO DE PROD'!B:B,'VERSÃO DE PROD'!R:R,0,0,1) -> LIB CAPC CPRE DMNV LOAT NOLQ ORSL | B64: 1960473 | C64: T26D0988 | D64: 1200 | E64: =_xlfn.XLOOKUP(B64,COHVPI!A:A,COHVPI!E:E,0,0,1) -> 1200 | F64: 469967 | G64: SA MONANGE DES ANTIT FLOR DE LAV TCP | I64: 46171 | M64: - | O64: =_xlfn.XLOOKUP(R64,PROCX!A:A,PROCX!H:H,"-",0,1) -> 0
A65: =_xlfn.XLOOKUP(B65,'VERSÃO DE PROD'!B:B,'VERSÃO DE PROD'!R:R,0,0,1) -> LIB CAPC CPRE DMNV LOAT NOLQ ORSL | B65: 1962507 | C65: T26E0280 | D65: 1200 | E65: =_xlfn.XLOOKUP(B65,COHVPI!A:A,COHVPI!E:E,0,0,1) -> 1200 | F65: 469967 | G65: SA MONANGE DES ANTIT FLOR DE LAV TCP | I65: 46171 | M65: - | O65: =_xlfn.XLOOKUP(R65,PROCX!A:A,PROCX!H:H,"-",0,1) -> - | P65: 17109-7 | Q65: MONANGE DES ANTIT FL LAV 12X90G MT | R65: 1962329 | S65: =_xlfn.XLOOKUP(R65,'VERSÃO DE PROD'!B:B,'VERSÃO DE PROD'!A:A,0,0,1) -> L40 | T65: =SUMIF(COHVPI!A:A,Envase!R65,COHVPI!F:F) -> 14640 | U65: =X65/12 -> 14866 | V65: =_xlfn.XLOOKUP(R65,'VERSÃO DE PROD'!B:B,'VERSÃO DE PROD'!H:H,0,0,1) -> 14866 | W65: =T65/U65 -> 0.98479752 | X65: 178392 | Y65: OK
A66: =_xlfn.XLOOKUP(B66,'VERSÃO DE PROD'!B:B,'VERSÃO DE PROD'!R:R,0,0,1) -> LIB CAPC CPRE DMNV LOAT NOLQ ORSL | B66: 1962508 | C66: T26E0281 | D66: 1200 | E66: =_xlfn.XLOOKUP(B66,COHVPI!A:A,COHVPI!E:E,0,0,1) -> 1200 | F66: 469967 | G66: SA MONANGE DES ANTIT FLOR DE LAV TCP | I66: 46172 | M66: - | O66: =_xlfn.XLOOKUP(R66,PROCX!A:A,PROCX!H:H,"-",0,1) -> 0
A67: =_xlfn.XLOOKUP(B67,'VERSÃO DE PROD'!B:B,'VERSÃO DE PROD'!R:R,0,0,1) -> LIB CAPC CPRE DMNV LOAT NOLQ ORSL | B67: 1962509 | C67: T26E0282 | D67: 1200 | E67: =_xlfn.XLOOKUP(B67,COHVPI!A:A,COHVPI!E:E,0,0,1) -> 1200 | F67: 469967 | G67: SA MONANGE DES ANTIT FLOR DE LAV TCP | I67: 46172 | M67: - | O67: =_xlfn.XLOOKUP(R67,PROCX!A:A,PROCX!H:H,"-",0,1) -> - | P67: 17109-7 | Q67: MONANGE DES ANTIT FL LAV 12X90G MT | R67: 1962330 | S67: =_xlfn.XLOOKUP(R67,'VERSÃO DE PROD'!B:B,'VERSÃO DE PROD'!A:A,0,0,1) -> L40 | T67: =SUMIF(COHVPI!A:A,Envase!R67,COHVPI!F:F) -> 14433 | U67: =X67/12 -> 14866 | V67: =_xlfn.XLOOKUP(R67,'VERSÃO DE PROD'!B:B,'VERSÃO DE PROD'!H:H,0,0,1) -> 14866 | W67: =T67/U67 -> 0.97087313 | X67: 178392 | Y67: OK
A68: =_xlfn.XLOOKUP(B68,'VERSÃO DE PROD'!B:B,'VERSÃO DE PROD'!R:R,0,0,1) -> LIB CAPC CPRE DMNV LOAT NOLQ ORSL | B68: 1962510 | C68: T26E0283 | D68: 1200 | E68: =_xlfn.XLOOKUP(B68,COHVPI!A:A,COHVPI!E:E,0,0,1) -> 1200 | F68: 469967 | G68: SA MONANGE DES ANTIT FLOR DE LAV TCP | I68: 46176 | M68: - | O68: =_xlfn.XLOOKUP(R68,PROCX!A:A,PROCX!H:H,"-",0,1) -> 0
B69: 1964912 | C69: T26E1750 | D69: 1000 | F69: 461826 | G69: SA MONANGE CLINICAL CONFORTO AERO | I69: 46176 | M69: - | O69: =_xlfn.XLOOKUP(R69,PROCX!A:A,PROCX!H:H,"-",0,1) -> - | P69: 25642-1 | Q69: MONANGE CLINICAL CONFORTO AERO 12X94G NL | R69: 1964889 | S69: =_xlfn.XLOOKUP(R69,'VERSÃO DE PROD'!B:B,'VERSÃO DE PROD'!A:A,0,0,1) -> 0 | T69: =SUMIF(COHVPI!A:A,Envase!R69,COHVPI!F:F) -> 4235 | U69: =X69/12 -> 4244 | V69: =_xlfn.XLOOKUP(R69,'VERSÃO DE PROD'!B:B,'VERSÃO DE PROD'!H:H,0,0,1) -> 0 | W69: =T69/U69 -> 0.99787936 | X69: 50928 | Y69: ESGOTAMENTO (PHASE OUT) - PROJETO MONTANA
B70: 1964911 | C70: T26E1749 | D70: 1200 | F70: 462828 | G70: SA MONANGE DES ANTI DETOX FRESH NVF | I70: 46176 | M70: - | O70: =_xlfn.XLOOKUP(R70,PROCX!A:A,PROCX!H:H,"-",0,1) -> - | P70: 24630-1 | Q70: MONANGE DES ANTI DETOX FRESH 12X90G NVF | R70: 1964892 | S70: =_xlfn.XLOOKUP(R70,'VERSÃO DE PROD'!B:B,'VERSÃO DE PROD'!A:A,0,0,1) -> 0 | T70: =SUMIF(COHVPI!A:A,Envase!R70,COHVPI!F:F) -> 7301 | U70: =X70/12 -> 7433 | V70: =_xlfn.XLOOKUP(R70,'VERSÃO DE PROD'!B:B,'VERSÃO DE PROD'!H:H,0,0,1) -> 0 | W70: =T70/U70 -> 0.98224136 | X70: 89196 | Y70: ESGOTAMENTO (PHASE OUT) - PROJETO MONTANA
B71: 1964917 | C71: T26E1755 | D71: 1200 | F71: 466770 | G71: SA MONANGE DES ANTI INVISIVEL FRAG RET | I71: 46177 | M71: FALTA TUBO 462806 (CQ) | O71: =_xlfn.XLOOKUP(R71,PROCX!A:A,PROCX!H:H,"-",0,1) -> - | P71: 20257-3 | Q71: MONANGE DES ANTI INVISIVEL 12X89G NVF | R71: 1964890 | S71: =_xlfn.XLOOKUP(R71,'VERSÃO DE PROD'!B:B,'VERSÃO DE PROD'!A:A,0,0,1) -> 0 | T71: =SUMIF(COHVPI!A:A,Envase!R71,COHVPI!F:F) -> 7495 | U71: =X71/12 -> 7513 | V71: =_xlfn.XLOOKUP(R71,'VERSÃO DE PROD'!B:B,'VERSÃO DE PROD'!H:H,0,0,1) -> 0 | W71: =T71/U71 -> 0.99760415 | X71: 90156 | Y71: ESGOTAMENTO (PHASE OUT) - PROJETO MONTANA
B72: 1964910 | C72: T26E1748 | D72: 1200 | E72: =_xlfn.XLOOKUP(B72,COHVPI!A:A,COHVPI!E:E,"-",0,1) -> 1200 | F72: 462825 | G72: SA MONANGE DES ANTI FRUTAS VM NVF | I72: 46178 | M72: - | O72: =_xlfn.XLOOKUP(R72,PROCX!A:A,PROCX!H:H,"-",0,1) -> - | P72: 17110-7 | Q72: MONANGE DES ANTI FRUTAS VM 12X90G NVF | R72: 1964891 | S72: =_xlfn.XLOOKUP(R72,'COHVPI DATAS REALIZADAS'!C:C,'COHVPI DATAS REALIZADAS'!T:T,0,0,1) -> L40 | T72: =SUMIF(COHVPI!A:A,Envase!R72,COHVPI!F:F) -> 2449 | U72: =X72/12 -> 7433 | V72: =_xlfn.XLOOKUP(R72,'COHVPI DATAS REALIZADAS'!C:C,'COHVPI DATAS REALIZADAS'!E:E,0,0,1) -> 7433 | W72: =T72/U72 -> 0.32947666 | X72: 89196 | Y72: ESGOTAMENTO (PHASE OUT) - PROJETO MONTANA
B73: 1964909 | C73: T26E1747 | D73: 1200 | E73: =_xlfn.XLOOKUP(B73,COHVPI!A:A,COHVPI!E:E,"-",0,1) -> 1200 | F73: 462824 | G73: SA MONANGE DES ANTI FLOR LAV NVF | I73: 46182 | M73: - | O73: =_xlfn.XLOOKUP(R73,PROCX!A:A,PROCX!H:H,"-",0,1) -> - | P73: 17109-6 | Q73: MONANGE DES ANTI FLOR LAV 12X90G NVF | R73: 1964894 | S73: =_xlfn.XLOOKUP(R73,'COHVPI DATAS REALIZADAS'!C:C,'COHVPI DATAS REALIZADAS'!T:T,0,0,1) -> L40 | T73: =SUMIF(COHVPI!A:A,Envase!R73,COHVPI!F:F) -> 0 | U73: =X73/12 -> 7433 | V73: =_xlfn.XLOOKUP(R73,'COHVPI DATAS REALIZADAS'!C:C,'COHVPI DATAS REALIZADAS'!E:E,0,0,1) -> 7433 | W73: =T73/U73 -> 0 | X73: 89196 | Y73: ESGOTAMENTO (PHASE OUT) - PROJETO MONTANA
B74: 1964908 | C74: T26E1746 | D74: 1200 | E74: =_xlfn.XLOOKUP(B74,COHVPI!A:A,COHVPI!E:E,"-",0,1) -> 1200 | F74: 462823 | G74: SA MONANGE DES ANTI SENSIVEL NVF | I74: 46184 | M74: FALTA TAPA 453598 (CHEGA 08/06) + TUBO 462802 (CQ) | O74: =_xlfn.XLOOKUP(R74,PROCX!A:A,PROCX!H:H,"-",0,1) -> - | P74: 17107-7 | Q74: MONANGE DES ANTI SENSIVEL 12X90G NVF | R74: 1964893 | S74: =_xlfn.XLOOKUP(R74,'COHVPI DATAS REALIZADAS'!C:C,'COHVPI DATAS REALIZADAS'!T:T,0,0,1) -> L40 | T74: =SUMIF(COHVPI!A:A,Envase!R74,COHVPI!F:F) -> 0 | U74: =X74/12 -> 7433 | V74: =_xlfn.XLOOKUP(R74,'COHVPI DATAS REALIZADAS'!C:C,'COHVPI DATAS REALIZADAS'!E:E,0,0,1) -> 7433 | W74: =T74/U74 -> 0 | X74: 89196 | Y74: ESGOTAMENTO (PHASE OUT) - PROJETO MONTANA
A75: =_xlfn.XLOOKUP(B75,'VERSÃO DE PROD'!B:B,'VERSÃO DE PROD'!R:R,0,0,1) -> 0 | B75: TROCA DE MARCA | E75: =_xlfn.XLOOKUP(B75,COHVPI!A:A,COHVPI!E:E,"-",0,1) -> - | O75: =_xlfn.XLOOKUP(R75,PROCX!A:A,PROCX!H:H,"-",0,1) -> 0 | P75: TROCA DE MARCA
A76: =_xlfn.XLOOKUP(B76,'VERSÃO DE PROD'!B:B,'VERSÃO DE PROD'!R:R,0,0,1) -> LIB CAPC CPRE DMNV LOAT NOLQ ORSL | B76: 1958372 | C76: T26C2184 | D76: 1200 | E76: =_xlfn.XLOOKUP(B76,COHVPI!A:A,COHVPI!E:E,"-",0,1) -> 1200 | F76: 465365 | G76: SA ADIDAS DES ANTI POWER BOOSTER MASC | I76: 46185 | M76: - | O76: =_xlfn.XLOOKUP(R76,PROCX!A:A,PROCX!H:H,"-",0,1) -> - | P76: 27172-0 | Q76: ADIDAS DES ANTI POWER BOOSTER MASC 150ML | R76: 1962339 | S76: =_xlfn.XLOOKUP(R76,'COHVPI DATAS REALIZADAS'!C:C,'COHVPI DATAS REALIZADAS'!T:T,0,0,1) -> L40 | T76: =SUMIF(COHVPI!A:A,Envase!R76,COHVPI!F:F) -> 0 | U76: =X76/12 -> 7433 | V76: =_xlfn.XLOOKUP(R76,'COHVPI DATAS REALIZADAS'!C:C,'COHVPI DATAS REALIZADAS'!E:E,0,0,1) -> 7433 | W76: =T76/U76 -> 0 | X76: 89196 | Y76: ESGOTAMENTO TUBO 465344
A77: =_xlfn.XLOOKUP(B77,'VERSÃO DE PROD'!B:B,'VERSÃO DE PROD'!R:R,0,0,1) -> 0 | B77: TROCA DE MARCA | E77: =_xlfn.XLOOKUP(B77,COHVPI!A:A,COHVPI!E:E,"-",0,1) -> - | O77: =_xlfn.XLOOKUP(R77,PROCX!A:A,PROCX!H:H,"-",0,1) -> 0 | P77: TROCA DE MARCA
B78: 1964937 | C78: T26E1775 | D78: 1200 | E78: =_xlfn.XLOOKUP(B78,COHVPI!A:A,COHVPI!E:E,"-",0,1) -> 1200 | F78: 469966 | G78: SA MONANGE DES ANTIT ESPORTE TCP | I78: 46186 | M78: FALTA FRAGRÂNCIA 469944 (CHEGA 10/06) + VÁLVULA 470375 (CHEGA 08/06) + TAMPA 453598 (CHEGA 08/06) + TUBO 470227 (CHEGA 08 A 10/06) | O78: =_xlfn.XLOOKUP(R78,PROCX!A:A,PROCX!H:H,"-",0,1) -> - | P78: 25503-1 | Q78: MONANGE DES ANTIT ESPORTE AERO 12X90G MT | R78: 1964901 | S78: =_xlfn.XLOOKUP(R78,'COHVPI DATAS REALIZADAS'!C:C,'COHVPI DATAS REALIZADAS'!T:T,0,0,1) -> L40 | T78: =SUMIF(COHVPI!A:A,Envase!R78,COHVPI!F:F) -> 0 | U78: =X78/12 -> 21237 | V78: =_xlfn.XLOOKUP(R78,'COHVPI DATAS REALIZADAS'!C:C,'COHVPI DATAS REALIZADAS'!E:E,0,0,1) -> 21237 | W78: =T78/U78 -> 0 | X78: 254844 | Y78: BAIXA DEMANDA
B79: 1964938 | C79: T26E1776 | D79: 1200 | E79: =_xlfn.XLOOKUP(B79,COHVPI!A:A,COHVPI!E:E,"-",0,1) -> 1200 | F79: 469966 | G79: SA MONANGE DES ANTIT ESPORTE TCP | I79: 46186 | M79: FALTA FRAGRÂNCIA 469944 (CHEGA 10/06) + VÁLVULA 470375 (CHEGA 08/06) + TAMPA 453598 (CHEGA 08/06) + TUBO 470227 (CHEGA 08 A 10/06) | O79: =_xlfn.XLOOKUP(R79,PROCX!A:A,PROCX!H:H,"-",0,1) -> 0
B80: 1964939 | C80: T26E1777 | D80: 1200 | E80: =_xlfn.XLOOKUP(B80,COHVPI!A:A,COHVPI!E:E,"-",0,1) -> 1200 | F80: 469966 | G80: SA MONANGE DES ANTIT ESPORTE TCP | I80: 46190 | M80: FALTA FRAGRÂNCIA 469944 (CHEGA 10/06) + VÁLVULA 470375 (CHEGA 08/06) + TAMPA 453598 (CHEGA 08/06) + TUBO 470227 (CHEGA 08 A 10/06) | O80: =_xlfn.XLOOKUP(R80,PROCX!A:A,PROCX!H:H,"-",0,1) -> 0
A81: =_xlfn.XLOOKUP(B81,'VERSÃO DE PROD'!B:B,'VERSÃO DE PROD'!R:R,0,0,1) -> 0 | B81: TROCA DE MARCA | E81: =_xlfn.XLOOKUP(B81,COHVPI!A:A,COHVPI!E:E,"-",0,1) -> - | O81: =_xlfn.XLOOKUP(R81,PROCX!A:A,PROCX!H:H,"-",0,1) -> 0 | P81: TROCA DE MARCA
A82: =_xlfn.XLOOKUP(B82,'VERSÃO DE PROD'!B:B,'VERSÃO DE PROD'!R:R,0,0,1) -> LIB CAPC CPRE DMNV LOAT NOLQ ORSL | B82: 1963572 | C82: T26E0940 | D82: 1200 | E82: =_xlfn.XLOOKUP(B82,COHVPI!A:A,COHVPI!E:E,"-",0,1) -> 1200 | F82: 465364 | G82: SA ADIDAS DES ANTI POWER BOOSTER FEM | I82: 46190 | M82: FALTA FRAGRÂNCIA 465405 (CHEGA 13/06) + CAIXA 467125 (EXTERNO) | O82: =_xlfn.XLOOKUP(R82,PROCX!A:A,PROCX!H:H,"-",0,1) -> - | P82: 27170-0 | Q82: ADIDAS DES ANTI POWER BOOSTER FEM 150ML | R82: 1963571 | S82: =_xlfn.XLOOKUP(R82,'COHVPI DATAS REALIZADAS'!C:C,'COHVPI DATAS REALIZADAS'!T:T,0,0,1) -> L40 | T82: =SUMIF(COHVPI!A:A,Envase!R82,COHVPI!F:F) -> 0 | U82: =X82/12 -> 19506 | V82: =_xlfn.XLOOKUP(R82,'COHVPI DATAS REALIZADAS'!C:C,'COHVPI DATAS REALIZADAS'!E:E,0,0,1) -> 19506 | W82: =T82/U82 -> 0 | X82: =19506*12 -> 234072 | Y82: BAIXA DEMANDA
A83: =_xlfn.XLOOKUP(B83,'VERSÃO DE PROD'!B:B,'VERSÃO DE PROD'!R:R,0,0,1) -> LIB CAPC CPRE DMNV LOAT NOLQ ORSL | B83: 1963573 | C83: T26E0941 | D83: 1200 | E83: =_xlfn.XLOOKUP(B83,COHVPI!A:A,COHVPI!E:E,"-",0,1) -> 1200 | F83: 465364 | G83: SA ADIDAS DES ANTI POWER BOOSTER FEM | I83: 46190 | M83: FALTA FRAGRÂNCIA 465405 (CHEGA 13/06) + CAIXA 467125 (EXTERNO) | O83: =_xlfn.XLOOKUP(R83,PROCX!A:A,PROCX!H:H,"-",0,1) -> 0
A84: =_xlfn.XLOOKUP(B84,'VERSÃO DE PROD'!B:B,'VERSÃO DE PROD'!R:R,0,0,1) -> LIB CAPC CPRE DMNV LOAT NOLQ ORSL | B84: 1964481 | C84: T26E1527 | D84: 900 | E84: =_xlfn.XLOOKUP(B84,COHVPI!A:A,COHVPI!E:E,"-",0,1) -> 900 | F84: 465364 | G84: SA ADIDAS DES ANTI POWER BOOSTER FEM | I84: 46192 | M84: ACOMPANHAMENTO AMANDA - FALTA FRAGRÂNCIA 465405 (CHEGA 13/06) + CAIXA 467125 (EXTERNO) + TUBO 465340 (CQ) | O84: =_xlfn.XLOOKUP(R84,PROCX!A:A,PROCX!H:H,"-",0,1) -> 0
A85: =_xlfn.XLOOKUP(B85,'VERSÃO DE PROD'!B:B,'VERSÃO DE PROD'!R:R,0,0,1) -> LIB MATF CAPC CPRE DMNV LOAT NOLQ ORSL | B85: 1962424 | C85: T26E0194 | D85: 1000 | E85: =_xlfn.XLOOKUP(B85,COHVPI!A:A,COHVPI!E:E,"-",0,1) -> 1000 | F85: 468245 | G85: SA ADIDAS CLINICAL CARE FEMALE AERO | I85: 46192 | M85: FALTA FRAGRÂNCIA 465410 (CHEGA 15/06) + CAIXA 467125 (EXTERNO) + TUBO 468241 (EXTERNO) | O85: =_xlfn.XLOOKUP(R85,PROCX!A:A,PROCX!H:H,"-",0,1) -> - | P85: 29030-0 | Q85: ADIDAS DES ANTI CLINICAL CARE FEM 150ML | R85: 1962337 | S85: =_xlfn.XLOOKUP(R85,'COHVPI DATAS REALIZADAS'!C:C,'COHVPI DATAS REALIZADAS'!T:T,0,0,1) -> L40 | T85: =SUMIF(COHVPI!A:A,Envase!R85,COHVPI!F:F) -> 0 | U85: =X85/12 -> 4244 | V85: =_xlfn.XLOOKUP(R85,'COHVPI DATAS REALIZADAS'!C:C,'COHVPI DATAS REALIZADAS'!E:E,0,0,1) -> 4244 | W85: =T85/U85 -> 0 | X85: 50928 | Y85: COBERTURA + 60 DIAS
B86: 1964921 | C86: T26E1759 | D86: 1200 | E86: =_xlfn.XLOOKUP(B86,COHVPI!A:A,COHVPI!E:E,"-",0,1) -> 1200 | F86: 470362 | G86: SA ADIDAS FRESH ENDURANCE AP SPRAY TCP | I86: 46193 | M86: FALTA VÁLVULA 470376 (AGDO INFO) + TUBO 470498 (CHEGA 16/06) | O86: =_xlfn.XLOOKUP(R86,PROCX!A:A,PROCX!H:H,"-",0,1) -> - | P86: 27173-2 | Q86: ADIDAS DES ANTI FR ENDUR MASC 150ML RV | R86: 1964885 | S86: =_xlfn.XLOOKUP(R86,'COHVPI DATAS REALIZADAS'!C:C,'COHVPI DATAS REALIZADAS'!T:T,0,0,1) -> L40 | T86: =SUMIF(COHVPI!A:A,Envase!R86,COHVPI!F:F) -> 0 | U86: =X86/12 -> 7433 | V86: =_xlfn.XLOOKUP(R86,'COHVPI DATAS REALIZADAS'!C:C,'COHVPI DATAS REALIZADAS'!E:E,0,0,1) -> 7433 | W86: =T86/U86 -> 0 | X86: 89196 | Y86: BAIXA DEMANDA
B87: 1964922 | C87: T26E1760 | D87: 1200 | E87: =_xlfn.XLOOKUP(B87,COHVPI!A:A,COHVPI!E:E,"-",0,1) -> 1200 | F87: 470363 | G87: SA ADIDAS INVISIBLE AP SPRAY TCP | I87: 46195 | M87: FALTA VÁLVULA 470376 (AGDO INFO) + TAMPA 467708 (EXTERNO) + TUBO 470496 (CHEGA 26/06) | O87: =_xlfn.XLOOKUP(R87,PROCX!A:A,PROCX!H:H,"-",0,1) -> - | P87: 23209-5 | Q87: ADIDAS DES ANTI PRO INVISIBLE MASC 150ML | R87: 1964888 | S87: =_xlfn.XLOOKUP(R87,'COHVPI DATAS REALIZADAS'!C:C,'COHVPI DATAS REALIZADAS'!T:T,0,0,1) -> L40 | T87: =SUMIF(COHVPI!A:A,Envase!R87,COHVPI!F:F) -> 0 | U87: =X87/12 -> 22539 | V87: =_xlfn.XLOOKUP(R87,'COHVPI DATAS REALIZADAS'!C:C,'COHVPI DATAS REALIZADAS'!E:E,0,0,1) -> 22539 | W87: =T87/U87 -> 0 | X87: 270468 | Y87: BAIXA DEMANDA
B88: 1964923 | C88: T26E1761 | D88: 1200 | E88: =_xlfn.XLOOKUP(B88,COHVPI!A:A,COHVPI!E:E,"-",0,1) -> 1200 | F88: 470363 | G88: SA ADIDAS INVISIBLE AP SPRAY TCP | I88: 46195 | M88: FALTA VÁLVULA 470376 (AGDO INFO) + TAMPA 467708 (EXTERNO) + TUBO 470496 (CHEGA 26/06) | O88: =_xlfn.XLOOKUP(R88,PROCX!A:A,PROCX!H:H,"-",0,1) -> 0
B89: 1964924 | C89: T26E1762 | D89: 1200 | E89: =_xlfn.XLOOKUP(B89,COHVPI!A:A,COHVPI!E:E,"-",0,1) -> 1200 | F89: 470363 | G89: SA ADIDAS INVISIBLE AP SPRAY TCP | I89: 46198 | M89: FALTA VÁLVULA 470376 (AGDO INFO) + TAMPA 467708 (EXTERNO) + TUBO 470496 (CHEGA 26/06) | O89: =_xlfn.XLOOKUP(R89,PROCX!A:A,PROCX!H:H,"-",0,1) -> 0
A90: =_xlfn.XLOOKUP(B90,'VERSÃO DE PROD'!B:B,'VERSÃO DE PROD'!R:R,0,0,1) -> 0 | B90: TROCA DE MARCA | E90: =_xlfn.XLOOKUP(B90,COHVPI!A:A,COHVPI!E:E,"-",0,1) -> - | O90: =_xlfn.XLOOKUP(R90,PROCX!A:A,PROCX!H:H,"-",0,1) -> 0 | P90: TROCA DE MARCA
B91: 1963478 | C91: T26E0854 | D91: 1200 | E91: =_xlfn.XLOOKUP(B91,COHVPI!A:A,COHVPI!E:E,"-",0,1) -> 1200 | F91: 462820 | G91: SA BOZZANO DES ANTI INVISIBLE NVF | I91: 46198 | M91: FALTA TAMPA 452602 (CHEGA 13/06) | O91: =_xlfn.XLOOKUP(R91,PROCX!A:A,PROCX!H:H,0,0,1) -> import | P91: 20159-4 | Q91: BOZZANO DES ANTI INVISIBLE 12X89G NVF | R91: 1963470 | S91: =_xlfn.XLOOKUP(R91,'COHVPI DATAS REALIZADAS'!C:C,'COHVPI DATAS REALIZADAS'!T:T,0,0,1) -> L40 | T91: =SUMIF(COHVPI!A:A,Envase!R91,COHVPI!F:F) -> 0 | U91: =X91/12 -> 22539 | V91: =_xlfn.XLOOKUP(R91,'COHVPI DATAS REALIZADAS'!C:C,'COHVPI DATAS REALIZADAS'!E:E,0,0,1) -> 22539 | W91: =T91/U91 -> 0 | X91: 270468 | Y91: FALTA DE TAMPA
B92: 1963479 | C92: T26E0855 | D92: 1200 | E92: =_xlfn.XLOOKUP(B92,COHVPI!A:A,COHVPI!E:E,"-",0,1) -> 1200 | F92: 462820 | G92: SA BOZZANO DES ANTI INVISIBLE NVF | I92: 46198 | M92: FALTA TAMPA 452602 (CHEGA 13/06) | O92: =_xlfn.XLOOKUP(R92,PROCX!A:A,PROCX!H:H,0,0,1) -> 0
B93: 1963480 | C93: T26E0856 | D93: 1200 | E93: =_xlfn.XLOOKUP(B93,COHVPI!A:A,COHVPI!E:E,"-",0,1) -> 1200 | F93: 462820 | G93: SA BOZZANO DES ANTI INVISIBLE NVF | I93: 46202 | M93: FALTA TAMPA 452602 (CHEGA 13/06) | O93: =_xlfn.XLOOKUP(R93,PROCX!A:A,PROCX!H:H,0,0,1) -> 0
A94: =_xlfn.XLOOKUP(B94,'VERSÃO DE PROD'!B:B,'VERSÃO DE PROD'!R:R,0,0,1) -> 0 | B94: TROCA DE MARCA | E94: =_xlfn.XLOOKUP(B94,COHVPI!A:A,COHVPI!E:E,"-",0,1) -> - | O94: =_xlfn.XLOOKUP(R94,PROCX!A:A,PROCX!H:H,"-",0,1) -> 0 | P94: TROCA DE MARCA
B95: 1964919 | C95: T26E1757 | D95: 1200 | E95: =_xlfn.XLOOKUP(B95,COHVPI!A:A,COHVPI!E:E,"-",0,1) -> 1200 | F95: 469965 | G95: SA MONANGE DES ANTIT DETOX FRESH TCP | I95: 46202 | M95: FALTA VÁLVULA 470375 (AGDO INFO) + TAMPA 453598 (AGDO INFO) + TUBO 470226 (CHEGA A PARIR DE 16/06) | O95: =_xlfn.XLOOKUP(R95,PROCX!A:A,PROCX!H:H,"-",0,1) -> - | P95: 24630-2 | Q95: MONANGE DES ANTIT DETOX FRESH 12X90G MT | R95: 1964895 | S95: =_xlfn.XLOOKUP(R95,'COHVPI DATAS REALIZADAS'!C:C,'COHVPI DATAS REALIZADAS'!T:T,0,0,1) -> L40 | T95: =SUMIF(COHVPI!A:A,Envase!R95,COHVPI!F:F) -> 0 | U95: =X95/12 -> 14866 | V95: =_xlfn.XLOOKUP(R95,'COHVPI DATAS REALIZADAS'!C:C,'COHVPI DATAS REALIZADAS'!E:E,0,0,1) -> 14866 | W95: =T95/U95 -> 0 | X95: 178392 | Y95: BAIXA DEMANDA
B96: 1964920 | C96: T26E1758 | D96: 1200 | E96: =_xlfn.XLOOKUP(B96,COHVPI!A:A,COHVPI!E:E,"-",0,1) -> 1200 | F96: 469965 | G96: SA MONANGE DES ANTIT DETOX FRESH TCP | I96: 46202 | M96: FALTA VÁLVULA 470375 (AGDO INFO) + TAMPA 453598 (AGDO INFO) + TUBO 470226 (CHEGA A PARIR DE 16/06) | O96: =_xlfn.XLOOKUP(R96,PROCX!A:A,PROCX!H:H,"-",0,1) -> 0
A97: =_xlfn.XLOOKUP(B97,'VERSÃO DE PROD'!B:B,'VERSÃO DE PROD'!R:R,0,0,1) -> 0 | B97: TROCA DE MARCA | E97: =_xlfn.XLOOKUP(B97,COHVPI!A:A,COHVPI!E:E,"-",0,1) -> - | O97: =_xlfn.XLOOKUP(R97,PROCX!A:A,PROCX!H:H,"-",0,1) -> 0 | P97: TROCA DE MARCA
B98: 1964913 | C98: T26E1751 | D98: 1000 | E98: =_xlfn.XLOOKUP(B98,COHVPI!A:A,COHVPI!E:E,"-",0,1) -> 1000 | F98: 461829 | G98: SA BOZZANO CLINICAL ULTRA COOL AERO | I98: 46203 | M98: FALTA TAMPA 452602 (CHEGA 13/06) | O98: =_xlfn.XLOOKUP(R98,PROCX!A:A,PROCX!H:H,"-",0,1) -> import | P98: 25645-0 | Q98: BOZZANO CLINIC ULTRA COOL AERO 12X94G | R98: 1964887 | S98: =_xlfn.XLOOKUP(R98,'COHVPI DATAS REALIZADAS'!C:C,'COHVPI DATAS REALIZADAS'!T:T,0,0,1) -> L40 | T98: =SUMIF(COHVPI!A:A,Envase!R98,COHVPI!F:F) -> 0 | U98: =X98/12 -> 4244 | V98: =_xlfn.XLOOKUP(R98,'COHVPI DATAS REALIZADAS'!C:C,'COHVPI DATAS REALIZADAS'!E:E,0,0,1) -> 4244 | W98: =T98/U98 -> 0 | X98: 50928 | Y98: BAIXA DEMANDA
B99: 1964914 | C99: T26E1752 | D99: 1200 | E99: =_xlfn.XLOOKUP(B99,COHVPI!A:A,COHVPI!E:E,"-",0,1) -> 1200 | F99: 462818 | G99: SA BOZZANO DES ANTI ANTBAC FRESH NVF | I99: 46203 | M99: FALTA TAMPA 460851 (AGDO INFO) + TUBO 462797 (AGDO INFO) | O99: =_xlfn.XLOOKUP(R99,PROCX!A:A,PROCX!H:H,"-",0,1) -> - | P99: 17425-5 | Q99: BOZZANO DES ANTI ANTBAC FRESH 12X90G NVF | R99: 1964886 | S99: =_xlfn.XLOOKUP(R99,'COHVPI DATAS REALIZADAS'!C:C,'COHVPI DATAS REALIZADAS'!T:T,0,0,1) -> L40 | T99: =SUMIF(COHVPI!A:A,Envase!R99,COHVPI!F:F) -> 0 | U99: =X99/12 -> 22299 | V99: =_xlfn.XLOOKUP(R99,'COHVPI DATAS REALIZADAS'!C:C,'COHVPI DATAS REALIZADAS'!E:E,0,0,1) -> 22299 | W99: =T99/U99 -> 0 | X99: 267588 | Y99: BAIXA DEMANDA
B100: 1964915 | C100: T26E1753 | D100: 1200 | E100: =_xlfn.XLOOKUP(B100,COHVPI!A:A,COHVPI!E:E,"-",0,1) -> 1200 | F100: 462818 | G100: SA BOZZANO DES ANTI ANTBAC FRESH NVF | I100: 46203 | M100: FALTA TAMPA 460851 (AGDO INFO) + TUBO 462797 (AGDO INFO) | O100: =_xlfn.XLOOKUP(R100,PROCX!A:A,PROCX!H:H,"-",0,1) -> 0
B101: 1964916 | C101: T26E1754 | D101: 1200 | E101: =_xlfn.XLOOKUP(B101,COHVPI!A:A,COHVPI!E:E,"-",0,1) -> 1200 | F101: 462818 | G101: SA BOZZANO DES ANTI ANTBAC FRESH NVF | I101: 46203 | M101: FALTA TAMPA 460851 (AGDO INFO) + TUBO 462797 (AGDO INFO) | O101: =_xlfn.XLOOKUP(R101,PROCX!A:A,PROCX!H:H,"-",0,1) -> 0
...

Sheet Planilha1
H1: Saldo de tubos
A2: Codigo | B2: Descrição | C2: Conversor | D2: Projeto | E2: Falta Produzir Ajustado MOQ | F2: Data Programada | G2: Qtd Programada (UN) | H2: Código Tubo | I2: Dep. 1000 | J2: CQ | K2: TRIVIUM | L2: Tubos em estoque + terceiros (UN) | M2: Sobra de tubos (UN)
A3: 25642-1 | B3: MONANGE CLINICAL CONFORTO AERO 12X94G NL | C3: 12 | D3: MONTANA | E3: 50928 | F3: 46176 | G3: 50928 | H3: 468382 | I3: 57753 | L3: 57753 | M3: 6825
A4: 27213-0 | B4: MONANGE DES ANTI INVISIVEL 12X200ML | C4: 12 | D4: MONTANA | E4: 67423 | F4: 46182 | G4: 67428 | H4: 465466 | I4: 71982 | L4: 71982 | M4: 4554
A5: 17109-6 | B5: MONANGE DES ANTI FLOR LAV 12X90G NVF | C5: 12 | D5: MONTANA | E5: 89196 | F5: 46182 | G5: 89196 | H5: 462803 | I5: 4304 | K5: 85932 | L5: 90236 | M5: 1040
A6: 17110-7 | B6: MONANGE DES ANTI FRUTAS VM 12X90G NVF | C6: 12 | D6: MONTANA | E6: 89196 | F6: 46181 | G6: 89196 | H6: 462804 | I6: 39060 | K6: 53568 | L6: 92628 | M6: 3432
A7: 24630-1 | B7: MONANGE DES ANTI DETOX FRESH 12X90G NVF | C7: 12 | D7: MONTANA | E7: 89196 | F7: 46177 | G7: 89196 | H7: 462807 | I7: 46686 | J7: 43431 | L7: 90117 | M7: 921
A8: 17107-7 | B8: MONANGE DES ANTI SENSIVEL 12X90G NVF | C8: 12 | D8: MONTANA | E8: 89196 | F8: 46183 | G8: 89196 | H8: 462802 | I8: 14973 | K8: 79794 | L8: 94767 | M8: 5571
A9: 20257-3 | B9: MONANGE DES ANTI INVISIVEL 12X89G NVF | C9: 12 | D9: MONTANA | E9: 90153 | F9: 46178 | G9: 90156 | H9: 462806 | I9: 35486 | K9: 61380 | L9: 96866 | M9: 6710
A10: 27170-0 | B10: ADIDAS DES ANTI POWER BOOSTER FEM 150ML | C10: 12 | D10: REVAMP | E10: 254844 | F10: 46185 | G10: 234072 | H10: 465340 | I10: 166377 | J10: 74772 | L10: 241149 | M10: 7077
A11: 27172-0 | B11: ADIDAS DES ANTI POWER BOOSTER MASC 12X90G | C11: 12 | D11: REVAMP | E11: 84948 | F11: 46184 | G11: 89196 | H11: 465344 | I11: 90001 | L11: 90001 | M11: 805
A12: 27171-0 | B12: ADIDAS DES ANTI FRESH ENDURANCE FEM 12X90G | C12: 12 | D12: REVAMP | E12: 169896 | F12: Sem data definida | G12: 169896 | H12: 465341 | I12: 39060 | K12: 134260 | L12: 173320 | M12: 3424
A13: 20003-6 | B13: ADIDAS DES ANTI CONTROL FEM 12X90G NVF | C13: 12 | D13: REVAMP | E13: Finalizado | F13: - | G13: - | H13: 465342 | I13: 31155 | J13: 0 | L13: 31155 | M13: 31155
A14: 23208-2 | B14: ADIDAS DES ANTI INVISIBLE FEM 12X90G | C14: 12 | D14: REVAMP | E14: Finalizado | F14: - | G14: - | H14: 465339 | I14: 9686 | J14: 0 | L14: 9686 | M14: 9686
A15: 27173-0 | B15: ADIDAS DES ANTI FRESH ENDURANCE MASC 12X90G | C15: 12 | D15: REVAMP | E15: Finalizado | F15: - | G15: - | H15: 465345 | I15: 2232 | J15: 0 | L15: 2232 | M15: 2232
A16: 23209-3 | B16: ADIDAS DES ANTI INVISIBLE MASC 12X90G | C16: 12 | D16: REVAMP | E16: Finalizado | F16: - | G16: - | H16: 465343 | I16: 0 | J16: 0 | L16: 0 | M16: 0
A17: 27174-0 | B17: ADIDAS DES ANTI 6 IN 1 MASC 150ML | C17: 12 | D17: REVAMP | E17: Finalizado | F17: - | G17: - | H17: 465346 | I17: 1621 | J17: 0 | L17: 1621 | M17: 1621
A18: 17111-6 | B18: MONANGE DES ANTI HIDR INTEN 12X90G NVF | C18: 12 | D18: MONTANA | E18: Finalizado | F18: - | G18: - | H18: 465942 | I18: 27385 | J18: 0 | L18: 27385 | M18: 27385
A19: 24631-1 | B19: MONANGE DES ANTI PROTECAO SEC 12X90G NVF | C19: 12 | D19: MONTANA | E19: Finalizado | F19: - | G19: - | H19: 462808 | I19: 1959 | J19: 0 | L19: 1959 | M19: 1959
A20: 25503-0 | B20: MONANGE DES ANTI ESPORTE AERO 12X90G | C20: 12 | D20: MONTANA | E20: Finalizado | F20: - | G20: - | H20: 461763 | I20: 17391 | J20: 0 | L20: 17391 | M20: 17391
A21: 25643-1 | B21: MONANGE CLIN REVIGORANTE AERO 12X94G NL | C21: 12 | D21: MONTANA | E21: Finalizado | F21: - | G21: - | H21: 468381 | I21: 25428 | J21: 0 | L21: 25428 | M21: 25428
A22: 27211-0 | B22: MONANGE DES ANTI HIDR INTENSIVA 12X200ML | C22: 12 | D22: MONTANA | E22: Finalizado | F22: - | G22: - | H22: 465464 | I22: 11160 | J22: 0 | L22: 11160 | M22: 11160
A23: 27212-0 | B23: MONANGE DES ANTI FR VERMELHAS 12X200ML | C23: 12 | D23: MONTANA | E23: Finalizado | F23: - | G23: - | H23: 465465 | I23: 29907 | J23: 0 | L23: 29907 | M23: 29907
A24: 29555-0 | B24: MONANGE DES ANTIT PROTECAO SECA 12X200ML | C24: 12 | D24: MONTANA | E24: Finalizado | F24: - | G24: - | H24: 469541 | I24: 1850 | J24: 0 | L24: 1850 | M24: 1850
A25: 29556-0 | B25: MONANGE DES ANTIT FLOR DE LAV 12X200ML | C25: 12 | D25: MONTANA | E25: Finalizado | F25: - | G25: - | H25: 469542 | I25: 15624 | J25: 0 | L25: 15624 | M25: 15624

Sheet Acompanhamento Rupturas
A1: SKU | B1: Descrição | C1: Ruptura UG | D1: Ruptura GS | E1: Volume Programado | F1: Data | G1: Ranking | H1: Motivos | J1: 46168
A2: 27213-1 | B2: MONANGE DES ANTIT INVIS 12X200ML MT | C2: 104844 | D2: 840082.33 | E2: 404568 | F2: 09/06 a 15/06 | G2: 1 | H2: Fragrância chega dia 02/06 e primeira oportunidade de envase é dia 09/06
A3: 29552-0 | B3: BOZZANO DES ANTIT CARVAO ATIV 12X200ML | C3: 43344 | D3: 342627.66 | E3: 401400 | F3: 22/06 a 26/06 | G3: 2 | H3: Falta tampa 460851 - Se usar qtd que chega dia 27/05 na L57, teremos parada na L58
A4: 23209-5 | B4: ADIDAS DES ANTI PRO INVISIBLE MASC 150ML | C4: 28092 | D4: 230703.31 | E4: 180312 | F4: 28/05 a 29/05 | G4: 3 | H4: -
A5: 23208-4 | B5: ADIDAS DES ANTI CONTR INVISIBLE FEM 150M | C5: 25164 | D5: 197138.56 | E5: 171720 | F5: 29/05 a 30/05 | G5: 4 | H5: -
A6: 29030-0 | B6: ADIDAS DES ANTI CLINICAL CARE FEM 150ML | C6: 15492 | D6: 165354.29 | E6: 50928 | F6: 18/06 a 19/06 | G6: 5 | H6: Fragrância atrasou. Nova previsão de chegada: 15/06. Talvez haja reprogramação pro dia 19/06 por segurança
A7: 17110-7 | B7: MONANGE DES ANTI FRUTAS VM 12X90G NVF | C7: 17004 | D7: 128344.96 | E7: 89196 | F7: 08/06 a 09/06 | G7: 6 | H7: Tubo chega 03/06 - Linha rodando os Phase Out Monange. Possibilidade de inverter seq. com 20257-3
A8: 27170-0 | B8: ADIDAS DES ANTI POWER BOOSTER FEM 150ML | C8: 11988 | D8: 85913.402 | E8: 234072 | F8: 11/06 a 15/06 | G8: 7 | H8: Fragrância 465405 chega 02/06. Não programei envase para 06/06 para não quebrar sequência de marca
A9: 10909-3 | B9: BOZZANO ESPUMA BARBA REFRES 6X193G CIN | C9: 4260 | D9: 61469.295 | E9: 79980 | F9: 28/05 a 30/05 | G9: 8 | H9: -
A10: 20257-3 | B10: MONANGE DES ANTI INVISIVEL 12X89G NVF | C10: 5868 | D10: 42393.394 | E10: 90156 | F10: 05/06 a 08/06 | G10: 9 | H10: Tubo chega 03/06 - Linha rodando os Phase Out Monange
A11: 27213-0 | B11: MONANGE DES ANTI INVISIVEL 12X200ML | C11: 3516 | D11: 37498.481 | E11: 67428 | F11: 09/06 a 10/06 | G11: 10 | H11: Oportunidade (para não quebrar sequência de marca)
A12: 17111-6 | B12: MONANGE DES ANTI HIDR INTEN 12X90G NVF | C12: 4500 | D12: 32998.185 | E12: - | F12: Plano Finalizado | G12: 11 | H12: Plano Phase Out Finalizado
A13: 17109-6 | B13: MONANGE DES ANTI FLOR LAV 12X90G NVF | C13: 3600 | D13: 28102.551 | E13: 89196 | F13: 09/06 a 10/06 | G13: 12 | H13: Tubo chega 03/06 - Linha rodando os Phase Out Monange
A14: 27212-0 | B14: MONANGE DES ANTI FR VERMELHAS 12X200ML | C14: 1836 | D14: 21408.91 | E14: - | F14: Plano Finalizado | G14: 13 | H14: Plano Phase Out Finalizado
A15: 27172-0 | B15: ADIDAS DES ANTI POWER BOOSTER MASC 150ML | C15: 1248 | D15: 9014.2832 | E15: 89196 | F15: 30/05 a 02/06 | G15: 14 | H15: Fragrância atrasou - Programado para 30/05 ou 02/06
A16: 20003-6 | B16: ADIDAS DES ANTI CONTROL FEM 150ML NVF | C16: 528 | D16: 4520.12 | E16: - | F16: Ordem de retrabalho feita | G16: 15 | H16: Qualidade avaliando o retrabalho feito com esse P.A. (OP feita dia 22/05)
E17: =_xlfn.XLOOKUP(A17,$A$1:$A$16,$E$1:$E$16,0,0,1) -> 0 | F17: =_xlfn.XLOOKUP(A17,$A$1:$A$16,$F$1:$F$16,0,0,1) -> 0 | G17: 1 | H17: =_xlfn.XLOOKUP(A17,$A$1:$A$16,$H$1:$H$16,0,0,1) -> 0
A18: SKU | B18: Descrição | C18: Ruptura UG | D18: Ruptura GS | E18: Volume Programado | F18: Data | G18: Ranking | H18: Motivos | J18: 46169
A19: 29552-0 | B19: BOZZANO DES ANTIT CARVAO ATIV 12X200ML | C19: 81804 | D19: 701270.62 | E19: 401400 | F19: 22/06 a 26/06 | G19: 1 | H19: Falta tampa 460851 - Se usar qtd que chega dia 27/05 na L57, teremos parada na L58
A20: 23209-5 | B20: ADIDAS DES ANTI PRO INVISIBLE MASC 150ML | C20: 68928 | D20: 623242.14 | E20: 180312 | F20: 28/05 a 29/05 | G20: 2 | H20: -
A21: 27212-0 | B21: MONANGE DES ANTI FR VERMELHAS 12X200ML | C21: 52716 | D21: 476416.44 | E21: - | F21: Plano Finalizado | G21: 3 | H21: Plano Phase Out Finalizado
A22: 23208-4 | B22: ADIDAS DES ANTI CONTR INVISIBLE FEM 150M | C22: 41844 | D22: 354308.87 | E22: 171720 | F22: 29/05 a 30/05 | G22: 4 | H22: -
A23: 29030-0 | B23: ADIDAS DES ANTI CLINICAL CARE FEM 150ML | C23: 15624 | D23: 167570.13 | E23: 50928 | F23: 18/06 a 19/06 | G23: 5 | H23: Fragrância atrasou. Nova previsão de chegada: 15/06. Talvez haja reprogramação pro dia 19/06 por segurança
A24: 17110-7 | B24: MONANGE DES ANTI FRUTAS VM 12X90G NVF | C24: 17004 | D24: 128344.96 | E24: 89196 | F24: 08/06 a 09/06 | G24: 6 | H24: Tubo chega 03/06 - Linha rodando os Phase Out Monange. Possibilidade de inverter seq. com 20257-3
A25: 27170-0 | B25: ADIDAS DES ANTI POWER BOOSTER FEM 150ML | C25: 12540 | D25: 90152.778 | E25: 234072 | F25: 11/06 a 15/06 | G25: 7 | H25: Fragrância 465405 chega 02/06. Não programei envase para 06/06 para não quebrar sequência de marca
A26: 10909-3 | B26: BOZZANO ESPUMA BARBA REFRES 6X193G CIN | C26: 6582 | D26: 90043.06 | E26: 79980 | F26: 28/05 a 30/05 | G26: 8 | H26: -
A27: 27213-0 | B27: MONANGE DES ANTI INVISIVEL 12X200ML | C27: 5304 | D27: 54665.156 | E27: 67428 | F27: 09/06 a 10/06 | G27: 9 | H27: Oportunidade (para não quebrar sequência de marca)
A28: 25643-1 | B28: MONANGE CLIN REVIGORANTE AERO 12X94G NL | C28: 4908 | D28: 36186.146 | E28: - | F28: Plano Finalizado | G28: 10 | H28: Plano Phase Out Finalizado
A29: 27172-0 | B29: ADIDAS DES ANTI POWER BOOSTER MASC 150ML | C29: 3624 | D29: 28042.893 | E29: 89196 | F29: 30/05 a 02/06 | G29: 11 | H29: Fragrância atrasou - Programado para 30/05 ou 02/06
A30: 20003-6 | B30: ADIDAS DES ANTI CONTROL FEM 150ML NVF | C30: 528 | D30: 4520.12 | E30: - | F30: Ordem de retrabalho feita | G30: 12 | H30: Qualidade avaliando o retrabalho feito com esse P.A. (OP feita dia 22/05)
A32: SKU | B32: Descrição | C32: Ruptura UG | D32: Ruptura GS | E32: Volume Programado | F32: Data | G32: Ranking | H32: Motivos | J32: 46170
A33: 24631-1 | B33: MONANGE DES ANTI PROTECAO SEC 12X90G NVF | C33: 241164 | D33: 1423942.3 | E33: - | F33: Plano Finalizado | G33: 1 | H33: Plano Phase Out Finalizado
A34: 29552-0 | B34: BOZZANO DES ANTIT CARVAO ATIV 12X200ML | C34: 114228 | D34: 966540.92 | E34: 401400 | F34: 22/06 a 26/06 | G34: 2 | H34: Falta tampa 460851 - Se usar qtd que chega dia 27/05 na L57, teremos parada na L58
A35: 23209-5 | B35: ADIDAS DES ANTI PRO INVISIBLE MASC 150ML | C35: 105132 | D35: 924139.99 | E35: 180312 | F35: 28/05 a 29/05 | G35: 3 | H35: -
A36: 24630-1 | B36: MONANGE DES ANTI DETOX FRESH 12X90G NVF | C36: 148956 | D36: 888537.83 | E36: 89196 | F36: 04/06 a 05/06 | G36: 4 | H36: Ultima produção Phase Out Montana - Tubo chega 02/06
A37: 23208-4 | B37: ADIDAS DES ANTI CONTR INVISIBLE FEM 150M | C37: 64896 | D37: 555549.2 | E37: 171720 | F37: 29/05 a 30/05 | G37: 5 | H37: -
A38: 27212-0 | B38: MONANGE DES ANTI FR VERMELHAS 12X200ML | C38: 50748 | D38: 460495.57 | E38: - | F38: Plano Finalizado | G38: 6 | H38: Plano Phase Out Finalizado
A39: 27211-0 | B39: MONANGE DES ANTI HIDR INTENSIVA 12X200ML | C39: 53556 | D39: 397684.85 | E39: - | F39: Plano Finalizado | G39: 7 | H39: Plano Phase Out Finalizado
A40: 17109-7 | B40: MONANGE DES ANTIT FL LAV 12X90G MT | C40: 57012 | D40: 339318.29 | E40: 624732 | F40: 27/05 a 03/06 | G40: 8 | H40: Em campanha na L40
A41: 10909-3 | B41: BOZZANO ESPUMA BARBA REFRES 6X193G CIN | C41: 17010 | D41: 218309.21 | E41: 79980 | F41: 28/05 a 30/05 | G41: 9 | H41: -
A42: 27213-1 | B42: MONANGE DES ANTIT INVIS 12X200ML MT | C42: 24960 | D42: 207071.41 | E42: 404568 | F42: Sem nova data | G42: 10 | H42: Fragrância chega dia 12/06
A43: 29030-0 | B43: ADIDAS DES ANTI CLINICAL CARE FEM 150ML | C43: 17748 | D43: 190555.14 | E43: 50928 | F43: 18/06 a 19/06 | G43: 11 | H43: Fragrância atrasou. Nova previsão de chegada: 15/06. Talvez haja reprogramação pro dia 19/06 por segurança
A44: 25643-1 | B44: MONANGE CLIN REVIGORANTE AERO 12X94G NL | C44: 18756 | D44: 139933.67 | E44: - | F44: - | G44: 12 | H44: Plano Phase Out Finalizado - Ordem de retrabalho (castelo amassado) em aberto (2570 cx)
A45: 17110-7 | B45: MONANGE DES ANTI FRUTAS VM 12X90G NVF | C45: 17004 | D45: 128344.96 | E45: 89196 | F45: 08/06 a 09/06 | G45: 13 | H45: Tubo chega 03/06 - Linha rodando os Phase Out Monange. Possibilidade de inverter seq. com 20257-3
A46: 25503-0 | B46: MONANGE DES ANTI ESPORTE AERO 12X90G | C46: 20052 | D46: 123252.22 | E46: - | F46: Plano Finalizado | G46: 6 | H46: Plano Phase Out Finalizado
A47: 27170-0 | B47: ADIDAS DES ANTI POWER BOOSTER FEM 150ML | C47: 15336 | D47: 106407.35 | E47: 234072 | F47: 11/06 a 15/06 | G47: 15 | H47: Fragrância 465405 chega 02/06. Não programei envase para 06/06 para não quebrar sequência de marca
A48: 27213-0 | B48: MONANGE DES ANTI INVISIVEL 12X200ML | C48: 11904 | D48: 94309.629 | E48: 67428 | F48: 09/06 a 10/06 | G48: 16 | H48: Oportunidade (para não quebrar sequência de marca)
A49: 27172-0 | B49: ADIDAS DES ANTI POWER BOOSTER MASC 150ML | C49: 10812 | D49: 88244.779 | E49: 89196 | F49: 30/05 a 02/06 | G49: 17 | H49: Fragrância atrasou - Programado para 30/05 ou 02/06
A50: 20003-6 | B50: ADIDAS DES ANTI CONTROL FEM 150ML NVF | C50: 528 | D50: 4520.12 | E50: - | F50: Ordem de retrabalho feita | G50: 18 | H50: Qualidade avaliando o retrabalho feito com esse P.A. (OP feita dia 22/05)
A53: 46171 | D53: =SUM(D55:D81) -> 18418211 | E53: =SUM(E55:E81) -> 18418211
A54: SKU | B54: Descrição | C54: Ruptura UG | D54: Ruptura GS | E54: Ruptura GS | F54: Resumo | G54: Volume Programado | H54: Data | I54: Ranking | J54: Motivos
A55: 24631-1 | B55: MONANGE DES ANTI PROTECAO SEC 12X90G NVF | C55: 287100 | D55: 1697738.3 | E55: =SUM(D55:D61) -> 3938696 | F55: Phase out finalizado | G55: - | H55: Plano Finalizado | I55: 3 | J55: Plano Phase Out Finalizado
A56: 25503-0 | B56: MONANGE DES ANTI ESPORTE AERO 12X90G | C56: 150372 | D56: 926605.69 | G56: - | H56: Plano Finalizado | I56: 10 | J56: Plano Phase Out Finalizado
A57: 27211-0 | B57: MONANGE DES ANTI HIDR INTENSIVA 12X200ML | C57: 77628 | D57: 576433.64 | G57: - | H57: Plano Finalizado | I57: 12 | J57: Plano Phase Out Finalizado
A58: 27212-0 | B58: MONANGE DES ANTI FR VERMELHAS 12X200ML | C58: 56952 | D58: 516791.67 | G58: - | H58: Plano Finalizado | I58: 14 | J58: Plano Phase Out Finalizado
A59: 25643-1 | B59: MONANGE CLIN REVIGORANTE AERO 12X94G NL | C59: 20220 | D59: 153335.53 | G59: - | H59: Plano Finalizado | I59: 18 | J59: Plano Phase Out Finalizado
A60: 17111-6 | B60: MONANGE DES ANTI HIDR INTEN 12X90G NVF | C60: 8268 | D60: 63373.721 | G60: - | H60: Plano Finalizado | I60: 23 | J60: Plano Phase Out Finalizado
A61: 20003-6 | B61: ADIDAS DES ANTI CONTROL FEM 150ML NVF | C61: 516 | D61: 4417.39 | G61: - | H61: Plano Finalizado | I61: 27 | J61: Plano Phase Out Finalizado - Ordem de retrabalho (castelo amassado) em aberto (2.570 cx)
A62: 17109-7 | B62: MONANGE DES ANTIT FL LAV 12X90G MT | C62: 468696 | D62: 2790722.1 | E62: =SUM(D62:D65) -> 5561965.6 | F62: Em linha | G62: 624372 | H62: 27/05 a 03/06 | I62: 1 | J62: Em linha
A63: 17110-8 | B63: MONANGE DES ANTIT FRTS VM 12X90G MT | C63: 411072 | D63: 2455025.8 | G63: 356784 | H63: 29/05 a 30/05 | I63: 2 | J63: Em linha
A64: 10909-3 | B64: BOZZANO ESPUMA BARBA REFRES 6X193G CIN | C64: 17184 | D64: 221388.8 | G64: 79980 | H64: 46171 | I64: 16 | J64: Em linha
A65: 27212-1 | B65: MONANGE DES ANTIT FR VM 12X200ML MT | C65: 12564 | D65: 94828.892 | G65: 195732 | H65: 46171 | I65: 21 | J65: Em linha
A66: 24630-1 | B66: MONANGE DES ANTI DETOX FRESH 12X90G NVF | C66: 246012 | D66: 1469286.5 | E66: =SUM(D66:D70) -> 2075190 | F66: Phase out em produção | G66: 89196 | H66: 46177 | I66: 4 | J66: Ultima produção Phase Out Montana - Tubo chega 02/06
A67: 27213-0 | B67: MONANGE DES ANTI INVISIVEL 12X200ML | C67: 50436 | D67: 399580.01 | G67: 67428 | H67: 46182 | I67: 15 | J67: Ultima produção Phase Out Montana - Rodaremos pós campanha de Bozzano
A68: 17110-7 | B68: MONANGE DES ANTI FRUTAS VM 12X90G NVF | C68: 17004 | D68: 128344.96 | G68: 89196 | H68: 46181 | I68: 19 | J68: Ultima produção Phase Out Montana - Tubo chega 03/06
A69: 17109-6 | B69: MONANGE DES ANTI FLOR LAV 12X90G NVF | C69: 7380 | D69: 56306.569 | G69: 89196 | H69: 46182 | I69: 25 | J69: Ultima produção Phase Out Montana - Tubo chega 03/06
A70: 20257-3 | B70: MONANGE DES ANTI INVISIVEL 12X89G NVF | C70: 2868 | D70: 21671.934 | G70: 90156 | H70: 46178 | I70: 26 | J70: Ultima produção Phase Out Montana - Tubo chega 03/06
A71: 25003-1 | B71: BOZZANO DES ANTI DRY 12X90G NVF | C71: 181140 | D71: 1112573.9 | E71: =SUM(D71:D74) -> 3361712.1 | F71: Em programação W+1 | G71: 267588 | H71: 30/05 a 03/06 | I71: 6 | J71: Próximo SKU a rodar na L58
A72: 27215-0 | B72: BOZZANO DES ANTI INVISIBLE 12X200ML | C72: 110280 | D72: 942492.53 | G72: 134928 | H72: 46176 | I72: 8 | J72: Rodaremos pós campanha de Espuma (em linha)
A73: 20159-4 | B73: BOZZANO DES ANTI INVISIBLE 12X89G NVF | C73: 121560 | D73: 748799.79 | G73: 270468 | H73: 46176 | I73: 11 | J73: Rodaremos após SKU TOP 6 ruptura - L58
A74: 23208-4 | B74: ADIDAS DES ANTI CONTR INVISIBLE FEM 150M | C74: 65136 | D74: 557845.8 | G74: 171720 | H74: 46171 | I74: 13 | J74: Próximo SKU a rodar na L53
A75: 23209-5 | B75: ADIDAS DES ANTI PRO INVISIBLE MASC 150ML | C75: 106020 | D75: 931977.06 | E75: =SUM(D75:D76) -> 993316.52 | F75: Em programação W+3 | G75: 270468 | H75: 46188 | I75: 9 | J75: Colocamos pós Phase Out Monange
A76: 17111-7 | B76: MONANGE DES ANTIT HIDR INTEN 12X90G MT | C76: 10164 | D76: 61339.456 | G76: 981156 | H76: 15/06 a 20/06 | I76: 24 | J76: Produzimos 346k entre 23 e 27/05. Entraremos novamente dia 15/06 por falta atual de tubo (chega 10/06)
A77: 27213-1 | B77: MONANGE DES ANTIT INVIS 12X200ML MT | C77: 134700 | D77: 1118265.4 | E77: =SUM(D77:D81) -> 2487331.1 | F77: Falta Material | G77: 404568 | H77: - | I77: 5 | J77: Fragrância 469948 chega 12/06
A78: 29552-0 | B78: BOZZANO DES ANTIT CARVAO ATIV 12X200ML | C78: 115212 | D78: 975505.6 | G78: 401400 | H78: - | I78: 7 | J78: Tampa 460851 chega 12/06
A79: 27170-0 | B79: ADIDAS DES ANTI POWER BOOSTER FEM 150ML | C79: 15384 | D79: 106740.39 | G79: 234072 | H79: - | I79: 20 | J79: Fragrância 465406 com divergência (Em CQ aguardando P&D)
A80: 27172-0 | B80: ADIDAS DES ANTI POWER BOOSTER MASC 150ML | C80: 10956 | D80: 89420.07 | G80: 178392 | H80: - | I80: 22 | J80: Fragrância 465406 com divergência (Em CQ aguardando P&D)
A81: 29030-0 | B81: ADIDAS DES ANTI CLINICAL CARE FEM 150ML | C81: 18348 | D81: 197399.64 | G81: 89196 | H81: 46191 | I81: 17 | J81: Fragrância 465410 chega 15/06
A83: 46176 | D83: =SUM(D85:D96) -> 3328305.5 | E83: =SUM(E85:E101) -> 8616953.6
A84: SKU | B84: Descrição | C84: Ruptura UG | D84: Ruptura GS | E84: Ruptura GS | F84: Resumo | G84: Volume Programado | H84: Data | I84: Ranking | J84: Motivos
A85: 25503-0 | B85: MONANGE DES ANTI ESPORTE AERO 12X90G | C85: 1428 | D85: 8350.5077 | E85: =D85 -> 8350.5077 | F85: Phase out finalizado | G85: - | H85: Plano Finalizado | I85: 12 | J85: Plano Phase Out Finalizado
A86: 23208-4 | B86: ADIDAS DES ANTI CONTR INVISIBLE FEM 150M | C86: 69324 | D86: 587674.56 | E86: =D87+D86 -> 886335.53 | F86: OP finalizada | G86: - | H86: - | I86: 2 | J86: Ordem com 170k un finalizada dia 02/06
A87: 10909-3 | B87: BOZZANO ESPUMA BARBA REFRES 6X193G CIN | C87: 22386 | D87: 298660.97 | G87: - | H87: - | I87: 4 | J87: Ordem com 31k un finalizada dia 31/05
A88: 25003-1 | B88: BOZZANO DES ANTI DRY 12X90G NVF | C88: 9768 | D88: 71878.125 | E88: =D88 -> 71878.125 | F88: Em linha | G88: 267588 | H88: 30/05 a 03/06 | I88: 10 | J88: Em linha
A89: 17110-7 | B89: MONANGE DES ANTI FRUTAS VM 12X90G NVF | C89: 10188 | D89: 82546.727 | E89: =D89+D90 -> 127060.16 | F89: Phase out em produção | G89: 89196 | H89: 46178 | I89: 9 | J89: Última produção Phase Out Montana - Tubo chega 03/06
A90: 20257-3 | B90: MONANGE DES ANTI INVISIVEL 12X89G NVF | C90: 5460 | D90: 44513.436 | G90: 90156 | H90: 46177 | I90: 11 | J90: Última produção Phase Out Montana - Tubo chega 03/06
A91: 27213-1 | B91: MONANGE DES ANTIT INVIS 12X200ML MT | C91: 59808 | D91: 505309.63 | E91: =D91+D92+D93 -> 824593.33 | F91: Em programação W+1 | G91: 404528 | H91: 46185 | I91: 3 | J91: Fragrância 469948 chega 04/06. Podemos reprogramar para dia 10/06
A92: 27215-0 | B92: BOZZANO DES ANTI INVISIBLE 12X200ML | C92: 21792 | D92: 202643.73 | G92: 404784 | H92: 46176 | I92: 5 | J92: Próximo SKU a rodar na L57
A93: 27172-0 | B93: ADIDAS DES ANTI POWER BOOSTER MASC 150ML | C93: 14328 | D93: 116639.97 | G93: 89196 | H93: 46183 | I93: 8 | J93: Rodaremos pós campanha de Phase Out Monange (L40)
A94: 27170-0 | B94: ADIDAS DES ANTI POWER BOOSTER FEM 150ML | C94: 16776 | D94: 117795.27 | E94: =D94 -> 117795.27 | F94: Em programação W+2 | G94: 234072 | H94: 46188 | I94: 7 | J94: Fragrância 465405 chega 10/06
A95: 29552-0 | B95: BOZZANO DES ANTIT CARVAO ATIV 12X200ML | C95: 129096 | D95: 1089893.8 | E95: =D95+D96 -> 1292292.5 | F95: Falta Material | G95: 401400 | H95: 46192 | I95: 1 | J95: Importação de tampa 460851 chega dia 12/06 (data não confirmada pela lindal)
A96: 29030-0 | B96: ADIDAS DES ANTI CLINICAL CARE FEM 150ML | C96: 18576 | D96: 202398.73 | G96: 50928 | H96: 46195 | I96: 6 | J96: Fragrância 465410 chega 15/06
A98: 46181 | D98: =SUM(D100:D110) -> 4449730.5 | E98: =SUM(E100:E110) -> 4449730.5
A99: SKU | B99: Descrição | C99: Ruptura UG | D99: Ruptura GS | E99: Ruptura GS | F99: Resumo | G99: Volume Programado | H99: Data | I99: Ranking | J99: Motivos
A100: 25503-0 | B100: MONANGE DES ANTI ESPORTE AERO 12X90G | C100: 1428 | D100: 8348.08 | E100: =D100 -> 8348.08 | F100: Phase out finalizado | G100: - | H100: - | I100: 12 | J100: Plano Phase Out Finalizado
A101: 20257-3 | B101: MONANGE DES ANTI INVISIVEL 12X89G NVF | C101: 56484 | D101: 437577.56 | E101: =SUM(D101:D102) -> 830569.55 | F101: OP finalizada | G101: - | H101: - | I101: 4 | J101: Produção de 89k entre 05 e 06/06
A102: 10909-3 | B102: BOZZANO ESPUMA BARBA REFRES 6X193G CIN | C102: 29688 | D102: 392991.99 | G102: - | H102: - | I102: 6 | J102: Produção de 155k entre 29 e 31/05
A103: 27215-0 | B103: BOZZANO DES ANTI INVISIBLE 12X200ML | C103: 58968 | D103: 533367.72 | E103: =SUM(D103:D104) -> 950067.31 | F103: Em linha | G103: 269856 | H103: 04/06 a 09/06 | I103: 3 | J103: Em linha (L57)
A104: 17110-7 | B104: MONANGE DES ANTI FRUTAS VM 12X90G NVF | C104: 53280 | D104: 416699.59 | G104: 89196 | H104: 05/06 a 09/06 | I104: 5 | J104: Em linha (L40)
A105: 27213-1 | B105: MONANGE DES ANTIT INVIS 12X200ML MT | C105: 107136 | D105: 860326.84 | E105: =SUM(D105:D106) -> 993996.16 | F105: Em programação W+1 | G105: 404528 | H105: 10/06 a 16/06 | I105: 2 | J105: Podemos rodar só 3 lotes (=202.264 un) para tentar antecipar SKU TOP1 ruptura
...

Sheet PROCX
A1: Ordem | B1: Material | C1: Lista comp.item | D1: Requirement date | E1: Qtd.necessária (EINHEIT) | F1: Qtd.retirada (EINHEIT) | G1: Qtd.pendente (EINHEIT) | H1: UM básica (=EINHEIT)
A2: 1962360 | B2: 452602 | C2: 0050 | D2: 46176 | E2: 135467.71 | F2: 36144 | G2: 0 | H2: ok
A3: 1963469 | B3: 452602 | C3: 0050 | D3: 46176 | E3: 271549.87 | F3: 137323.1 | G3: 0 | H3: ok
A4: 1962361 | B4: 452602 | C4: 0050 | D4: 46178 | E4: 135467.71 | F4: 97757.472 | G4: 36000 | H4: ok
A5: 1963058 | B5: 452602 | C5: 0050 | D5: 46181 | E5: 135467.71 | F5: 0 | G5: 135467.71 | H5: ok
A6: 1963470 | B6: 452602 | C6: 0050 | D6: 46198 | E6: 271549.87 | F6: 0 | G6: 271549.87 | H6: import
A7: 1963493 | B7: 452602 | C7: 0050 | D7: 46203 | E7: 77793.936 | F7: 0 | G7: 77793.936 | H7: import
A8: 1964887 | B8: 452602 | C8: 0030 | D8: 46203 | E8: 51131.712 | F8: 0 | G8: 51131.712 | H8: import
G10: 42
G11: 660 | H11: dia 08

Sheet NPD + Esgotamentos
F2: =SUM(F4:F17) -> 1402202 | G2: =SUM(G4:G17) -> 602076 | H2: =SUM(H4:H17) -> 801377
B3: Motivo | C3: SKU | D3: Descrição | E3: Plano Pendente excl NPD | F3: Plano Pendente Dash NPD 28/04 | G3: Realizado entre 29 e 13/05 | H3: Plano Pendente Atualizado 13/05 | I3: Volume Próximo Envase | J3: Data Prev. Envase | K3: Obs
B4: Phase Out para Montana | C4: 25642-1 | D4: MONANGE CLINICAL CONFORTO AERO 12X94G NL | F4: =VLOOKUP(C4,'[4]Phase out '!$A:$G,7,0) -> 50928 | H4: =F4-G4 -> 50928 | I4: 50928 | J4: 46176 | K4: Tubo 468382 chega 02/06
B5: Phase Out para Montana | C5: 17110-7 | D5: MONANGE DES ANTI FRUTAS VM 12X90G NVF | F5: =VLOOKUP(C5,'[4]Phase out '!$A:$G,7,0) -> 89196 | H5: =F5-G5 -> 89196 | I5: 89196 | J5: 46181 | K5: Tubo 462804 chega 03/06
B6: Phase Out para Montana | C6: 24630-1 | D6: MONANGE DES ANTI DETOX FRESH 12X90G NVF | F6: =VLOOKUP(C6,'[4]Phase out '!$A:$G,7,0) -> 89196 | H6: =F6-G6 -> 89196 | I6: 89196 | J6: 46177 | K6: Tubo 462807 chega 03/06
B7: Phase Out para Montana | C7: 20257-3 | D7: MONANGE DES ANTI INVISIVEL 12X89G NVF | F7: 90153 | H7: =F7-G7 -> 90153 | I7: =180312/2 -> 90156 | J7: 46178 | K7: Tubo 462806 chega 03/06
B8: Phase Out para Montana | C8: 17107-7 | D8: MONANGE DES ANTI SENSIVEL 12X90G NVF | F8: =VLOOKUP(C8,'[4]Phase out '!$A:$G,7,0) -> 267588 | G8: 178392 | H8: =F8-G8 -> 89196 | I8: 89196 | J8: 46183 | K8: Tubo 462802 chega 04/06
B9: Phase Out para Montana | C9: 17109-6 | D9: MONANGE DES ANTI FLOR LAV 12X90G NVF | F9: =VLOOKUP(C9,'[4]Phase out '!$A:$G,7,0) -> 267588 | G9: 178392 | H9: =F9-G9 -> 89196 | I9: 89196 | J9: 46182 | K9: Tubo 462803 chega 04/06
B10: Phase Out para Montana | C10: 27212-0 | D10: MONANGE DES ANTI FR VERMELHAS 12X200ML | F10: =VLOOKUP(C10,'[4]Phase out '!$A:$G,7,0) -> 66894 | G10: 66900 | H10: =F10-G10 -> -6 | J10: - | K10: FINALIZADO
B11: Phase Out para Montana | C11: 17111-6 | D11: MONANGE DES ANTI HIDR INTEN 12X90G NVF | F11: =VLOOKUP(C11,'[4]Phase out '!$A:$G,7,0) -> 178392 | G11: 178392 | H11: =F11-G11 -> 0 | J11: - | K11: FINALIZADO
B12: Phase Out para Montana | C12: 27213-0 | D12: MONANGE DES ANTI INVISIVEL 12X200ML | F12: =VLOOKUP(C12,'[4]Phase out '!$A:$G,7,0) -> 67423 | H12: =F12-G12 -> 67423 | I12: 67428 | J12: 46182
C13: 27170-0 | D13: ADIDAS DES ANTI POWER BOOSTER FEM 150ML | F13: 234844 | I13: 234072 | J13: 46185 | K13: Fragrância 465405 chega 02/06
B14: Tubo 465344 com vencimento em 08/26 | C14: 27172-0 | D14: ADIDAS DES ANTI POWER BOOSTER MASC 150ML | E14: 17133 | I14: 89196 | J14: 46184
B15: Esgotamento tubo 468239 | C15: 29028-0 | D15: ADIDAS DES ANTI CLINICAL DRY MASC 150ML | E15: 123876 | F15: 0 | H15: 123876 | J15: Julho | K15: Tubo novo: 469926
B16: Esgotamento tubo 468240 | C16: 29029-0 | D16: ADIDAS DES ANTI CLINICAL FRESH MAS 150ML | E16: 112219 | F16: 0 | H16: 112219 | J16: Julho | K16: Tubo novo: 469927
B17: Esgotamento 468506 (TUBO - AGORA) e 467709 (TAMPA - POSTERIORMENTE) | C17: 29140-0 | D17: ADIDAS DES ANTI UEFA GOAL 150ML 12UN | F17: 0 | J17: Julho
B18: PHASE OUT REVAMP | C18: 27171-0 | D18: ADIDAS DES ANTI FRESH ENDURANCE FEM 12X90G | E18: 168896 | J18: PROGRAMAR JUNHO | K18: Fragrância 465410 chega 02/06 - Vou verificar a inserção dele na prog | L18: =_xlfn.XLOOKUP(C18,Planilha1!A:A,Planilha1!G:G,0,0,1) -> 169896 | M18: =_xlfn.XLOOKUP(C18,Planilha1!A:A,Planilha1!F:F,0,0,1) -> Sem data definida

Sheet P&D
A1: Cód. PA | B1: Descrição | C1: Cód. SA | D1: Status | E1: Fabricação | F1: Envase | I1: Material | J1: Texto Produto Acabado | K1: Datas previstas | L1: Qtd (CX) | O1: Material | P1: Texto Produto Acabado | Q1: Categoria / Marca | R1: VERP - Tubo | S1: Tubo | T1: VERP - Tampa | U1: Tampa | V1: ROH | W1: Fragrância | X1: VERP - Válvula | Y1: Válvula | Z1: Autonomia | AA1: SIM
A2: 25643-2 | B2: MONANGE CLIN REVIGORANTE AERO 12X94G MT | C2: 469964 | D2: PLANNED | E2: 28/04 | F2: 29/04 | I2: 27170-0 | J2: ADIDAS DES ANTI POWER BOOSTER FEM 150ML | K2: 46168 | L2: 21237 | O2: 20003-5 | P2: ADIDAS DES AE C&C CONTROL FE AP12X150 NF | Q2: ADIDAS | R2: 460954 | S2: Não | T2: 451922 | U2: Não | W2: Não | X2: 451507 | Y2: Não | Z2: =IF(AND(S2="Sim",U2="Sim",W2="Sim"),"Sim","Não") -> Não | AA2: =COUNTIF(S2:Z2,"Sim") -> 0
A3: 24630-2 | B3: MONANGE DES ANTIT DETOX FRESH 12X90G MT | C3: 469965 | D3: PLANNED | E3: 28/04 a 01/05 | F3: 29/04 a 04/05 | I3: 27172-0 | J3: ADIDAS DES ANTI POWER BOOSTER MASC 150ML | K3: 46171 | L3: 7433 | O3: 20006-5 | P3: ADIDAS DES AE C&C FRESH FE AP 12X150 NF | Q3: ADIDAS | R3: 460955 | S3: Não | T3: 451922 | U3: Não | W3: Não | X3: 451507 | Y3: Não | Z3: =IF(AND(S3="Sim",U3="Sim",W3="Sim"),"Sim","Não") -> Não | AA3: =COUNTIF(S3:Z3,"Sim") -> 0
A4: 25503-1 | B4: MONANGE DES ANTIT ESPORTE AERO 12X90G MT | C4: 469966 | D4: PLANNED | E4: 01/07 | F4: 01/07 | I4: 29140-0 | J4: ADIDAS DES ANTI UEFA GOAL 150ML 12UN | K4: 46170 | L4: 7079 | O4: 20019-3 | P4: ADIDAS DES AE C&C DRYPOWER M AP 12X150SI | Q4: ADIDAS | R4: 456067 | S4: Não | T4: 452006 | W4: Não | X4: 451507 | Y4: Não | Z4: =IF(AND(S4="Sim",U4="Sim",W4="Sim"),"Sim","Não") -> Não | AA4: =COUNTIF(S4:Z4,"Sim") -> 0
A5: 29556-1 | B5: MONANGE DES ANTIT FLOR LAVAN 12X200ML MT | C5: 469967 | D5: PLANNED | E5: 01/07 | F5: 01/07 | I5: 29030-0 | J5: ADIDAS DES ANTI CLINICAL CARE FEM 150ML | K5: 46174 | L5: 4244 | O5: 20125-0 | P5: ADIDAS DES AER CLIMACOOL MAS AP 12X150ML | Q5: ADIDAS | R5: 456070 | S5: Não | T5: 452006 | W5: Não | X5: 451507 | Y5: Não | Z5: =IF(AND(S5="Sim",U5="Sim",W5="Sim"),"Sim","Não") -> Não | AA5: =COUNTIF(S5:Z5,"Sim") -> 0
A6: 27212-1 | B6: MONANGE DES ANTIT FR VERMELH 12X200ML MT | C6: 469968 | D6: PLANNED | E6: 26/05 | F6: 27/05 | I6: Total programado | L6: =SUM(L2:L5) -> 39993 | O6: 20266-0 | P6: ADIDAS DES AERO ADIPOWER FEM AP 150ML | Q6: ADIDAS | R6: 452609 | S6: Não | T6: 451922 | U6: Não | W6: Não | X6: 451507 | Y6: Não | Z6: =IF(AND(S6="Sim",U6="Sim",W6="Sim"),"Sim","Não") -> Não | AA6: =COUNTIF(S6:Z6,"Sim") -> 0
A7: 27211-1 | B7: MONANGE DES ANTIT HID INTENS 12X200ML MT | C7: 469969 | D7: PLANNED | E7: 30/04 a 07/05 | F7: 01/05 a 08/05 | I7: A programar (considerando estoque externo = 79.912 un) | L7: =79916-L6 -> 39923 | O7: 20267-0 | P7: ADIDAS DES AERO ADIPOWER MAS AP 150ML | Q7: ADIDAS | R7: 452610 | S7: Não | T7: 452006 | W7: Não | X7: 451507 | Y7: Não | Z7: =IF(AND(S7="Sim",U7="Sim",W7="Sim"),"Sim","Não") -> Não | AA7: =COUNTIF(S7:Z7,"Sim") -> 0
A8: 27213-1 | B8: MONANGE DES ANTIT INVISIVEL 12X200ML MT | C8: 469970 | D8: PLANNED | E8: 21/05 a 26/05 | F8: 22/05 a 27/05 | O8: 23208-0 | P8: ADIDAS DES AERO INVISIBLE FEM AP 150ML | Q8: ADIDAS | R8: 456775 | S8: Não | T8: 451922 | U8: Não | W8: Não | X8: 451507 | Y8: Não | Z8: =IF(AND(S8="Sim",U8="Sim",W8="Sim"),"Sim","Não") -> Não | AA8: =COUNTIF(S8:Z8,"Sim") -> 0
A9: 29555-1 | B9: MONANGE DES ANTIT PROT SECA 12X200ML MT | C9: 469971 | D9: PLANNED | E9: 28/05 | F9: 29/05 | O9: 23209-2 | P9: ADIDAS DES AE INVISIBLE MAS AP 12X150 NF | Q9: ADIDAS | R9: 460956 | S9: Não | T9: 452006 | W9: Não | X9: 451507 | Y9: Não | Z9: =IF(AND(S9="Sim",U9="Sim",W9="Sim"),"Sim","Não") -> Não | AA9: =COUNTIF(S9:Z9,"Sim") -> 0
O10: 20020-3 | P10: ADIDAS DES AE C&C SPORTENER M AP12X150SI | Q10: ADIDAS | R10: 452899 | S10: Não | T10: 452006 | W10: Não | X10: 451507 | Y10: Não | Z10: =IF(AND(S10="Sim",U10="Sim",W10="Sim"),"Sim","Não") -> Não | AA10: =COUNTIF(S10:Z10,"Sim") -> 0
O11: 20124-0 | P11: ADIDAS DES AER CLIMACOOL FEM AP 12X150ML | Q11: ADIDAS | R11: 456069 | S11: Não | T11: 451922 | U11: Não | W11: Não | X11: 451507 | Y11: Não | Z11: =IF(AND(S11="Sim",U11="Sim",W11="Sim"),"Sim","Não") -> Não | AA11: =COUNTIF(S11:Z11,"Sim") -> 0
O12: 23208-2 | P12: ADIDAS DES ANTI INVISIBLE FEM 150ML NVF | Q12: ADIDAS - GREGOS | R12: 465339 | S12: Não | T12: 451922 | U12: Não | W12: Não | X12: 451507 | Y12: Não | Z12: =IF(AND(S12="Sim",U12="Sim",W12="Sim"),"Sim","Não") -> Não | AA12: =COUNTIF(S12:Z12,"Sim") -> 0
O13: 23209-3 | P13: ADIDAS DES ANTI INVISIBLE MASC 150ML NVF | Q13: ADIDAS - GREGOS | R13: 465343 | S13: Não | T13: 452006 | U13: Não | W13: Sim | X13: 451507 | Y13: Não | Z13: =IF(AND(S13="Sim",U13="Sim",W13="Sim"),"Sim","Não") -> Não | AA13: =COUNTIF(S13:Z13,"Sim") -> 1
O14: 20003-6 | P14: ADIDAS DES ANTI CONTROL FEM 150ML NVF | Q14: ADIDAS - GREGOS | R14: 465342 | S14: Não | T14: 451922 | U14: Não | W14: Sim | X14: 451507 | Y14: Não | Z14: =IF(AND(S14="Sim",U14="Sim",W14="Sim"),"Sim","Não") -> Não | AA14: =COUNTIF(S14:Z14,"Sim") -> 1
O15: 27170-0 | P15: ADIDAS DES ANTI POWER BOOSTER FEM 150ML | Q15: ADIDAS - GREGOS | R15: 465340 | S15: Não | T15: 451922 | U15: Não | W15: Não | X15: 451507 | Y15: Não | Z15: =IF(AND(S15="Sim",U15="Sim",W15="Sim"),"Sim","Não") -> Não | AA15: =COUNTIF(S15:Z15,"Sim") -> 0
O16: 27171-0 | P16: ADIDAS DES ANTI FRESH ENDURANCE FEM 150M | Q16: ADIDAS - GREGOS | R16: 465341 | S16: Sim | T16: 451922 | U16: Não | W16: Não | X16: 451507 | Y16: Não | Z16: =IF(AND(S16="Sim",U16="Sim",W16="Sim"),"Sim","Não") -> Não | AA16: =COUNTIF(S16:Z16,"Sim") -> 1
O17: 27172-0 | P17: ADIDAS DES ANTI POWER BOOSTER MASC 150ML | Q17: ADIDAS - GREGOS | R17: 465344 | S17: Não | T17: 452006 | U17: Não | W17: Não | X17: 451507 | Y17: Não | Z17: =IF(AND(S17="Sim",U17="Sim",W17="Sim"),"Sim","Não") -> Não | AA17: =COUNTIF(S17:Z17,"Sim") -> 0
O18: 27173-0 | P18: ADIDAS DES ANTI FR ENDURANCE MASC 150ML | Q18: ADIDAS - GREGOS | R18: 465345 | S18: Não | T18: 452006 | U18: Não | W18: Sim | X18: 451507 | Y18: Não | Z18: =IF(AND(S18="Sim",U18="Sim",W18="Sim"),"Sim","Não") -> Não | AA18: =COUNTIF(S18:Z18,"Sim") -> 1
O19: 27174-0 | P19: ADIDAS DES ANTI 6 IN 1 MASC 150ML | Q19: ADIDAS - GREGOS | R19: 465346 | S19: Não | T19: 452006 | U19: Não | W19: Não | X19: 451507 | Y19: Não | Z19: =IF(AND(S19="Sim",U19="Sim",W19="Sim"),"Sim","Não") -> Não | AA19: =COUNTIF(S19:Z19,"Sim") -> 0
O20: 27175-0 | P20: ADIDAS DES ANTI UEFA MASC 150ML | Q20: ADIDAS - GREGOS | R20: 465347 | S20: Não | T20: 451923 | U20: Não | W20: Não | X20: 451507 | Y20: Não | Z20: =IF(AND(S20="Sim",U20="Sim",W20="Sim"),"Sim","Não") -> Não | AA20: =COUNTIF(S20:Z20,"Sim") -> 0
O21: 29140-0 | P21: ADIDAS DES ANTI UEFA GOAL 150ML 12UN | Q21: ADIDAS - GREGOS | R21: 468506 | S21: Não | T21: 467709 | U21: Sim | W21: Sim | X21: 451507 | Y21: Não | Z21: =IF(AND(S21="Sim",U21="Sim",W21="Sim"),"Sim","Não") -> Não | AA21: =COUNTIF(S21:Z21,"Sim") -> 2
O22: 29028-0 | P22: ADIDAS DES ANTI CLINICAL DRY MASC 150ML | Q22: ADIDAS - CLINICAL | R22: 468239 | S22: Não | T22: 467708 | U22: Não | W22: Sim | X22: 451507 | Y22: Não | Z22: =IF(AND(S22="Sim",U22="Sim",W22="Sim"),"Sim","Não") -> Não | AA22: =COUNTIF(S22:Z22,"Sim") -> 1
... O25: 29031-0 | P25: ADIDAS DES ANTI CLINICAL FRESH FEM 150ML | Q25: ADIDAS - CLINICAL | R25: 468242 | S25: Sim | T25: 467707 | U25: Sim | W25: Não | X25: 451507 | Y25: Não | Z25: =IF(AND(S25="Sim",U25="Sim",W25="Sim"),"Sim","Não") -> Não | AA25: =COUNTIF(S25:Z25,"Sim") -> 2

Sheet INDICADOR DE RENDIMENTO
A2: LINHA | B2: CÓDIGO | C2: DESCRIÇÃO P.A | D2: ORDEM | E2: Data Início | F2: Data Fim | G2: QTD | H2: QTD | I2: RENDIMENTO
A3: L40 | B3: 17109-7 | C3: MONANGE DES ANTIT FL LAV 12X90G MT | D3: 1962330 | E3: =_xlfn.XLOOKUP(D3,'COHVPI DATAS REALIZADAS'!C:C,'COHVPI DATAS REALIZADAS'!N:N,0,0,1) -> 46172 | F3: =_xlfn.XLOOKUP(D3,'COHVPI DATAS REALIZADAS'!C:C,'COHVPI DATAS REALIZADAS'!O:O,0,0,1) -> 46176 | G3: =_xlfn.XLOOKUP(D3,COHVPI!A:A,COHVPI!E:E,0,0,1) -> 14866 | H3: =_xlfn.XLOOKUP(D3,COHVPI!A:A,COHVPI!F:F,0,0,1) -> 14433 | I3: =H3/G3 -> 0.97087313
A4: L40 | B4: 25642-1 | C4: MONANGE CLINICAL CONFORTO AERO 12X94G NL | D4: 1964889 | E4: =_xlfn.XLOOKUP(D4,'COHVPI DATAS REALIZADAS'!C:C,'COHVPI DATAS REALIZADAS'!N:N,0,0,1) -> 46176 | F4: =_xlfn.XLOOKUP(D4,'COHVPI DATAS REALIZADAS'!C:C,'COHVPI DATAS REALIZADAS'!O:O,0,0,1) -> 46177 | G4: =_xlfn.XLOOKUP(D4,COHVPI!A:A,COHVPI!E:E,0,0,1) -> 4244 | H4: =_xlfn.XLOOKUP(D4,COHVPI!A:A,COHVPI!F:F,0,0,1) -> 4235 | I4: =H4/G4 -> 0.99787936
A5: L40 | B5: 24630-1 | C5: MONANGE DES ANTI DETOX FRESH 12X90G NVF | D5: 1964892 | E5: =_xlfn.XLOOKUP(D5,'COHVPI DATAS REALIZADAS'!C:C,'COHVPI DATAS REALIZADAS'!N:N,0,0,1) -> 46177 | F5: =_xlfn.XLOOKUP(D5,'COHVPI DATAS REALIZADAS'!C:C,'COHVPI DATAS REALIZADAS'!O:O,0,0,1) -> 46178 | G5: =_xlfn.XLOOKUP(D5,COHVPI!A:A,COHVPI!E:E,0,0,1) -> 7433 | H5: =_xlfn.XLOOKUP(D5,COHVPI!A:A,COHVPI!F:F,0,0,1) -> 7301 | I5: =H5/G5 -> 0.98224136
A6: L40 | B6: 20257-3 | C6: MONANGE DES ANTI INVISIVEL 12X89G NVF | D6: 1964890 | E6: =_xlfn.XLOOKUP(D6,'COHVPI DATAS REALIZADAS'!C:C,'COHVPI DATAS REALIZADAS'!N:N,0,0,1) -> 46178 | F6: =_xlfn.XLOOKUP(D6,'COHVPI DATAS REALIZADAS'!C:C,'COHVPI DATAS REALIZADAS'!O:O,0,0,1) -> 46179 | G6: =_xlfn.XLOOKUP(D6,COHVPI!A:A,COHVPI!E:E,0,0,1) -> 7513 | H6: =_xlfn.XLOOKUP(D6,COHVPI!A:A,COHVPI!F:F,0,0,1) -> 7495 | I6: =H6/G6 -> 0.99760415
A7: TOTAL L40 | G7: =SUM(G3:G6) -> 34056 | H7: =SUM(H3:H6) -> 33464 | I7: =H7/G7 -> 0.98261687
A8: L53 | B8: 23208-4 | C8: ADIDAS DES ANTI CONTR INVISIBLE FEM 150M | D8: 1962343 | E8: =_xlfn.XLOOKUP(D8,'COHVPI DATAS REALIZADAS'!C:C,'COHVPI DATAS REALIZADAS'!N:N,0,0,1) -> 46172 | F8: =_xlfn.XLOOKUP(D8,'COHVPI DATAS REALIZADAS'!C:C,'COHVPI DATAS REALIZADAS'!O:O,0,0,1) -> 46175 | G8: =_xlfn.XLOOKUP(D8,COHVPI!A:A,COHVPI!E:E,0,0,1) -> 14310 | H8: =_xlfn.XLOOKUP(D8,COHVPI!A:A,COHVPI!F:F,0,0,1) -> 14637 | I8: =H8/G8 -> 1.0228512
A9: TOTAL L53 | G9: =SUM(G8:G8) -> 14310 | H9: =SUM(H8:H8) -> 14637 | I9: =H9/G9 -> 1.0228512
A10: L57 | B10: 8486-5 | C10: BOZZANO ESPUMA BARBA PELE SEN 6X193G CIN | D10: 1962779 | E10: =_xlfn.XLOOKUP(D10,'COHVPI DATAS REALIZADAS'!C:C,'COHVPI DATAS REALIZADAS'!N:N,0,0,1) -> 46172 | F10: =_xlfn.XLOOKUP(D10,'COHVPI DATAS REALIZADAS'!C:C,'COHVPI DATAS REALIZADAS'!O:O,0,0,1) -> 46175 | G10: =_xlfn.XLOOKUP(D10,COHVPI!A:A,COHVPI!E:E,0,0,1) -> 7998 | H10: =_xlfn.XLOOKUP(D10,COHVPI!A:A,COHVPI!F:F,0,0,1) -> 7388 | I10: =H10/G10 -> 0.92373093
A11: L57 | B11: 10907-4 | C11: BOZZANO ESPUMA BARBA HIDRAT 6X193G CIN | D11: 1962780 | E11: =_xlfn.XLOOKUP(D11,'COHVPI DATAS REALIZADAS'!C:C,'COHVPI DATAS REALIZADAS'!N:N,0,0,1) -> 46175 | F11: =_xlfn.XLOOKUP(D11,'COHVPI DATAS REALIZADAS'!C:C,'COHVPI DATAS REALIZADAS'!O:O,0,0,1) -> 46176 | G11: =_xlfn.XLOOKUP(D11,COHVPI!A:A,COHVPI!E:E,0,0,1) -> 7998 | H11: =_xlfn.XLOOKUP(D11,COHVPI!A:A,COHVPI!F:F,0,0,1) -> 7520 | I11: =H11/G11 -> 0.94023506
A12: L57 | B12: 27215-0 | C12: BOZZANO DES ANTI INVISIBLE 12X200ML | D12: 1962360 | E12: =_xlfn.XLOOKUP(D12,'COHVPI DATAS REALIZADAS'!C:C,'COHVPI DATAS REALIZADAS'!N:N,0,0,1) -> 46176 | F12: =_xlfn.XLOOKUP(D12,'COHVPI DATAS REALIZADAS'!C:C,'COHVPI DATAS REALIZADAS'!O:O,0,0,1) -> 46178 | G12: =_xlfn.XLOOKUP(D12,COHVPI!A:A,COHVPI!E:E,0,0,1) -> 11244 | H12: =_xlfn.XLOOKUP(D12,COHVPI!A:A,COHVPI!F:F,0,0,1) -> 11240 | I12: =H12/G12 -> 0.99964425
A13: TOTAL L57 | G13: =SUM(G10:G12) -> 27240 | H13: =SUM(H10:H12) -> 26148 | I13: =H13/G13 -> 0.95991189
A14: L58 | B14: 25003-1 | C14: BOZZANO DES ANTI DRY 12X90G NVF | D14: 1963471 | E14: =_xlfn.XLOOKUP(D14,'COHVPI DATAS REALIZADAS'!C:C,'COHVPI DATAS REALIZADAS'!N:N,0,0,1) -> 46173 | F14: =_xlfn.XLOOKUP(D14,'COHVPI DATAS REALIZADAS'!C:C,'COHVPI DATAS REALIZADAS'!O:O,0,0,1) -> 46176 | G14: =_xlfn.XLOOKUP(D14,COHVPI!A:A,COHVPI!E:E,0,0,1) -> 22299 | H14: =_xlfn.XLOOKUP(D14,COHVPI!A:A,COHVPI!F:F,0,0,1) -> 22217 | I14: =H14/G14 -> 0.99632271
A15: L58 | B15: 20159-4 | C15: BOZZANO DES ANTI INVISIBLE 12X89G NVF | D15: 1963469 | E15: =_xlfn.XLOOKUP(D15,'COHVPI DATAS REALIZADAS'!C:C,'COHVPI DATAS REALIZADAS'!N:N,0,0,1) -> 46176 | F15: =_xlfn.XLOOKUP(D15,'COHVPI DATAS REALIZADAS'!C:C,'COHVPI DATAS REALIZADAS'!O:O,0,0,1) -> 46177 | G15: =_xlfn.XLOOKUP(D15,COHVPI!A:A,COHVPI!E:E,0,0,1) -> 22539 | H15: =_xlfn.XLOOKUP(D15,COHVPI!A:A,COHVPI!F:F,0,0,1) -> 23158 | I15: =H15/G15 -> 1.0274635
A16: L58 | B16: 24631-2 | C16: MONANGE DES ANTIT PROT SEC 12X90G MT | D16: 1964907 | E16: =_xlfn.XLOOKUP(D16,'COHVPI DATAS REALIZADAS'!C:C,'COHVPI DATAS REALIZADAS'!N:N,0,0,1) -> 46177 | F16: =_xlfn.XLOOKUP(D16,'COHVPI DATAS REALIZADAS'!C:C,'COHVPI DATAS REALIZADAS'!O:O,0,0,1) -> 46179 | G16: =_xlfn.XLOOKUP(D16,COHVPI!A:A,COHVPI!E:E,0,0,1) -> 22299 | H16: =_xlfn.XLOOKUP(D16,COHVPI!A:A,COHVPI!F:F,0,0,1) -> 22320 | I16: =H16/G16 -> 1.0009417
A17: TOTAL L58 | G17: =SUM(G14:G16) -> 67137 | H17: =SUM(H14:H16) -> 67695 | I17: =H17/G17 -> 1.0083114

Sheet COHVPI DATAS REALIZADAS
A1: Nº do material | B1: Texto breve de material | C1: Ordem | D1: Lote | E1: Quantidade da ordem (GMEIN) | F1: Unidade de medida (=GMEIN) | G1: Planejador MRP | H1: Qtd.fornecida (GMEIN) | I1: Data-base iníc. | J1: Data de conclusão base | K1: Hr.início programada | L1: Fim program. (hora) | M1: Linha de produção | N1: Data início real | O1: Data fim real | P1: Início real hr. | Q1: Código de fixação | R1: Status do sistema | S1: Texto breve | T1: Versão de produção | U1: Tipo de ordem | V1: Último modificador | W1: Hora da modificação
A2: 432304 | B2: RESINA TRITURADA DES PRETO | C2: 1964848 | E2: 149.6 | F2: KG | G2: 301 | H2: 149.6 | I2: 46167 | J2: 46167 | K2: 0.27777778 | L2: 0.27777778 | N2: 46166 | O2: 46166 | P2: 0.46082176 | R2: ENTE CONF FORN CAPC MOME MatC NOLQ | S2: MOEDOR DE FRASCOS | T2: 0001 | U2: ZSC2 | V2: ABFERNANDE | W2: 0.37986111
A3: 432305 | B3: RESINA TRITURADA DES RASTRO RS | C3: 1964849 | E3: 56.6 | F3: KG | G3: 301 | H3: 56.6 | I3: 46167 | J3: 46167 | K3: 0.27777778 | L3: 0.27777778 | N3: 46166 | O3: 46166 | P3: 0.46107639 | R3: ENTE CONF FORN CAPC MOME MatC NOLQ | S3: MOEDOR DE FRASCOS | T3: 0001 | U3: ZSC2 | V3: ABFERNANDE | W3: 0.51021991
A4: 439876 | B4: RESINA TRIT FR PRETO TONAL BH GC | C4: 1964852 | E4: 148.7 | F4: KG | G4: Z06 | H4: 148.7 | I4: 46167 | J4: 46167 | K4: 0.27777778 | L4: 0.27777778 | N4: 46166 | O4: 46166 | P4: 0.46328704 | R4: ENTE CONF FORN CAPC MOME MatC NOLQ | S4: MOEDOR DE FRASCOS | T4: 0001 | U4: ZSC2 | V4: ABFERNANDE | W4: 0.51021991
A5: 432311 | B5: RESINA TRITURADA LOC ORIGINAL VD | C5: 1964857 | E5: 53.9 | F5: KG | G5: 301 | H5: 53 | I5: 46167 | J5: 46167 | K5: 0.27777778 | L5: 0.27777778 | N5: 46166 | O5: 46166 | P5: 0.72915509 | R5: ENTE CNPA CAPC FRNP MOME MatC NOLQ | S5: MOEDOR DE FRASCOS | T5: 0001 | U5: ZSC2 | V5: ABFERNANDE | W5: 0.51023148
A6: 456282 | B6: SA WELLA KOLESTON OIL AOX 9% DEITY | C6: 1954405 | D6: T26B1187 | E6: 2500 | F6: KG | G6: Z09 | H6: 2487 | I6: 46160 | J6: 46160 | K6: 0.27777778 | L6: 0.27777778 | N6: 46154 | O6: 46154 | P6: 0.23899306 | R6: ENTE IMPR CNPA CAPC CANC CPRE DMNV FRNP* | S6: SA WELLA KOLESTON OIL AOX 9% | T6: 1 | U6: ZSC2 | V6: ABFERNANDE | W6: 0.51027778
A7: 454867 | B7: SA GEL BENTONE TFF RISQUE | C7: 1956538 | D7: T26C0994 | E7: 700 | F7: KG | G7: Z01 | H7: 700 | I7: 46143 | J7: 46143 | K7: 0.27777778 | L7: 0.49652778 | N7: 46143 | O7: 46143 | P7: 0.21689815 | R7: ENTE IMPR CNPA FORN CAPC CANC CPRE DMNV* | S7: SA GEL BENTONE TFF TESTE | T7: 1 | U7: ZSC2 | V7: ABFERNANDE | W7: 0.51027778
A8: 454867 | B8: SA GEL BENTONE TFF RISQUE | C8: 1956539 | D8: T26C0995 | E8: 700 | F8: KG | G8: Z01 | H8: 705 | I8: 46143 | J8: 46143 | K8: 0.27777778 | L8: 0.49652778 | N8: 46143 | O8: 46143 | P8: 0.84921296 | R8: ENTE IMPR CNPA FORN CAPC CANC CPRE DMNV* | S8: SA GEL BENTONE TFF TESTE | T8: 1 | U8: ZSC2 | V8: ABFERNANDE | W8: 0.51063657
A9: 462203 | B9: SA WELLA KOLESTON AOX 6% HEMERA | C9: 1957224 | D9: T26C1432 | E9: 2500 | F9: KG | G9: Z09 | H9: 2465 | I9: 46143 | J9: 46143 | K9: 0.27777778 | L9: 0.27777778 | N9: 46143 | O9: 46143 | P9: 0.026840278 | R9: ENTE IMPR CNPA CAPC CANC CPRE DMNV FRNP* | S9: SA WELLA KOLESTON AOX 6% HEMERA | T9: 1 | U9: ZSC2 | V9: RMELO | W9: 0.49079861
A10: 462203 | B10: SA WELLA KOLESTON AOX 6% HEMERA | C10: 1957225 | D10: T26C1433 | E10: 2500 | F10: KG | G10: Z09 | H10: 2500 | I10: 46147 | J10: 46147 | K10: 0.27777778 | L10: 0.27777778 | N10: 46143 | O10: 46143 | P10: 0.18295139 | R10: ENTE IMPR CNPA FORN CAPC CANC CPRE DMNV* | S10: SA WELLA KOLESTON AOX 6% HEMERA | T10: 1 | U10: ZSC2 | V10: ABFERNANDE | W10: 0.51063657
A11: 462203 | B11: SA WELLA KOLESTON AOX 6% HEMERA | C11: 1957226 | D11: T26C1434 | E11: 2500 | F11: KG | G11: Z09 | H11: 2490 | I11: 46149 | J11: 46149 | K11: 0.27777778 | L11: 0.27777778 | N11: 46147 | O11: 46147 | P11: 0.55239583 | R11: ENTE IMPR CNPA CAPC CANC CPRE DMNV FRNP* | S11: SA WELLA KOLESTON AOX 6% HEMERA | T11: 1 | U11: ZSC2 | V11: RMELO | W11: 0.46927083
A12: 462203 | B12: SA WELLA KOLESTON AOX 6% HEMERA | C12: 1957227 | D12: T26C1435 | E12: 2500 | F12: KG | G12: Z09 | H12: 2500 | I12: 46150 | J12: 46150 | K12: 0.27777778 | L12: 0.27777778 | N12: 46147 | O12: 46147 | P12: 0.85083333 | R12: ENTE IMPR CNPA FORN CAPC CANC CPRE DMNV* | S12: SA WELLA KOLESTON AOX 6% HEMERA | T12: 1 | U12: ZSC2 | V12: RMELO | W12: 0.46793981
A13: 462203 | B13: SA WELLA KOLESTON AOX 6% HEMERA | C13: 1957228 | D13: T26C1436 | E13: 2500 | F13: KG | G13: Z09 | H13: 2480 | I13: 46153 | J13: 46153 | K13: 0.27777778 | L13: 0.27777778 | N13: 46150 | O13: 46150 | P13: 0.30619213 | R13: ENTE IMPR CNPA CAPC CANC CPRE DMNV FRNP* | S13: SA WELLA KOLESTON AOX 6% HEMERA | T13: 1 | U13: ZSC2 | V13: RMELO | W13: 0.46802083
A14: 462203 | B14: SA WELLA KOLESTON AOX 6% HEMERA | C14: 1957229 | D14: T26C1437 | E14: 2500 | F14: KG | G14: Z09 | H14: 2500 | I14: 46155 | J14: 46155 | K14: 0.27777778 | L14: 0.27777778 | N14: 46150 | O14: 46150 | P14: 0.5437037 | R14: ENTE IMPR CNPA FORN CAPC CPRE DMNV LOAT* | S14: SA WELLA KOLESTON AOX 6% HEMERA | T14: 1 | U14: ZSC2 | V14: RMELO | W14: 0.46738426
A15: 462203 | B15: SA WELLA KOLESTON AOX 6% HEMERA | C15: 1957230 | D15: T26C1438 | E15: 2500 | F15: KG | G15: Z09 | H15: 2500 | I15: 46157 | J15: 46157 | K15: 0.27777778 | L15: 0.27777778 | N15: 46151 | O15: 46151 | P15: 0.41548611 | R15: ENTE IMPR CNPA FORN CAPC CPRE DMNV LOAT* | S15: SA WELLA KOLESTON AOX 6% HEMERA | T15: 1 | U15: ZSC2 | V15: ABFERNANDE | W15: 0.59357639
A16: 462203 | B16: SA WELLA KOLESTON AOX 6% HEMERA | C16: 1957231 | D16: T26C1439 | E16: 2500 | F16: KG | G16: Z09 | H16: 2480 | I16: 46158 | J16: 46158 | K16: 0.27777778 | L16: 0.27777778 | N16: 46151 | O16: 46151 | P16: 0.67927083 | R16: ENTE IMPR CNPA CAPC CPRE DMNV FRNP LOAT* | S16: SA WELLA KOLESTON AOX 6% HEMERA | T16: 1 | U16: ZSC2 | V16: ABFERNANDE | W16: 0.59357639
A17: 462203 | B17: SA WELLA KOLESTON AOX 6% HEMERA | C17: 1957232 | D17: T26C1440 | E17: 2500 | F17: KG | G17: Z09 | H17: 2500 | I17: 46172 | J17: 46172 | K17: 0.27777778 | L17: 0.27777778 | N17: 46155 | O17: 46155 | P17: 0.10991898 | R17: ENTE IMPR CNPA FORN CAPC CPRE DMNV LOAT* | S17: SA WELLA KOLESTON AOX 6% HEMERA | T17: 1 | U17: ZSC2 | V17: RMELO | W17: 0.46809028
... A20: 462203 | B20: SA WELLA KOLESTON AOX 6% HEMERA | C20: 1957235 | D20: T26C1443 | E20: 2500 | F20: KG | G20: Z09 | H20: 2500 | I20: 46183 | J20: 46183 | K20: 0.27777778 | L20: 0.27777778 | N20: 46178 | O20: 46178 | P20: 0.77070602 | R20: LIB IMPR CNPA FORN CAPC CPRE DMNV LOAT* | S20: SA WELLA KOLESTON AOX 6% HEMERA | T20: 1 | U20: ZSC2 | V20: RMELO | W20: 0.46818287
A21: 462203 | B21: SA WELLA KOLESTON AOX 6% HEMERA | C21: 1957236 | D21: T26C1444 | E21: 2500 | F21: KG | G21: Z09 | H21: 0 | I21: 46185 | J21: 46185 | K21: 0.27777778 | L21: 0.27777778 | P21: 0 | R21: LIB MATF CAPC CPRE DMNV LOAT NOLQ ORSL | S21: SA WELLA KOLESTON AOX 6% HEMERA | T21: 1 | U21: ZSC2 | V21: ABFERNANDE | W21: 0.59363426
A22: 462203 | B22: SA WELLA KOLESTON AOX 6% HEMERA | C22: 1957237 | D22: T26C1445 | E22: 2500 | F22: KG | G22: Z09 | H22: 0 | I22: 46186 | J22: 46186 | K22: 0.27777778 | L22: 0.27777778 | P22: 0 | R22: LIB MATF CAPC CPRE DMNV LOAT NOLQ ORSL | S22: SA WELLA KOLESTON AOX 6% HEMERA | T22: 1 | U22: ZSC2 | V22: RMELO | W22: 0.46755787
A23: 462203 | B23: SA WELLA KOLESTON AOX 6% HEMERA | C23: 1957238 | D23: T26C1446 | E23: 2500 | F23: KG | G23: Z09 | H23: 0 | I23: 46189 | J23: 46189 | K23: 0.27777778 | L23: 0.27777778 | P23: 0 | R23: LIB CAPC CPRE DMNV LOAT NOLQ ORSL | S23: SA WELLA KOLESTON AOX 6% HEMERA | T23: 1 | U23: ZSC2 | V23: ABFERNANDE | W23: 0.51199074
A24: 462203 | B24: SA WELLA KOLESTON AOX 6% HEMERA | C24: 1957239 | D24: T26C1447 | E24: 2500 | F24: KG | G24: Z09 | H24: 0 | I24: 46190 | J24: 46190 | K24: 0.27777778 | L24: 0.27777778 | P24: 0 | R24: LIB CAPC CPRE DMNV LOAT NOLQ ORSL | S24: SA WELLA KOLESTON AOX 6% HEMERA | T24: 1 | U24: ZSC2 | V24: ABFERNANDE | W24: 0.51199074
A25: 462203 | B25: SA WELLA KOLESTON AOX 6% HEMERA | C25: 1957240 | D25: T26C1448 | E25: 2500 | F25: KG | G25: Z09 | H25: 0 | I25: 46192 | J25: 46192 | K25: 0.27777778 | L25: 0.27777778 | P25: 0 | R25: LIB CAPC CPRE DMNV LOAT NOLQ ORSL | S25: SA WELLA KOLESTON AOX 6% HEMERA | T25: 1 | U25: ZSC2 | V25: RMELO | W25: 0.40466435
A26: 456282 | B26: SA WELLA KOLESTON OIL AOX 9% DEITY | C26: 1957241 | D26: T26C1449 | E26: 2500 | F26: KG | G26: Z09 | H26: 2468 | I26: 46158 | J26: 46158 | K26: 0.27777778 | L26: 0.27777778 | N26: 46137 | O26: 46137 | P26: 0.33752315 | R26: ENTE IMPR CNPA CAPC CPRE DMNV FRNP LOAT* | S26: SA WELLA KOLESTON OIL AOX 9% | T26: 1 | U26: ZSC2 | V26: RMELO | W26: 0.46842593
A27: 456282 | B27: SA WELLA KOLESTON OIL AOX 9% DEITY | C27: 1957242 | D27: T26C1450 | E27: 2500 | F27: KG | G27: Z09 | H27: 2476 | I27: 46160 | J27: 46160 | K27: 0.27777778 | L27: 0.27777778 | N27: 46137 | O27: 46137 | P27: 0.54138889 | R27: ENTE IMPR CNPA CAPC CPRE DMNV FRNP LOAT* | S27: SA WELLA KOLESTON OIL AOX 9% | T27: 1 | U27: ZSC2 | V27: RMELO | W27: 0.46766204
A28: 456282 | B28: SA WELLA KOLESTON OIL AOX 9% DEITY | C28: 1957243 | D28: T26C1451 | E28: 2500 | F28: KG | G28: Z09 | H28: 2480 | I28: 46162 | J28: 46162 | K28: 0.27777778 | L28: 0.27777778 | N28: 46157 | O28: 46157 | P28: 0.57775463 | R28: ENTE IMPR CNPA CAPC CPRE DMNV FRNP LOAT* | S28: SA WELLA KOLESTON OIL AOX 9% | T28: 1 | U28: ZSC2 | V28: RMELO | W28: 0.46853009
A29: 463568 | B29: SA WELLA SOFT COLOR AOX 4% DARWIN | C29: 1957277 | D29: T26C1485 | E29: 2500 | F29: KG | G29: Z09 | H29: 2500 | I29: 46163 | J29: 46163 | K29: 0.27777778 | L29: 0.27777778 | N29: 46161 | O29: 46161 | P29: 0.38711806 | R29: ENTE IMPR CNPA FORN CAPC CPRE DMNV LOAT* | S29: SA WELLA SOFT COLOR AOX 4% DARWIN | T29: 1 | U29: ZSC2 | V29: RMELO | W29: 0.46770833
A30: 463568 | B30: SA WELLA SOFT COLOR AOX 4% DARWIN | C30: 1957278 | D30: T26C1486 | E30: 2500 | F30: KG | G30: Z09 | H30: 2497 | I30: 46163 | J30: 46163 | K30: 0.27777778 | L30: 0.27777778 | N30: 46163 | O30: 46163 | P30: 0.085590278 | R30: ENTE IMPR CNPA CAPC CPRE DMNV FRNP LOAT* | S30: SA WELLA SOFT COLOR AOX 4% DARWIN | T30: 1 | U30: ZSC2 | V30: RMELO | W30: 0.4675
A31: 463568 | B31: SA WELLA SOFT COLOR AOX 4% DARWIN | C31: 1957279 | D31: T26C1487 | E31: 2500 | F31: KG | G31: Z09 | H31: 2530 | I31: 46164 | J31: 46164 | K31: 0.27777778 | L31: 0.27777778 | N31: 46163 | O31: 46163 | P31: 0.39010417 | R31: ENTE IMPR CNPA FORN CAPC CPRE DMNV LOAT* | S31: SA WELLA SOFT COLOR AOX 4% DARWIN | T31: 1 | U31: ZSC2 | V31: RMELO | W31: 0.46784722
A32: 463568 | B32: SA WELLA SOFT COLOR AOX 4% DARWIN | C32: 1957280 | D32: T26C1488 | E32: 2500 | F32: KG | G32: Z09 | H32: 2470 | I32: 46164 | J32: 46164 | K32: 0.27777778 | L32: 0.27777778 | N32: 46164 | O32: 46164 | P32: 0.36482639 | R32: ENTE IMPR CNPA CAPC CPRE DMNV FRNP LOAT* | S32: SA WELLA SOFT COLOR AOX 4% DARWIN | T32: 1 | U32: ZSC2 | V32: RMELO | W32: 0.40508102
A33: 463568 | B33: SA WELLA SOFT COLOR AOX 4% DARWIN | C33: 1957281 | D33: T26C1489 | E33: 2500 | F33: KG | G33: Z09 | H33: 2500 | I33: 46165 | J33: 46165 | K33: 0.27777778 | L33: 0.27777778 | N33: 46164 | O33: 46164 | P33: 0.54876157 | R33: ENTE IMPR CNPA FORN CAPC CPRE DMNV LOAT* | S33: SA WELLA SOFT COLOR AOX 4% DARWIN | T33: 1 | U33: ZSC2 | V33: ABFERNANDE | W33: 0.51211806
A34: 465364 | B34: SA ADIDAS DES ANTI POWER BOOSTER FEM | C34: 1957824 | D34: T26C1856 | E34: 1200 | F34: KG | G34: Z11 | H34: 0 | I34: 46169 | J34: 46169 | K34: 0.27777778 | L34: 0.34027778 | P34: 0 | R34: ENTE CAPC CPRE DMNV LOAT NOLQ ORSL | S34: SA ADIDAS DES ANTI POWER BOOSTER FEM | T34: 1 | U34: ZSC2 | V34: RMELO | W34: 0.46825231
A35: 465365 | B35: SA ADIDAS DES ANTI POWER BOOSTER MASC | C35: 1958372 | D35: T26C2184 | E35: 1200 | F35: KG | G35: Z11 | H35: 0 | I35: 46184 | J35: 46184 | K35: 0.82385417 | L35: 0.88635417 | P35: 0 | R35: LIB CAPC CPRE DMNV LOAT NOLQ ORSL | S35: SA ADIDAS DES ANTI POWER BOOSTER MASC | T35: 1 | U35: ZSC2 | V35: RMELO | W35: 0.46896991
A36: 452065 | B36: SA BOZZANO BAL PELE SENS COMFORT REPAIR | C36: 1958497 | D36: T26C2289 | E36: 2000 | F36: KG | G36: Z08 | H36: 0 | I36: 46161 | J36: 46161 | K36: 0.27777778 | L36: 0.40277778 | P36: 0 | R36: ENTE CAPC CPRE DMNV LOAT NOLQ ORSL | S36: SA BOZZANO BAL PELE SENS COMFORT REPAIR | T36: 1 | U36: ZSC2 | V36: ABFERNANDE | W36: 0.66736111
A37: 457126 | B37: SA MONANGE CPP CACHOS DEFINIDOS T | C37: 1958908 | D37: T26C2601 | E37: 9500 | F37: KG | G37: Z03 | H37: 9500 | I37: 46146 | J37: 46146 | K37: 0.27777778 | L37: 0.47569444 | N37: 46146 | O37: 46146 | P37: 0.5221412 | R37: ENTE MATF IMPR CNPA FORN CAPC CANC CPRE* | S37: SA MONANGE ATIVADOR DE CACHOS QUE TAL | T37: 1 | U37: ZSC2 | V37: RMELO | W37: 0.44402778
A38: 457126 | B38: SA MONANGE CPP CACHOS DEFINIDOS T | C38: 1958909 | D38: T26C2602 | E38: 9500 | F38: KG | G38: Z03 | H38: 9500 | I38: 46146 | J38: 46146 | K38: 0.27777778 | L38: 0.47569444 | N38: 46147 | O38: 46147 | P38: 0.41738426 | R38: ENTE MATF IMPR CNPA FORN CAPC CANC CPRE* | S38: SA MONANGE ATIVADOR DE CACHOS QUE TAL | T38: 1 | U38: ZSC2 | V38: RMELO | W38: 0.444375
A39: 457126 | B39: SA MONANGE CPP CACHOS DEFINIDOS T | C39: 1958910 | D39: T26C2603 | E39: 9500 | F39: KG | G39: Z03 | H39: 9500 | I39: 46147 | J39: 46147 | K39: 0.27777778 | L39: 0.47569444 | N39: 46148 | O39: 46148 | P39: 0.30849537 | R39: ENTE MATF IMPR CNPA FORN CAPC CANC CPRE* | S39: SA MONANGE ATIVADOR DE CACHOS QUE TAL | T39: 1 | U39: ZSC2 | V39: RMELO | W39: 0.40420139
A40: 454867 | B40: SA GEL BENTONE TFF RISQUE | C40: 1959098 | D40: T26D0019 | E40: 700 | F40: KG | G40: Z01 | H40: 700 | I40: 46146 | J40: 46146 | K40: 0.27777778 | L40: 0.49652778 | N40: 46144 | O40: 46144 | P40: 0.026979167 | R40: ENTE IMPR CNPA FORN CAPC CANC CPRE DMNV* | S40: SA GEL BENTONE TFF TESTE | T40: 1 | U40: ZSC2 | V40: RMELO | W40: 0.44512731
A41: 454867 | B41: SA GEL BENTONE TFF RISQUE | C41: 1959099 | D41: T26D0020 | E41: 700 | F41: KG | G41: Z01 | H41: 710 | I41: 46146 | J41: 46146 | K41: 0.27777778 | L41: 0.49652778 | N41: 46146 | O41: 46146 | P41: 0.81184028 | R41: ENTE IMPR CNPA FORN CAPC CPRE DMNV LOAT* | S41: SA GEL BENTONE TFF TESTE | T41: 1 | U41: ZSC2 | V41: RMELO | W41: 0.44469907
A42: 454867 | B42: SA GEL BENTONE TFF RISQUE | C42: 1959100 | D42: T26D0021 | E42: 700 | F42: KG | G42: Z01 | H42: 700 | I42: 46147 | J42: 46148 | K42: 0.37711806 | L42: 0.27777778 | N42: 46147 | O42: 46147 | P42: 0.37711806 | R42: ENTE IMPR CNPA FORN CAPC CPRE DMNV LOAT* | S42: SA GEL BENTONE TFF TESTE | T42: 1 | U42: ZSC2 | V42: RMELO | W42: 0.40585648
A43: 454867 | B43: SA GEL BENTONE TFF RISQUE | C43: 1959101 | D43: T26D0022 | E43: 700 | F43: KG | G43: Z01 | H43: 715 | I43: 46149 | J43: 46149 | K43: 0.27777778 | L43: 0.49652778 | N43: 46147 | O43: 46147 | P43: 0.70546296 | R43: ENTE IMPR CNPA FORN CAPC CPRE DMNV LOAT* | S43: SA GEL BENTONE TFF TESTE | T43: 1 | U43: ZSC2 | V43: ABFERNANDE | W43: 0.37928241
A44: 454867 | B44: SA GEL BENTONE TFF RISQUE | C44: 1959102 | D44: T26D0023 | E44: 700 | F44: KG | G44: Z01 | H44: 700 | I44: 46149 | J44: 46149 | K44: 0.27777778 | L44: 0.49652778 | N44: 46148 | O44: 46148 | P44: 0.42952546 | R44: ENTE MATF IMPR CNPA FORN CAPC CPRE DMNV* | S44: SA GEL BENTONE TFF TESTE | T44: 1 | U44: ZSC2 | V44: RMELO | W44: 0.40547454
A45: 454867 | B45: SA GEL BENTONE TFF RISQUE | C45: 1959103 | D45: T26D0024 | E45: 700 | F45: KG | G45: Z01 | H45: 710 | I45: 46150 | J45: 46150 | K45: 0.27777778 | L45: 0.49652778 | N45: 46149 | O45: 46149 | P45: 0.49773148 | R45: ENTE MATF IMPR CNPA FORN CAPC CPRE DMNV* | S45: SA GEL BENTONE TFF TESTE | T45: 1 | U45: ZSC2 | V45: RMELO | W45: 0.40549769
A46: 454867 | B46: SA GEL BENTONE TFF RISQUE | C46: 1959104 | D46: T26D0025 | E46: 700 | F46: KG | G46: Z01 | H46: 700 | I46: 46150 | J46: 46150 | K46: 0.27777778 | L46: 0.49652778 | N46: 46150 | O46: 46150 | P46: 0.39796296 | R46: ENTE MATF IMPR CNPA FORN CAPC CPRE DMNV* | S46: SA GEL BENTONE TFF TESTE | T46: 1 | U46: ZSC2 | V46: RMELO | W46: 0.47243056
A47: 456642 | B47: SA WELLA SOFT COLOR COND DARWIN | C47: 1959136 | D47: T26D0055 | E47: 3000 | F47: KG | G47: Z09 | H47: 2896 | I47: 46148 | J47: 46149 | K47: 0 | L47: 0 | N47: 46140 | O47: 46140 | P47: 0.098252315 | R47: ENTE MATF IMPR CNPA CAPC CPRE DMNV FRNP* | S47: SA WELLA KOLESTON CC05L 0.4MERLOT BRA | T47: 1 | U47: ZSC2 | V47: RMELO | W47: 0.49072917
A48: 456642 | B48: SA WELLA SOFT COLOR COND DARWIN | C48: 1959137 | D48: T26D0056 | E48: 3000 | F48: KG | G48: Z09 | H48: 2958 | I48: 46148 | J48: 46149 | K48: 0 | L48: 0 | N48: 46140 | O48: 46140 | P48: 0.39388889 | R48: ENTE MATF IMPR CNPA CAPC CPRE DMNV FRNP* | S48: SA WELLA KOLESTON CC05L 0.4MERLOT BRA | T48: 1 | U48: ZSC2 | V48: RMELO | W48: 0.49099537
... A87: 461829 | B87: SA BOZZANO CLINICAL ULTRA COOL AERO | C87: 1960334 | D87: T26D0865 | E87: 1000 | F87: KG | G87: Z11 | H87: 1005 | I87: 46163 | J87: 46163 | K87: 0.27777778 | L87: 0.36458333 | N87: 46163 | O87: 46163 | P87: 0.39084491 | R87: ENTE IMPR CNPA FORN CAPC CPRE DMNV LOAT* | S87: SA BOZZANO CLINICAL ULTRA COOL AERO | T87: 1 | U87: ZSC2 | V87: RMELO | W87: 0.34898148
A88: 465364 | B88: SA ADIDAS DES ANTI POWER BOOSTER FEM | C88: 1960335 | D88: T26D0866 | E88: 1200 | F88: KG | G88: Z11 | H88: 0 | I88: 46171 | J88: 46171 | K88: 0.27777778 | L88: 0.34027778 | P88: 0 | R88: ENTE MATF CNAT DMNV LBRJ LOAT NOLQ ORSL | S88: SA ADIDAS DES ANTI POWER BOOSTER FEM | T88: 1 | U88: ZSC2 | V88: RMELO | W88: 0.34899306
A89: 465364 | B89: SA ADIDAS DES ANTI POWER BOOSTER FEM | C89: 1960336 | D89: T26D0867 | E89: 1200 | F89: KG | G89: Z11 | H89: 0 | I89: 46171 | J89: 46171 | K89: 0.27777778 | L89: 0.34027778 | P89: 0 | R89: ENTE MATF CNAT DMNV LBRJ LOAT NOLQ ORSL | S89: SA ADIDAS DES ANTI POWER BOOSTER FEM | T89: 1 | U89: ZSC2 | V89: RMELO | W89: 0.34900463
A90: 465364 | B90: SA ADIDAS DES ANTI POWER BOOSTER FEM | C90: 1960337 | D90: T26D0868 | E90: 1200 | F90: KG | G90: Z11 | H90: 0 | I90: 46165 | J90: 46165 | K90: 0.27777778 | L90: 0.34027778 | P90: 0 | R90: ENTE MATF CNAT LBRJ LOAT NOLQ ORSL | S90: SA ADIDAS DES ANTI POWER BOOSTER FEM | T90: 1 | U90: ZSC2 | V90: RMELO | W90: 0.3490162
A91: 465365 | B91: SA ADIDAS DES ANTI POWER BOOSTER MASC | C91: 1960338 | D91: T26D0869 | E91: 1200 | F91: KG | G91: Z11 | H91: 0 | I91: 46167 | J91: 46167 | K91: 0.27777778 | L91: 0.34027778 | P91: 0 | R91: ENTE MATF CNAT LBRJ LOAT NOLQ ORSL | S91: SA ADIDAS DES ANTI POWER BOOSTER MASC | T91: 1 | U91: ZSC2 | V91: RMELO | W91: 0.3490162
A92: 461828 | B92: SA BOZZANO CLINICAL CLEAN AERO | C92: 1960361 | D92: T26D0888 | E92: 1000 | F92: KG | G92: Z11 | H92: 971 | I92: 46143 | J92: 46143 | K92: 0.27777778 | L92: 0.36458333 | N92: 46143 | O92: 46143 | P92: 0.72734954 | R92: ENTE IMPR CNPA CAPC CANC CPRE DMNV FRNP* | S92: SA BOZZANO CLINICAL CLEAN AERO | T92: 1 | U92: ZSC2 | V92: RMELO | W92: 0.34902778
A93: 454867 | B93: SA GEL BENTONE TFF RISQUE | C93: 1960748 | D93: T26D1129 | E93: 700 | F93: KG | G93: Z01 | H93: 700 | I93: 46162 | J93: 46162 | K93: 0.57777778 | L93: 0.79652778 | N93: 46162 | O93: 46162 | P93: 0.45925926 | R93: ENTE IMPR CNPA FORN CAPC CPRE DMNV LOAT* | S93: SA GEL BENTONE TFF TESTE | T93: 1 | U93: ZSC2 | V93: RMELO | W93: 0.34903935
A94: 454867 | B94: SA GEL BENTONE TFF RISQUE | C94: 1960750 | D94: T26D1130 | E94: 700 | F94: KG | G94: Z01 | H94: 700 | I94: 46169 | J94: 46169 | K94: 0.27777778 | L94: 0.49652778 | N94: 46170 | O94: 46170 | P94: 0.45701389 | R94: ENTE IMPR CNPA FORN CAPC CPRE DMNV LOAT* | S94: SA GEL BENTONE TFF TESTE | T94: 1 | U94: ZSC2 | V94: RMELO | W94: 0.34905093
A95: 454867 | B95: SA GEL BENTONE TFF RISQUE | C95: 1960751 | D95: T26D1131 | E95: 700 | F95: KG | G95: Z01 | H95: 700 | I95: 46171 | J95: 46171 | K95: 0.27777778 | L95: 0.49652778 | N95: 46171 | O95: 46171 | P95: 0.018576389 | R95: ENTE IMPR CNPA FORN CAPC CPRE DMNV LOAT* | S95: SA GEL BENTONE TFF TESTE | T95: 1 | U95: ZSC2 | V95: RMELO | W95: 0.34905093
A96: 454867 | B96: SA GEL BENTONE TFF RISQUE | C96: 1960752 | D96: T26D1132 | E96: 700 | F96: KG | G96: Z01 | H96: 705 | I96: 46172 | J96: 46172 | K96: 0.27777778 | L96: 0.49652778 | N96: 46171 | O96: 46171 | P96: 0.51506944 | R96: ENTE IMPR CNPA FORN CAPC CPRE DMNV LOAT* | S96: SA GEL BENTONE TFF TESTE | T96: 1 | U96: ZSC2 | V96: RMELO | W96: 0.50658565
A97: 454867 | B97: SA GEL BENTONE TFF RISQUE | C97: 1960753 | D97: T26D1133 | E97: 700 | F97: KG | G97: Z01 | H97: 700 | I97: 46176 | J97: 46177 | K97: 0.82395833 | L97: 0.042708333 | N97: 46175 | O97: 46175 | P97: 0.46263889 | R97: ENTE IMPR CNPA FORN CAPC CANC CPRE DMNV* | S97: SA GEL BENTONE TFF TESTE | T97: 1 | U97: ZSC2 | V97: RMELO | W97: 0.50658565
A98: 454867 | B98: SA GEL BENTONE TFF RISQUE | C98: 1960754 | D98: T26D1134 | E98: 700 | F98: KG | G98: Z01 | H98: 700 | I98: 46177 | J98: 46177 | K98: 0.27777778 | L98: 0.49652778 | N98: 46175 | O98: 46175 | P98: 0.46625 | R98: ENTE IMPR CNPA FORN CAPC CANC CPRE DMNV* | S98: SA GEL BENTONE TFF TESTE | T98: 1 | U98: ZSC2 | V98: RMELO | W98: 0.50659722
A99: 454867 | B99: SA GEL BENTONE TFF RISQUE | C99: 1960755 | D99: T26D1135 | E99: 700 | F99: KG | G99: Z01 | H99: 705 | I99: 46177 | J99: 46177 | K99: 0.27777778 | L99: 0.49652778 | N99: 46177 | O99: 46177 | P99: 0.033541667 | R99: ENTE IMPR CNPA FORN CAPC CANC CPRE DMNV* | S99: SA GEL BENTONE TFF TESTE | T99: 1 | U99: ZSC2 | V99: RMELO | W99: 0.5066088
A100: 453581 | B100: SA WELLA COLR KOLESTON PERFECT PLUS 70 | C100: 1960814 | D100: T26D1162 | E100: 2000 | F100: KG | G100: Z09 | H100: 1928 | I100: 46147 | J100: 46148 | K100: 0 | L100: 0 | N100: 46148 | O100: 46148 | P100: 0.22521991 | R100: ENTE IMPR CNPA CAPC CANC CPRE DMNV FRNP* | S100: SA WELLA COLR KOLESTON PERFECT PLUS 70 | T100: 1 | U100: ZSC2 | V100: RMELO | W100: 0.5066088
A101: 453581 | B101: SA WELLA COLR KOLESTON PERFECT PLUS 70 | C101: 1960815 | D101: T26D1163 | E101: 1000 | F101: KG | G101: Z09 | H101: 941 | I101: 46147 | J101: 46148 | K101: 0 | L101: 0 | N101: 46148 | O101: 46148 | P101: 0.69677083 | R101: ENTE IMPR CNPA CAPC CANC CPRE DMNV FRNP* | S101: SA WELLA COLR KOLESTON PERFECT PLUS 70 | T101: 1 | U101: ZSC2 | V101: RMELO | W101: 0.50662037
A102: 453582 | B102: SA WELLA COLR KOLESTON PERFECT PLUS 60 | C102: 1960816 | D102: T26D1164 | E102: 2000 | F102: KG | G102: Z09 | H102: 1923 | I102: 46148 | J102: 46149 | K102: 0 | L102: 0 | N102: 46148 | O102: 46148 | P102: 0.99228009 | R102: ENTE IMPR CNPA CAPC CANC CPRE DMNV FRNP* | S102: SA WELLA COLR KOLESTON PERFECT PLUS 60 | T102: 1 | U102: ZSC2 | V102: RMELO | W102: 0.50663194
A103: 453582 | B103: SA WELLA COLR KOLESTON PERFECT PLUS 60 | C103: 1960817 | D103: T26D1165 | E103: 2000 | F103: KG | G103: Z09 | H103: 1927 | I103: 46149 | J103: 46150 | K103: 0 | L103: 0 | N103: 46150 | O103: 46150 | P103: 0.066365741 | R103: ENTE IMPR CNPA CAPC CPRE DMNV FRNP LOAT* | S103: SA WELLA COLR KOLESTON PERFECT PLUS 60 | T103: 1 | U103: ZSC2 | V103: RMELO | W103: 0.50664352
... A172: 452075 | B172: SA BOZZANO LOC AGUA N NIGHTBLUE COMF REP | C172: 1961731 | D172: T26D1757 | E172: 1700 | F172: KG | G172: Z08 | H172: 1714 | I172: 46153 | J172: 46156 | K172: 0.98569444 | L172: 0.27777778 | N172: 46153 | O172: 46153 | P172: 0.98569444 | R172: ENTE IMPR CNPA FORN CAPC CPRE DMNV LOAT* | S172: SA BOZZANO LOC AGUA N NIGHTBLUE COMF REP | T172: 1 | U172: ZSC2 | V172: RMELO | W172: 0.62091435
A173: 452072 | B173: SA BOZZANO GEL POS REFRES COMFORT REPAIR | C173: 1961772 | D173: T26D1796 | E173: 1000 | F173: KG | G173: Z08 | H173: 0 | I173: 46162 | J173: 46162 | K173: 0.27777778 | L173: 0.34027778 | P173: 0 | R173: ENTE CAPC CPRE LOAT MatC NOLQ ORSL | S173: SA BOZZANO GEL POS REFRES COMFORT REPAIR | T173: 1 | U173: ZSC2 | V173: RMELO | W173: 0.62092593
A174: 463568 | B174: SA WELLA SOFT COLOR AOX 4% DARWIN | C174: 1961918 | D174: T26D1915 | E174: 2500 | F174: KG | G174: Z09 | H174: 2474 | I174: 46172 | J174: 46172 | K174: 0.82421296 | L174: 0.82421296 | N174: 46173 | O174: 46173 | P174: 0.012789352 | R174: ENTE IMPR CNPA CAPC CANC CPRE DMNV FRNP* | S174: SA WELLA SOFT COLOR AOX 4% DARWIN | T174: 1 | U174: ZSC2 | V174: RMELO | W174: 0.6209375
A175: 463568 | B175: SA WELLA SOFT COLOR AOX 4% DARWIN | C175: 1961919 | D175: T26D1916 | E175: 2500 | F175: KG | G175: Z09 | H175: 0 | I175: 46202 | J175: 46202 | K175: 0.82431713 | L175: 0.82431713 | P175: 0 | R175: LIB CAPC CPRE DMNV LOAT NOLQ ORSL | S175: SA WELLA SOFT COLOR AOX 4% DARWIN | T175: 1 | U175: ZSC2 | V175: RMELO | W175: 0.6209375
A176: 462204 | B176: SA WELLA KOLEST REAT 1 DEEP BLACK HEMERA | C176: 1961944 | D176: T26D1930 | E176: 3000 | F176: KG | G176: Z09 | H176: 2948 | I176: 46153 | J176: 46153 | K176: 0 | L176: 0 | N176: 46150 | O176: 46150 | P176: 0.30489583 | R176: ENTE IMPR CNPA CAPC CPRE DMNV FRNP LOAT* | S176: SA WELLA KOLEST REAT 1 DEEP BLACK HEMERA | T176: 1 | U176: ZSC2 | V176: RMELO | W176: 0.58696759
A177: 462204 | B177: SA WELLA KOLEST REAT 1 DEEP BLACK HEMERA | C177: 1961945 | D177: T26D1931 | E177: 3000 | F177: KG | G177: Z09 | H177: 3075 | I177: 46153 | J177: 46153 | K177: 0 | L177: 0 | N177: 46150 | O177: 46150 | P177: 0.43037037 | R177: ENTE IMPR CNPA FORN CAPC CPRE DMNV LOAT* | S177: SA WELLA KOLEST REAT 1 DEEP BLACK HEMERA | T177: 1 | U177: ZSC2 | V177: RMELO | W177: 0.58694444
A178: 462204 | B178: SA WELLA KOLEST REAT 1 DEEP BLACK HEMERA | C178: 1961946 | D178: T26D1932 | E178: 3000 | F178: KG | G178: Z09 | H178: 3059 | I178: 46153 | J178: 46153 | K178: 0 | L178: 0 | N178: 46150 | O178: 46150 | P178: 0.59398148 | R178: ENTE IMPR CNPA FORN CAPC CPRE DMNV LOAT* | S178: SA WELLA KOLEST REAT 1 DEEP BLACK HEMERA | T178: 1 | U178: ZSC2 | V178: RMELO | W178: 0.58695602
A179: 462204 | B179: SA WELLA KOLEST REAT 1 DEEP BLACK HEMERA | C179: 1961947 | D179: T26D1933 | E179: 3000 | F179: KG | G179: Z09 | H179: 3054 | I179: 46153 | J179: 46153 | K179: 0 | L179: 0 | N179: 46150 | O179: 46150 | P179: 0.75800926 | R179: ENTE IMPR CNPA FORN CAPC CPRE DMNV LOAT* | S179: SA WELLA KOLEST REAT 1 DEEP BLACK HEMERA | T179: 1 | U179: ZSC2 | V179: RMELO | W179: 0.62096065
A180: 462204 | B180: SA WELLA KOLEST REAT 1 DEEP BLACK HEMERA | C180: 1961948 | D180: T26D1934 | E180: 3000 | F180: KG | G180: Z09 | H180: 3055 | I180: 46153 | J180: 46153 | K180: 0 | L180: 0 | N180: 46150 | O180: 46150 | P180: 0.91445602 | R180: ENTE IMPR CNPA FORN CAPC CPRE DMNV LOAT* | S180: SA WELLA KOLEST REAT 1 DEEP BLACK HEMERA | T180: 1 | U180: ZSC2 | V180: RMELO | W180: 0.62096065
A181: 454867 | B181: SA GEL BENTONE TFF RISQUE | C181: 1962283 | D181: T26E0124 | E181: 700 | F181: KG | G181: Z01 | H181: 0 | I181: 46178 | J181: 46178 | K181: 0.27777778 | L181: 0.49652778 | P181: 0 | R181: LIB IMPR CAPC CPRE DMNV LOAT MOME NOLQ* | S181: SA GEL BENTONE TFF TESTE | T181: 1 | U181: ZSC2 | V181: RMELO | W181: 0.62096065
A182: 454867 | B182: SA GEL BENTONE TFF RISQUE | C182: 1962284 | D182: T26E0125 | E182: 700 | F182: KG | G182: Z01 | H182: 706 | I182: 46176 | J182: 46176 | K182: 0.27777778 | L182: 0.49652778 | N182: 46172 | O182: 46172 | P182: 0.10775463 | R182: ENTE IMPR CNPA FORN CAPC CPRE DMNV LOAT* | S182: SA GEL BENTONE TFF TESTE | T182: 1 | U182: ZSC2 | V182: RMELO | W182: 0.62097222
A183: 454867 | B183: SA GEL BENTONE TFF RISQUE | C183: 1962285 | D183: T26E0126 | E183: 700 | F183: KG | G183: Z01 | H183: 700 | I183: 46177 | J183: 46177 | K183: 0.27777778 | L183: 0.49652778 | N183: 46172 | O183: 46172 | P183: 0.45096065 | R183: ENTE IMPR CNPA FORN CAPC CPRE DMNV LOAT* | S183: SA GEL BENTONE TFF TESTE | T183: 1 | U183: ZSC2 | V183: RMELO | W183: 0.52765046
A184: 454867 | B184: SA GEL BENTONE TFF RISQUE | C184: 1962286 | D184: T26E0127 | E184: 700 | F184: KG | G184: Z01 | H184: 700 | I184: 46178 | J184: 46178 | K184: 0.27777778 | L184: 0.49652778 | N184: 46176 | O184: 46176 | P184: 0.37959491 | R184: ENTE IMPR CNPA FORN CAPC CANC CPRE DMNV* | S184: SA GEL BENTONE TFF TESTE | T184: 1 | U184: ZSC2 | V184: RMELO | W184: 0.52766204
A185: 454867 | B185: SA GEL BENTONE TFF RISQUE | C185: 1962287 | D185: T26E0128 | E185: 700 | F185: KG | G185: Z01 | H185: 700 | I185: 46181 | J185: 46181 | K185: 0.27777778 | L185: 0.49652778 | N185: 46177 | O185: 46177 | P185: 0.45012731 | R185: LIB IMPR CNPA FORN CAPC CPRE DMNV LOAT* | S185: SA GEL BENTONE TFF TESTE | T185: 1 | U185: ZSC2 | V185: RMELO | W185: 0.52766204
A186: 454867 | B186: SA GEL BENTONE TFF RISQUE | C186: 1962288 | D186: T26E0129 | E186: 700 | F186: KG | G186: Z01 | H186: 700 | I186: 46181 | J186: 46181 | K186: 0.27777778 | L186: 0.49652778 | N186: 46178 | O186: 46178 | P186: 0.42104167 | R186: LIB IMPR CNPA FORN CAPC CPRE DMNV LOAT* | S186: SA GEL BENTONE TFF TESTE | T186: 1 | U186: ZSC2 | V186: RMELO | W186: 0.52767361
A187: 454867 | B187: SA GEL BENTONE TFF RISQUE | C187: 1962289 | D187: T26E0130 | E187: 700 | F187: KG | G187: Z01 | H187: 0 | I187: 46182 | J187: 46182 | K187: 0.27777778 | L187: 0.49652778 | P187: 0 | R187: LIB IMPR CAPC CPRE DMNV LOAT MOME NOLQ* | S187: SA GEL BENTONE TFF TESTE | T187: 1 | U187: ZSC2 | V187: RMELO | W187: 0.52767361
A188: 454867 | B188: SA GEL BENTONE TFF RISQUE | C188: 1962290 | D188: T26E0131 | E188: 700 | F188: KG | G188: Z01 | H188: 0 | I188: 46182 | J188: 46182 | K188: 0.27777778 | L188: 0.49652778 | P188: 0 | R188: LIB MATF IMPR CAPC CPRE DMNV LOAT MOME* | S188: SA GEL BENTONE TFF TESTE | T188: 1 | U188: ZSC2 | V188: RMELO | W188: 0.52768519
A189: 461829 | B189: SA BOZZANO CLINICAL ULTRA COOL AERO | C189: 1962377 | D189: T26E0147 | E189: 1000 | F189: KG | G189: Z11 | H189: 0 | I189: 46167 | J189: 46167 | K189: 0.27777778 | L189: 0.36458333 | P189: 0 | R189: ENTE CAPC CPRE LOAT MatC NOLQ ORSL | S189: SA BOZZANO CLINICAL ULTRA COOL AERO | T189: 1 | U189: ZSC2 | V189: RMELO | W189: 0.52768519
A190: 465365 | B190: SA ADIDAS DES ANTI POWER BOOSTER MASC | C190: 1962423 | D190: T26E0193 | E190: 1200 | F190: KG | G190: Z11 | H190: 0 | I190: 46164 | J190: 46164 | K190: 0.27777778 | L190: 0.34027778 | P190: 0 | R190: ENTE MATF CAPC CPRE LOAT NOLQ ORSL | S190: SA ADIDAS DES ANTI POWER BOOSTER MASC | T190: 1 | U190: ZSC2 | V190: RMELO | W190: 0.52770833
A191: 465364 | B191: SA ADIDAS DES ANTI POWER BOOSTER FEM | C191: 1962512 | D191: T26E0285 | E191: 1200 | F191: KG | G191: Z11 | H191: 0 | I191: 46171 | J191: 46171 | K191: 0.27777778 | L191: 0.34027778 | P191: 0 | R191: ENTE MATF CAPC CPRE DMNV LOAT NOLQ ORSL | S191: SA ADIDAS DES ANTI POWER BOOSTER FEM | T191: 1 | U191: ZSC2 | V191: RMELO | W191: 0.52770833
A192: 454867 | B192: SA GEL BENTONE TFF RISQUE | C192: 1962580 | D192: T26E0375 | E192: 700 | F192: KG | G192: Z01 | H192: 0 | I192: 46183 | J192: 46183 | K192: 0.27777778 | L192: 0.49652778 | P192: 0 | R192: LIB MATF IMPR CAPC CPRE DMNV LOAT MOME* | S192: SA GEL BENTONE TFF TESTE | T192: 1 | U192: ZSC2 | V192: RMELO | W192: 0.52771991
A193: 454867 | B193: SA GEL BENTONE TFF RISQUE | C193: 1962581 | D193: T26E0376 | E193: 700 | F193: KG | G193: Z01 | H193: 0 | I193: 46183 | J193: 46183 | K193: 0.27777778 | L193: 0.49652778 | P193: 0 | R193: LIB MATF CAPC CPRE DMNV LOAT NOLQ ORSL | S193: SA GEL BENTONE TFF TESTE | T193: 1 | U193: ZSC2 | V193: RMELO | W193: 0.52771991
A194: 454867 | B194: SA GEL BENTONE TFF RISQUE | C194: 1962582 | D194: T26E0377 | E194: 700 | F194: KG | G194: Z01 | H194: 0 | I194: 46184 | J194: 46184 | K194: 0.27777778 | L194: 0.49652778 | P194: 0 | R194: LIB MATF CAPC CPRE DMNV LOAT NOLQ ORSL | S194: SA GEL BENTONE TFF TESTE | T194: 1 | U194: ZSC2 | V194: RMELO | W194: 0.52773148
A195: 454867 | B195: SA GEL BENTONE TFF RISQUE | C195: 1962583 | D195: T26E0378 | E195: 700 | F195: KG | G195: Z01 | H195: 0 | I195: 46184 | J195: 46184 | K195: 0.27777778 | L195: 0.49652778 | P195: 0 | R195: LIB MATF CAPC CPRE DMNV LOAT MOME NOLQ* | S195: SA GEL BENTONE TFF TESTE | T195: 1 | U195: ZSC2 | V195: RMELO | W195: 0.52769676
A196: 454867 | B196: SA GEL BENTONE TFF RISQUE | C196: 1962584 | D196: T26E0379 | E196: 700 | F196: KG | G196: Z01 | H196: 0 | I196: 46185 | J196: 46185 | K196: 0.27777778 | L196: 0.49652778 | P196: 0 | R196: LIB MATF CAPC CPRE DMNV LOAT NOLQ ORSL | S196: SA GEL BENTONE TFF TESTE | T196: 1 | U196: ZSC2 | V196: RMELO | W196: 0.52773148
A197: 454846 | B197: SA RISQUE ESM EFT GLIT GRAN ROSE | C197: 1962839 | D197: T26E0481 | E197: 400 | F197: KG | G197: Z01 | H197: 394 | I197: 46162 | J197: 46162 | K197: 0.57416667 | L197: 0.5825 | N197: 46161 | O197: 46161 | P197: 0.87766204 | R197: ENTE IMPR CNPA CAPC CPRE DMNV FRNP LOAT* | S197: SA RISQUE ESM EFT GLIT GRAN ROSE | T197: 1 | U197: ZSC2 | V197: RMELO | W197: 0.52774306
A198: 454844 | B198: SA RISQUE ESM EFT GLIT MIL PURPURINAS | C198: 1962843 | D198: T26E0485 | E198: 1200 | F198: KG | G198: Z01 | H198: 1196 | I198: 46164 | J198: 46164 | K198: 0.27777778 | L198: 0.30277778 | N198: 46162 | O198: 46162 | P198: 0.75435185 | R198: ENTE IMPR CNPA CAPC CPRE DMNV FRNP LOAT* | S198: SA RISQUE ESM EFT GLIT MIL PURPURINAS | T198: 1 | U198: ZSC2 | V198: RMELO | W198: 0.52775463
A199: 461829 | B199: SA BOZZANO CLINICAL ULTRA COOL AERO | C199: 1963049 | D199: T26E0614 | E199: 1000 | F199: KG | G199: Z11 | H199: 996 | I199: 46163 | J199: 46164 | K199: 0 | L199: 0.086805556 | N199: 46163 | O199: 46163 | P199: 0.83908565 | R199: ENTE IMPR CNPA CAPC CPRE DMNV FRNP LOAT* | S199: SA BOZZANO CLINICAL ULTRA COOL AERO | T199: 1 | U199: ZSC2 | V199: RMELO | W199: 0.52775463
A200: 456282 | B200: SA WELLA KOLESTON OIL AOX 9% DEITY | C200: 1963193 | D200: T26E0723 | E200: 2500 | F200: KG | G200: Z09 | H200: 2490 | I200: 46167 | J200: 46167 | K200: 0 | L200: 0 | N200: 46164 | O200: 46164 | P200: 0.73765046 | R200: ENTE IMPR CNPA CAPC CPRE FRNP LOAT MOME* | S200: SA WELLA KOLESTON OIL AOX 9% | T200: 1 | U200: ZSC2 | V200: RMELO | W200: 0.5277662
A201: 456282 | B201: SA WELLA KOLESTON OIL AOX 9% DEITY | C201: 1963194 | D201: T26E0724 | E201: 2500 | F201: KG | G201: Z09 | H201: 2480 | I201: 46168 | J201: 46168 | K201: 0.27777778 | L201: 0.27777778 | N201: 46165 | O201: 46165 | P201: 0.94449074 | R201: ENTE IMPR CNPA CAPC CPRE FRNP LOAT MOME* | S201: SA WELLA KOLESTON OIL AOX 9% | T201: 1 | U201: ZSC2 | V201: RMELO | W201: 0.5277662
A202: 454867 | B202: SA GEL BENTONE TFF RISQUE | C202: 1963202 | D202: T26E0748 | E202: 700 | F202: KG | G202: Z01 | H202: 0 | I202: 46185 | J202: 46185 | K202: 0.27777778 | L202: 0.49652778 | P202: 0 | R202: LIB MATF CAPC CPRE DMNV LOAT NOLQ ORSL | S202: SA GEL BENTONE TFF TESTE | T202: 1 | U202: ZSC2 | V202: ABFERNANDE | W202: 0.68873843
A203: 454867 | B203: SA GEL BENTONE TFF RISQUE | C203: 1963203 | D203: T26E0749 | E203: 700 | F203: KG | G203: Z01 | H203: 0 | I203: 46186 | J203: 46186 | K203: 0.27777778 | L203: 0.49652778 | P203: 0 | R203: LIB MATF CAPC CPRE DMNV LOAT NOLQ ORSL | S203: SA GEL BENTONE TFF TESTE | T203: 1 | U203: ZSC2 | V203: JFRANCO2 | W203: 0.47972222
A204: 454867 | B204: SA GEL BENTONE TFF RISQUE | C204: 1963204 | D204: T26E0750 | E204: 700 | F204: KG | G204: Z01 | H204: 0 | I204: 46186 | J204: 46186 | K204: 0.27777778 | L204: 0.49652778 | P204: 0 | R204: LIB MATF CAPC CPRE DMNV LOAT NOLQ ORSL | S204: SA GEL BENTONE TFF TESTE | T204: 1 | U204: ZSC2 | V204: JFRANCO2 | W204: 0.4797338
A205: 454867 | B205: SA GEL BENTONE TFF RISQUE | C205: 1963205 | D205: T26E0751 | E205: 700 | F205: KG | G205: Z01 | H205: 0 | I205: 46188 | J205: 46188 | K205: 0.27777778 | L205: 0.49652778 | P205: 0 | R205: LIB MATF CAPC CPRE DMNV LOAT NOLQ ORSL | S205: SA GEL BENTONE TFF TESTE | T205: 1 | U205: ZSC2 | V205: JFRANCO2 | W205: 0.47975694
A206: 454867 | B206: SA GEL BENTONE TFF RISQUE | C206: 1963206 | D206: T26E0752 | E206: 700 | F206: KG | G206: Z01 | H206: 0 | I206: 46188 | J206: 46188 | K206: 0.27777778 | L206: 0.49652778 | P206: 0 | R206: LIB MATF CAPC CPRE DMNV LOAT NOLQ ORSL | S206: SA GEL BENTONE TFF TESTE | T206: 1 | U206: ZSC2 | V206: JFRANCO2 | W206: 0.47976852
A207: 454867 | B207: SA GEL BENTONE TFF RISQUE | C207: 1963207 | D207: T26E0753 | E207: 700 | F207: KG | G207: Z01 | H207: 0 | I207: 46189 | J207: 46189 | K207: 0.27777778 | L207: 0.49652778 | P207: 0 | R207: LIB MATF CAPC CPRE DMNV LOAT NOLQ ORSL | S207: SA GEL BENTONE TFF TESTE | T207: 1 | U207: ZSC2 | V207: JFRANCO2 | W207: 0.47978009
A208: 454867 | B208: SA GEL BENTONE TFF RISQUE | C208: 1963208 | D208: T26E0754 | E208: 700 | F208: KG | G208: Z01 | H208: 0 | I208: 46189 | J208: 46189 | K208: 0.27777778 | L208: 0.49652778 | P208: 0 | R208: LIB MATF CAPC CPRE DMNV LOAT NOLQ ORSL | S208: SA GEL BENTONE TFF TESTE | T208: 1 | U208: ZSC2 | V208: JFRANCO2 | W208: 0.47979167
...

Sheet COHVPI
A1: Ordem | B1: Nº do material | C1: Texto breve de material | D1: Lote | E1: Quantidade da ordem (GMEIN) | F1: Qtd.fornecida (GMEIN) | G1: Unidade de medida (=GMEIN) | H1: Planejador MRP | I1: Data início (prog.) | J1: Data de conclusão base | K1: Hr.início programada | L1: Fim program. (hora) | M1: Linha de produção | N1: Status do sistema
A2: 1960533 | B2: 13441-6 | C2: BOZZANO DES ANTI S PERF SENS 12X90G NVF | E2: 14158 | F2: 0 | G2: CX | H2: Z11 | I2: 46143 | J2: 46144 | K2: 0.27777778 | L2: 0.35820602 | N2: ENTE CNAT DMNV NOLQ ORSL
A3: 1960534 | B3: 13441-6 | C3: BOZZANO DES ANTI S PERF SENS 12X90G NVF | D3: 6121C1 | E3: 7079 | F3: 7392 | G3: CX | H3: Z11 | I3: 46144 | J3: 46164 | K3: 0.14740741 | L3: 0.90743056 | N3: ENTE IMPR CNPA FORN CAPC CPRE DMNV LOAT*
A4: 1962336 | B4: 13441-6 | C4: BOZZANO DES ANTI S PERF SENS 12X90G NVF | D4: 6139C1 | E4: 21237 | F4: 22010 | G4: CX | H4: Z11 | I4: 46161 | J4: 46171 | K4: 0.53959491 | L4: 0.040428241 | N4: ENTE MATF IMPR CNPA FORN CAPC CPRE DMNV*
A5: 1959055 | B5: 17107-7 | C5: MONANGE DES ANTI SENSIVEL 12X90G NVF | E5: 14866 | F5: 0 | G5: CX | H5: Z11 | I5: 46143 | J5: 46144 | K5: 0.27777778 | L5: 0.41224537 | N5: ENTE CNAT DMNV NOLQ ORSL
A6: 1962321 | B6: 17107-7 | C6: MONANGE DES ANTI SENSIVEL 12X90G NVF | D6: 6133C1 | E6: 14866 | F6: 14553 | G6: CX | H6: Z11 | I6: 46156 | J6: 46157 | K6: 0.37100694 | L6: 0.48715278 | N6: ENTE MATF IMPR CNPA CAPC CPRE DMNV FRNP*
A7: 1964893 | B7: 17107-7 | C7: MONANGE DES ANTI SENSIVEL 12X90G NVF | E7: 7433 | F7: 0 | G7: CX | H7: Z11 | I7: 46184 | J7: 46184 | K7: 0.27777778 | L7: 0.84501157 | N7: ABER CNAT DMNV NOLQ ORSL
A8: 1962558 | B8: 17109-6 | C8: MONANGE DES ANTI FLOR LAV 12X90G NVF | D8: 6131C1 | E8: 14866 | F8: 14628 | G8: CX | H8: Z11 | I8: 46153 | J8: 46154 | K8: 0.77813657 | L8: 0.9006713 | N8: ENTE MATF IMPR CNPA CAPC CPRE DMNV FRNP*
A9: 1963258 | B9: 17109-6 | C9: MONANGE DES ANTI FLOR LAV 12X90G NVF | D9: 5363C1R | E9: 321 | F9: 415 | G9: CX | H9: Z11 | I9: 46168 | J9: 46168 | K9: 0.27777778 | L9: 0.30226852 | N9: ENTE MATF IMPR CNPA FORN CAPC CPRE LOAT*
A10: 1963257 | B10: 17109-6 | C10: MONANGE DES ANTI FLOR LAV 12X90G NVF | D10: 5315C1R | E10: 418 | F10: 0 | G10: CX | H10: Z11 | I10: 46175 | J10: 46175 | K10: 0.30594907 | L10: 0.33784722 | N10: ENTE MATF IMPR CAPC CPRE DMNV LOAT NOLQ*
A11: 1964982 | B11: 17109-6 | C11: MONANGE DES ANTI FLOR LAV 12X90G NVF | D11: 5363C1R | E11: 418 | F11: 0 | G11: CX | H11: Z11 | I11: 46175 | J11: 46175 | K11: 0.30609954 | L11: 0.33799769 | N11: ENTE CNAT DMNV LOAT NOLQ ORSL
A12: 1964894 | B12: 17109-6 | C12: MONANGE DES ANTI FLOR LAV 12X90G NVF | E12: 7433 | F12: 0 | G12: CX | H12: Z11 | I12: 46182 | J12: 46182 | K12: 0.27777778 | L12: 0.84501157 | N12: ABER CNAT DMNV NOLQ ORSL
A13: 1962325 | B13: 17109-7 | C13: MONANGE DES ANTIT FL LAV 12X90G MT | D13: 6140C1 | E13: 22299 | F13: 22040 | G13: CX | H13: Z11 | I13: 46162 | J13: 46164 | K13: 0.98503472 | L13: 0.68829861 | N13: ENTE MATF IMPR CNPA CAPC CPRE DMNV FRNP*
A14: 1962326 | B14: 17109-7 | C14: MONANGE DES ANTIT FL LAV 12X90G MT | D14: 6142C1 | E14: 22299 | F14: 21406 | G14: CX | H14: Z11 | I14: 46164 | J14: 46167 | K14: 0.74533565 | L14: 0.4659375 | N14: ENTE MATF IMPR CNPA CAPC CPRE DMNV FRNP*
A15: 1960584 | B15: 17109-7 | C15: MONANGE DES ANTIT FL LAV 12X90G MT | E15: 22299 | F15: 0 | G15: CX | H15: Z11 | I15: 46167 | J15: 46168 | K15: 0.27777778 | L15: 0.42484954 | N15: ENTE CNAT DMNV NOLQ ORSL
A16: 1962327 | B16: 17109-7 | C16: MONANGE DES ANTIT FL LAV 12X90G MT | D16: 6145C1 | E16: 22299 | F16: 22320 | G16: CX | H16: Z11 | I16: 46167 | J16: 46169 | K16: 0.85907407 | L16: 0.55775463 | N16: ENTE MATF IMPR CNPA FORN CAPC CPRE DMNV*
A17: 1960585 | B17: 17109-7 | C17: MONANGE DES ANTIT FL LAV 12X90G MT | E17: 22299 | F17: 0 | G17: CX | H17: Z11 | I17: 46168 | J17: 46169 | K17: 0.27777778 | L17: 0.42484954 | N17: ENTE CNAT DMNV NOLQ ORSL
A18: 1962328 | B18: 17109-7 | C18: MONANGE DES ANTIT FL LAV 12X90G MT | D18: 6147C1 | E18: 22299 | F18: 21360 | G18: CX | H18: Z11 | I18: 46169 | J18: 46171 | K18: 0.680625 | L18: 0.39908565 | N18: ENTE MATF IMPR CNPA CAPC CPRE DMNV FRNP*
A19: 1960586 | B19: 17109-7 | C19: MONANGE DES ANTIT FL LAV 12X90G MT | E19: 22299 | F19: 0 | G19: CX | H19: Z11 | I19: 46170 | J19: 46171 | K19: 0.27777778 | L19: 0.42484954 | N19: ENTE CNAT DMNV NOLQ ORSL
A20: 1960587 | B20: 17109-7 | C20: MONANGE DES ANTIT FL LAV 12X90G MT | E20: 22299 | F20: 0 | G20: CX | H20: Z11 | I20: 46171 | J20: 46172 | K20: 0.27777778 | L20: 0.42484954 | N20: ENTE CNAT DMNV NOLQ ORSL
A21: 1962329 | B21: 17109-7 | C21: MONANGE DES ANTIT FL LAV 12X90G MT | D21: 6149C1 | E21: 14866 | F21: 14640 | G21: CX | H21: Z11 | I21: 46171 | J21: 46172 | K21: 0.40277778 | L21: 0.54984954 | N21: ENTE MATF IMPR CNPA CAPC CPRE FRNP LOAT*
A22: 1962330 | B22: 17109-7 | C22: MONANGE DES ANTIT FL LAV 12X90G MT | D22: 6150C1 | E22: 14866 | F22: 14433 | G22: CX | H22: Z11 | I22: 46172 | J22: 46174 | K22: 0.65506944 | L22: 0.7031713 | N22: ENTE MATF IMPR CNPA CAPC CANC CPRE DMNV*
A23: 1960778 | B23: 17109-7 | C23: MONANGE DES ANTIT FL LAV 12X90G MT | E23: 22299 | F23: 0 | G23: CX | H23: Z11 | I23: 46174 | J23: 46175 | K23: 0.27777778 | L23: 0.42484954 | N23: ENTE CNAT DMNV NOLQ ORSL
A24: 1964904 | B24: 17109-7 | C24: MONANGE DES ANTIT FL LAV 12X90G MT | E24: 22299 | F24: 0 | G24: CX | H24: Z11 | I24: 46182 | J24: 46183 | K24: 0.27777778 | L24: 0.42484954 | N24: ABER CNAT DMNV NOLQ ORSL
A25: 1964905 | B25: 17109-7 | C25: MONANGE DES ANTIT FL LAV 12X90G MT | E25: 22299 | F25: 0 | G25: CX | H25: Z11 | I25: 46198 | J25: 46199 | K25: 0.27777778 | L25: 0.42484954 | N25: ABER CNAT DMNV NOLQ ORSL
A26: 1964906 | B26: 17109-7 | C26: MONANGE DES ANTIT FL LAV 12X90G MT | E26: 22299 | F26: 0 | G26: CX | H26: Z11 | I26: 46199 | J26: 46200 | K26: 0.27777778 | L26: 0.42484954 | N26: ABER CNAT DMNV NOLQ ORSL
A27: 1964891 | B27: 17110-7 | C27: MONANGE DES ANTI FRUTAS VM 12X90G NVF | D27: 6156C1 | E27: 7433 | F27: 2449 | G27: CX | H27: Z11 | I27: 46178 | J27: 46178 | K27: 0.27777778 | L27: 0.84501157 | N27: LIB MATF IMPR CNPA CAPC CPRE FRNP LOAT*
A28: 1960578 | B28: 17110-8 | C28: MONANGE DES ANTIT FRTS VM 12X90G MT | E28: 22299 | F28: 0 | G28: CX | H28: Z11 | I28: 46156 | J28: 46157 | K28: 0.27777778 | L28: 0.42484954 | N28: ENTE CNAT DMNV NOLQ ORSL
A29: 1960579 | B29: 17110-8 | C29: MONANGE DES ANTIT FRTS VM 12X90G MT | E29: 22299 | F29: 0 | G29: CX | H29: Z11 | I29: 46157 | J29: 46158 | K29: 0.27777778 | L29: 0.42484954 | N29: ENTE CNAT DMNV NOLQ ORSL
A30: 1960580 | B30: 17110-8 | C30: MONANGE DES ANTIT FRTS VM 12X90G MT | E30: 22299 | F30: 0 | G30: CX | H30: Z11 | I30: 46158 | J30: 46160 | K30: 0.27777778 | L30: 0.42484954 | N30: ENTE CNAT DMNV NOLQ ORSL
A31: 1960581 | B31: 17110-8 | C31: MONANGE DES ANTIT FRTS VM 12X90G MT | E31: 22299 | F31: 0 | G31: CX | H31: Z11 | I31: 46161 | J31: 46162 | K31: 0.27777778 | L31: 0.42484954 | N31: ENTE CNAT DMNV NOLQ ORSL
A32: 1960582 | B32: 17110-8 | C32: MONANGE DES ANTIT FRTS VM 12X90G MT | E32: 22299 | F32: 0 | G32: CX | H32: Z11 | I32: 46162 | J32: 46163 | K32: 0.27777778 | L32: 0.42484954 | N32: ENTE CNAT DMNV NOLQ ORSL
A33: 1962369 | B33: 17110-8 | C33: MONANGE DES ANTIT FRTS VM 12X90G MT | D33: 6140C1 | E33: 22299 | F33: 22320 | G33: CX | H33: Z11 | I33: 46162 | J33: 46163 | K33: 0.57511574 | L33: 0.7221875 | N33: ENTE MATF IMPR CNPA FORN CAPC CPRE DMNV*
A34: 1960583 | B34: 17110-8 | C34: MONANGE DES ANTIT FRTS VM 12X90G MT | E34: 22299 | F34: 0 | G34: CX | H34: Z11 | I34: 46163 | J34: 46164 | K34: 0.27777778 | L34: 0.42484954 | N34: ENTE CNAT DMNV NOLQ ORSL
A35: 1962370 | B35: 17110-8 | C35: MONANGE DES ANTIT FRTS VM 12X90G MT | D35: 6141C1 | E35: 22299 | F35: 22320 | G35: CX | H35: Z11 | I35: 46163 | J35: 46164 | K35: 0.84774306 | L35: 0.94572917 | N35: ENTE MATF IMPR CNPA FORN CAPC CPRE DMNV*
A36: 1962371 | B36: 17110-8 | C36: MONANGE DES ANTIT FRTS VM 12X90G MT | D36: 6142C1 | E36: 22299 | F36: 22186 | G36: CX | H36: Z11 | I36: 46165 | J36: 46166 | K36: 0.0012152778 | L36: 0.27777778 | N36: ENTE MATF IMPR CNPA CAPC CPRE DMNV FRNP*
A37: 1960827 | B37: 17110-8 | C37: MONANGE DES ANTIT FRTS VM 12X90G MT | E37: 22299 | F37: 0 | G37: CX | H37: Z11 | I37: 46165 | J37: 46167 | K37: 0.27777778 | L37: 0.42484954 | N37: ENTE CNAT DMNV NOLQ ORSL
A38: 1962372 | B38: 17110-8 | C38: MONANGE DES ANTIT FRTS VM 12X90G MT | D38: 6145C1 | E38: 22299 | F38: 22560 | G38: CX | H38: Z11 | I38: 46167 | J38: 46168 | K38: 0.52548611 | L38: 0.67255787 | N38: ENTE MATF IMPR CNPA FORN CAPC CPRE DMNV*
A39: 1962373 | B39: 17110-8 | C39: MONANGE DES ANTIT FRTS VM 12X90G MT | D39: 6146C1 | E39: 22299 | F39: 22560 | G39: CX | H39: Z11 | I39: 46168 | J39: 46169 | K39: 0.74800926 | L39: 0.89508102 | N39: ENTE MATF IMPR CNPA FORN CAPC CPRE DMNV*
A40: 1962374 | B40: 17110-8 | C40: MONANGE DES ANTIT FRTS VM 12X90G MT | D40: 6147C1 | E40: 22299 | F40: 22646 | G40: CX | H40: Z11 | I40: 46170 | J40: 46171 | K40: 0.13640046 | L40: 0.15508102 | N40: ENTE IMPR CNPA FORN CAPC CPRE DMNV LOAT*
A41: 1962375 | B41: 17110-8 | C41: MONANGE DES ANTIT FRTS VM 12X90G MT | D41: 6149C1 | E41: 14866 | F41: 15021 | G41: CX | H41: Z11 | I41: 46171 | J41: 46171 | K41: 0.22541667 | L41: 0.9827662 | N41: ENTE IMPR CNPA FORN CAPC CPRE DMNV LOAT*
A42: 1962376 | B42: 17110-8 | C42: MONANGE DES ANTIT FRTS VM 12X90G MT | D42: 6149C2 | E42: 14866 | F42: 15120 | G42: CX | H42: Z11 | I42: 46171 | J42: 46172 | K42: 0.98611111 | L42: 0.75082176 | N42: ENTE MATF IMPR CNPA FORN CAPC CPRE LOAT*
A43: 1964902 | B43: 17110-8 | C43: MONANGE DES ANTIT FRTS VM 12X90G MT | E43: 22299 | F43: 0 | G43: CX | H43: Z11 | I43: 46195 | J43: 46196 | K43: 0.27777778 | L43: 0.42484954 | N43: ABER CNAT DMNV NOLQ ORSL
A44: 1964903 | B44: 17110-8 | C44: MONANGE DES ANTIT FRTS VM 12X90G MT | E44: 22299 | F44: 0 | G44: CX | H44: Z11 | I44: 46196 | J44: 46197 | K44: 0.27777778 | L44: 0.42484954 | N44: ABER CNAT DMNV NOLQ ORSL
A45: 1962536 | B45: 17111-6 | C45: MONANGE DES ANTI HIDR INTEN 12X90G NVF | D45: 6132C1 | E45: 14866 | F45: 14517 | G45: CX | H45: Z11 | I45: 46155 | J45: 46156 | K45: 0.015590278 | L45: 0.15005787 | N45: ENTE IMPR CNPA CAPC CPRE DMNV FRNP LOAT*
A46: 1960572 | B46: 17111-7 | C46: MONANGE DES ANTIT HIDR INTEN 12X90G MT | D46: 6125C1 | E46: 22299 | F46: 22320 | G46: CX | H46: Z11 | I46: 46147 | J46: 46148 | K46: 0.30038194 | L46: 0.4474537 | N46: ENTE MATF IMPR CNPA FORN CAPC CPRE DMNV*
A47: 1960573 | B47: 17111-7 | C47: MONANGE DES ANTIT HIDR INTEN 12X90G MT | D47: 6125C2 | E47: 22299 | F47: 22080 | G47: CX | H47: Z11 | I47: 46148 | J47: 46149 | K47: 0.58365741 | L47: 0.70982639 | N47: ENTE IMPR CNPA CAPC CPRE DMNV FRNP LOAT*
A48: 1960574 | B48: 17111-7 | C48: MONANGE DES ANTIT HIDR INTEN 12X90G MT | D48: 6127C1 | E48: 22299 | F48: 22703 | G48: CX | H48: Z11 | I48: 46149 | J48: 46150 | K48: 0.73847222 | L48: 0.88554398 | N48: ENTE MATF IMPR CNPA FORN CAPC CPRE DMNV*
A49: 1960575 | B49: 17111-7 | C49: MONANGE DES ANTIT HIDR INTEN 12X90G MT | D49: 6129C1 | E49: 22299 | F49: 22985 | G49: CX | H49: Z11 | I49: 46151 | J49: 46153 | K49: 0.36542824 | L49: 0.5125 | N49: ENTE MATF IMPR CNPA FORN CAPC CPRE DMNV*
A50: 1960576 | B50: 17111-7 | C50: MONANGE DES ANTIT HIDR INTEN 12X90G MT | E50: 22299 | F50: 0 | G50: CX | H50: Z11 | I50: 46153 | J50: 46154 | K50: 0.27777778 | L50: 0.42484954 | N50: ENTE CNAT DMNV NOLQ ORSL
A51: 1960577 | B51: 17111-7 | C51: MONANGE DES ANTIT HIDR INTEN 12X90G MT | E51: 22299 | F51: 0 | G51: CX | H51: Z11 | I51: 46154 | J51: 46155 | K51: 0.27777778 | L51: 0.42484954 | N51: ENTE CNAT DMNV NOLQ ORSL
A52: 1962367 | B52: 17111-7 | C52: MONANGE DES ANTIT HIDR INTEN 12X90G MT | D52: 6136C1 | E52: 22299 | F52: 22414 | G52: CX | H52: Z11 | I52: 46158 | J52: 46161 | K52: 0.92465278 | L52: 0.028865741 | N52: ENTE MATF IMPR CNPA FORN CAPC CPRE DMNV*
A53: 1962368 | B53: 17111-7 | C53: MONANGE DES ANTIT HIDR INTEN 12X90G MT | D53: 6138C1 | E53: 22299 | F53: 22830 | G53: CX | H53: Z11 | I53: 46161 | J53: 46162 | K53: 0.31648148 | L53: 0.43938657 | N53: ENTE MATF IMPR CNPA FORN CAPC CPRE DMNV*
A54: 1962764 | B54: 17111-7 | C54: MONANGE DES ANTIT HIDR INTEN 12X90G MT | D54: 6143C1 | E54: 14866 | F54: 14321 | G54: CX | H54: Z11 | I54: 46165 | J54: 46168 | K54: 0.94530093 | L54: 0.092372685 | N54: ENTE MATF IMPR CNPA CAPC CPRE DMNV FRNP*
A55: 1962765 | B55: 17111-7 | C55: MONANGE DES ANTIT HIDR INTEN 12X90G MT | D55: 6146C1 | E55: 14866 | F55: 14584 | G55: CX | H55: Z11 | I55: 46168 | J55: 46169 | K55: 0.60834491 | L55: 0.75541667 | N55: ENTE MATF IMPR CNPA CAPC CPRE DMNV FRNP*
A56: 1964864 | B56: 17111-7 | C56: MONANGE DES ANTIT HIDR INTEN 12X90G MT | E56: 22299 | F56: 0 | G56: CX | H56: Z11 | I56: 46189 | J56: 46190 | K56: 0.27777778 | L56: 0.42484954 | N56: ABER CNAT DMNV NOLQ ORSL
A57: 1964865 | B57: 17111-7 | C57: MONANGE DES ANTIT HIDR INTEN 12X90G MT | E57: 22299 | F57: 0 | G57: CX | H57: Z11 | I57: 46191 | J57: 46192 | K57: 0.27777778 | L57: 0.42484954 | N57: ABER CNAT DMNV NOLQ ORSL
A58: 1964866 | B58: 17111-7 | C58: MONANGE DES ANTIT HIDR INTEN 12X90G MT | E58: 22299 | F58: 0 | G58: CX | H58: Z11 | I58: 46192 | J58: 46193 | K58: 0.27777778 | L58: 0.42484954 | N58: ABER CNAT DMNV NOLQ ORSL
A59: 1964867 | B59: 17111-7 | C59: MONANGE DES ANTIT HIDR INTEN 12X90G MT | E59: 14866 | F59: 0 | G59: CX | H59: Z11 | I59: 46193 | J59: 46194 | K59: 0.27777778 | L59: 0.042488426 | N59: ABER CNAT DMNV NOLQ ORSL
A60: 1960539 | B60: 17425-5 | C60: BOZZANO DES ANTI ANTBAC FRESH 12X90G NVF | D60: 6127C1 | E60: 14866 | F60: 14640 | G60: CX | H60: Z11 | I60: 46150 | J60: 46151 | K60: 0.375 | L60: 0.50946759 | N60: ENTE MATF IMPR CNPA CAPC CPRE DMNV FRNP*
A61: 1962331 | B61: 17425-5 | C61: BOZZANO DES ANTI ANTBAC FRESH 12X90G NVF | D61: 6129C1 | E61: 22299 | F61: 21952 | G61: CX | H61: Z11 | I61: 46151 | J61: 46154 | K61: 0.90751157 | L61: 0.54707176 | N61: ENTE MATF IMPR CNPA CAPC CPRE DMNV FRNP*
A62: 1960540 | B62: 17425-5 | C62: BOZZANO DES ANTI ANTBAC FRESH 12X90G NVF | E62: 14866 | F62: 0 | G62: CX | H62: Z11 | I62: 46153 | J62: 46154 | K62: 0.27777778 | L62: 0.41224537 | N62: ENTE CNAT DMNV NOLQ ORSL
A63: 1960541 | B63: 17425-5 | C63: BOZZANO DES ANTI ANTBAC FRESH 12X90G NVF | E63: 14866 | F63: 0 | G63: CX | H63: Z11 | I63: 46154 | J63: 46155 | K63: 0.27777778 | L63: 0.41224537 | N63: ENTE CNAT DMNV NOLQ ORSL
A64: 1962332 | B64: 17425-5 | C64: BOZZANO DES ANTI ANTBAC FRESH 12X90G NVF | D64: 6132C1 | E64: 14866 | F64: 14852 | G64: CX | H64: Z11 | I64: 46154 | J64: 46155 | K64: 0.88133102 | L64: 0.95774306 | N64: ENTE MATF IMPR CNPA CAPC CPRE DMNV FRNP*
A65: 1964886 | B65: 17425-5 | C65: BOZZANO DES ANTI ANTBAC FRESH 12X90G NVF | E65: 22299 | F65: 0 | G65: CX | H65: Z11 | I65: 46203 | J65: 46204 | K65: 0.27777778 | L65: 0.97946759 | N65: ABER CNAT DMNV NOLQ ORSL
A66: 1960535 | B66: 18998-5 | C66: BOZZANO DES ANTI EXTREM SPORT 12X90G NVF | D66: 6124C1 | E66: 14866 | F66: 14160 | G66: CX | H66: Z11 | I66: 46146 | J66: 46150 | K66: 0.9477662 | L66: 0.62582176 | N66: ENTE MATF IMPR CNPA CAPC CPRE DMNV FRNP*
A67: 1960537 | B67: 18998-5 | C67: BOZZANO DES ANTI EXTREM SPORT 12X90G NVF | D67: 6125C1 | E67: 14866 | F67: 14640 | G67: CX | H67: Z11 | I67: 46148 | J67: 46149 | K67: 0.15587963 | L67: 0.2243287 | N67: ENTE MATF IMPR CNPA CAPC CPRE DMNV FRNP*
A68: 1960538 | B68: 18998-5 | C68: BOZZANO DES ANTI EXTREM SPORT 12X90G NVF | D68: 6126C1 | E68: 14866 | F68: 15126 | G68: CX | H68: Z11 | I68: 46149 | J68: 46150 | K68: 0.26979167 | L68: 0.36909722 | N68: ENTE IMPR CNPA FORN CAPC CPRE DMNV LOAT*
A69: 1963494 | B69: 18998-5 | C69: BOZZANO DES ANTI EXTREM SPORT 12X90G NVF | E69: 14866 | F69: 0 | G69: CX | H69: Z11 | I69: 46203 | J69: 46204 | K69: 0.27777778 | L69: 0.025868056 | N69: ABER CNAT DMNV NOLQ ORSL
A70: 1963495 | B70: 18998-5 | C70: BOZZANO DES ANTI EXTREM SPORT 12X90G NVF | E70: 14866 | F70: 0 | G70: CX | H70: Z11 | I70: 46203 | J70: 46204 | K70: 0.27777778 | L70: 0.025868056 | N70: ABER CNAT DMNV NOLQ ORSL
A71: 1963254 | B71: 20003-6 | C71: ADIDAS DES ANTI CONTROL FEM 150ML NVF | D71: 6026C1R | E71: 3614 | F71: 3603 | G71: CX | H71: Z11 | I71: 46163 | J71: 46163 | K71: 0.27777778 | L71: 0.55357639 | N71: ENTE MATF IMPR CNPA CAPC CPRE DMNV FRNP*
A72: 1960546 | B72: 20159-4 | C72: BOZZANO DES ANTI INVISIBLE 12X89G NVF | E72: 15026 | F72: 0 | G72: CX | H72: Z11 | I72: 46162 | J72: 46163 | K72: 0.27777778 | L72: 0.42445602 | N72: ENTE CNAT DMNV NOLQ ORSL
A73: 1960547 | B73: 20159-4 | C73: BOZZANO DES ANTI INVISIBLE 12X89G NVF | E73: 15026 | F73: 0 | G73: CX | H73: Z11 | I73: 46163 | J73: 46164 | K73: 0.27777778 | L73: 0.42445602 | N73: ENTE CNAT DMNV NOLQ ORSL
A74: 1962344 | B74: 20159-4 | C74: BOZZANO DES ANTI INVISIBLE 12X89G NVF | E74: 22539 | F74: 0 | G74: CX | H74: Z11 | I74: 46169 | J74: 46170 | K74: 0.27777778 | L74: 0.99778935 | N74: ENTE CNAT DMNV NOLQ ORSL
A75: 1963469 | B75: 20159-4 | C75: BOZZANO DES ANTI INVISIBLE 12X89G NVF | D75: 6153C1 | E75: 22539 | F75: 23158 | G75: CX | H75: Z11 | I75: 46176 | J75: 46177 | K75: 0.375 | L75: 0.50921296 | N75: LIB MATF IMPR CNPA FORN CAPC CPRE DMNV*
A76: 1963470 | B76: 20159-4 | C76: BOZZANO DES ANTI INVISIBLE 12X89G NVF | E76: 22539 | F76: 0 | G76: CX | H76: Z11 | I76: 46190 | J76: 46191 | K76: 0.27777778 | L76: 0.99778935 | N76: ABER CNAT DMNV NOLQ ORSL
A77: 1963047 | B77: 20257-3 | C77: MONANGE DES ANTI INVISIVEL 12X89G NVF | D77: 6135C1 | E77: 7513 | F77: 7473 | G77: CX | H77: Z11 | I77: 46157 | J77: 46158 | K77: 0.48611111 | L77: 0.059444444 | N77: ENTE MATF IMPR CNPA CAPC CPRE DMNV FRNP*
A78: 1963255 | B78: 20257-3 | C78: MONANGE DES ANTI INVISIVEL 12X89G NVF | D78: 6099C1R | E78: 1440 | F78: 0 | G78: CX | H78: Z11 | I78: 46175 | J78: 46175 | K78: 0.305625 | L78: 0.41552083 | N78: ENTE CNAT DMNV LOAT NOLQ ORSL
A79: 1965407 | B79: 20257-3 | C79: MONANGE DES ANTI INVISIVEL 12X89G NVF | D79: 6099C1R | E79: 1286 | F79: 0 | G79: CX | H79: Z11 | I79: 46176 | J79: 46176 | K79: 0.27777778 | L79: 0.37591435 | N79: ENTE MATF IMPR CAPC CPRE LOAT NOLQ ORSL
A80: 1964890 | B80: 20257-3 | C80: MONANGE DES ANTI INVISIVEL 12X89G NVF | D80: 6155C1 | E80: 7513 | F80: 7495 | G80: CX | H80: Z11 | I80: 46177 | J80: 46177 | K80: 0.27777778 | L80: 0.85111111 | N80: LIB MATF IMPR CNPA CAPC CPRE FRNP LOAT*
A81: 1962363 | B81: 20257-4 | C81: MONANGE DES ANTIT INVISL 12X89G MT | D81: 6131C1 | E81: 22539 | F81: 23040 | G81: CX | H81: Z11 | I81: 46153 | J81: 46161 | K81: 0.86094907 | L81: 0.93326389 | N81: ENTE MATF IMPR CNPA FORN CAPC CPRE DMNV*
A82: 1960519 | B82: 20257-4 | C82: MONANGE DES ANTIT INVISL 12X89G MT | E82: 15026 | F82: 0 | G82: CX | H82: Z11 | I82: 46154 | J82: 46155 | K82: 0.27777778 | L82: 0.4371875 | N82: ENTE CNAT DMNV NOLQ ORSL
A83: 1962364 | B83: 20257-4 | C83: MONANGE DES ANTIT INVISL 12X89G MT | D83: 6132C1 | E83: 22539 | F83: 23040 | G83: CX | H83: Z11 | I83: 46155 | J83: 46156 | K83: 0.071851852 | L83: 0.23016204 | N83: ENTE MATF IMPR CNPA FORN CAPC CPRE DMNV*
A84: 1960520 | B84: 20257-4 | C84: MONANGE DES ANTIT INVISL 12X89G MT | E84: 15026 | F84: 0 | G84: CX | H84: Z11 | I84: 46156 | J84: 46157 | K84: 0.27777778 | L84: 0.4371875 | N84: ENTE CNAT DMNV NOLQ ORSL
A85: 1962365 | B85: 20257-4 | C85: MONANGE DES ANTIT INVISL 12X89G MT | D85: 6133C1 | E85: 22539 | F85: 23040 | G85: CX | H85: Z11 | I85: 46156 | J85: 46157 | K85: 0.34725694 | L85: 0.47773148 | N85: ENTE IMPR CNPA FORN CAPC CPRE DMNV LOAT*
A86: 1960521 | B86: 20257-4 | C86: MONANGE DES ANTIT INVISL 12X89G MT | E86: 15026 | F86: 0 | G86: CX | H86: Z11 | I86: 46157 | J86: 46158 | K86: 0.27777778 | L86: 0.4371875 | N86: ENTE CNAT DMNV NOLQ ORSL
A87: 1962366 | B87: 20257-4 | C87: MONANGE DES ANTIT INVISL 12X89G MT | D87: 6135C1 | E87: 22539 | F87: 23485 | G87: CX | H87: Z11 | I87: 46157 | J87: 46158 | K87: 0.47916667 | L87: 0.63857639 | N87: ENTE MATF IMPR CNPA FORN CAPC CPRE LOAT*
A88: 1960522 | B88: 20257-4 | C88: MONANGE DES ANTIT INVISL 12X89G MT | E88: 15026 | F88: 0 | G88: CX | H88: Z11 | I88: 46160 | J88: 46161 | K88: 0.27777778 | L88: 0.4371875 | N88: ENTE CNAT DMNV NOLQ ORSL
A89: 1960523 | B89: 20257-4 | C89: MONANGE DES ANTIT INVISL 12X89G MT | E89: 15026 | F89: 0 | G89: CX | H89: Z11 | I89: 46161 | J89: 46162 | K89: 0.27777778 | L89: 0.4371875 | N89: ENTE CNAT DMNV NOLQ ORSL
A90: 1960524 | B90: 20257-4 | C90: MONANGE DES ANTIT INVISL 12X89G MT | E90: 15026 | F90: 0 | G90: CX | H90: Z11 | I90: 46162 | J90: 46163 | K90: 0.27777778 | L90: 0.4371875 | N90: ENTE CNAT DMNV NOLQ ORSL
A91: 1960525 | B91: 20257-4 | C91: MONANGE DES ANTIT INVISL 12X89G MT | E91: 15026 | F91: 0 | G91: CX | H91: Z11 | I91: 46164 | J91: 46165 | K91: 0.27777778 | L91: 0.4371875 | N91: ENTE CNAT DMNV NOLQ ORSL
A92: 1960526 | B92: 20257-4 | C92: MONANGE DES ANTIT INVISL 12X89G MT | E92: 15026 | F92: 0 | G92: CX | H92: Z11 | I92: 46165 | J92: 46167 | K92: 0.27777778 | L92: 0.4371875 | N92: ENTE CNAT DMNV NOLQ ORSL
A93: 1960795 | B93: 20257-4 | C93: MONANGE DES ANTIT INVISL 12X89G MT | E93: 15026 | F93: 0 | G93: CX | H93: Z11 | I93: 46167 | J93: 46168 | K93: 0.27777778 | L93: 0.4371875 | N93: ENTE CNAT DMNV NOLQ ORSL
A94: 1962323 | B94: 20257-4 | C94: MONANGE DES ANTIT INVISL 12X89G MT | E94: 22539 | F94: 0 | G94: CX | H94: Z11 | I94: 46169 | J94: 46171 | K94: 0.27777778 | L94: 0.016898148 | N94: ENTE CNAT DMNV NOLQ ORSL
A95: 1962324 | B95: 20257-4 | C95: MONANGE DES ANTIT INVISL 12X89G MT | E95: 22539 | F95: 0 | G95: CX | H95: Z11 | I95: 46171 | J95: 46173 | K95: 0.27777778 | L95: 0.016898148 | N95: ENTE CNAT DMNV NOLQ ORSL
A96: 1963473 | B96: 20257-4 | C96: MONANGE DES ANTIT INVISL 12X89G MT | E96: 22539 | F96: 0 | G96: CX | H96: Z11 | I96: 46183 | J96: 46184 | K96: 0.27777778 | L96: 0.4371875 | N96: ABER CNAT DMNV NOLQ ORSL
A97: 1963474 | B97: 20257-4 | C97: MONANGE DES ANTIT INVISL 12X89G MT | E97: 22539 | F97: 0 | G97: CX | H97: Z11 | I97: 46184 | J97: 46185 | K97: 0.27777778 | L97: 0.4371875 | N97: ABER CNAT DMNV NOLQ ORSL
A98: 1964862 | B98: 20257-4 | C98: MONANGE DES ANTIT INVISL 12X89G MT | E98: 22539 | F98: 0 | G98: CX | H98: Z11 | I98: 46185 | J98: 46186 | K98: 0.27777778 | L98: 0.4371875 | N98: ABER CNAT DMNV NOLQ ORSL
A99: 1964863 | B99: 20257-4 | C99: MONANGE DES ANTIT INVISL 12X89G MT | E99: 22539 | F99: 0 | G99: CX | H99: Z11 | I99: 46188 | J99: 46189 | K99: 0.27777778 | L99: 0.4371875 | N99: ABER CNAT DMNV NOLQ ORSL
A100: 1963266 | B100: 23208-2 | C100: ADIDAS DES ANTI INVISIBLE FEM 150ML NVF | D100: 6148C1 | E100: 900 | F100: 0 | G100: CX | H100: Z11 | I100: 46178 | J100: 46178 | K100: 0.27777778 | L100: 0.34799769 | N100: ENTE MATF IMPR CAPC CPRE DMNV LOAT NOLQ*
...

Sheet VERSÃO DE PROD
A1: Versão de produção | B1: Ordem | C1: Nº do material | D1: Texto breve de material | E1: Unidade de medida (=GMEIN) | F1: Lote | G1: Planejador MRP | H1: Quantidade da ordem (GMEIN) | I1: Qtd.fornecida (GMEIN) | J1: Data-base iníc. | K1: Data de conclusão base | L1: Hr.início programada | M1: Fim program. (hora) | N1: Linha de produção | O1: Data início real | P1: Data fim real | Q1: Início real hr. | R1: Status do sistema | S1: Data início (prog.)
A2: L01 | B2: 1959749 | C2: 13784-6 | D2: RISQUE CARE COBERTURA BRILHANTE BL8ML | E2: UN | F2: 6141C1 | G2: Z01 | H2: 59375 | I2: 59514 | J2: 46163 | K2: 46163 | L2: 0.56458333 | M2: 0.82890046 | O2: 46163 | P2: 46164 | Q2: 0.86550926 | R2: LIB IMPR CNPA FORN CAPC CPRE LOAT MOME* | S2: 46163
A3: L01 | B3: 1959753 | C3: 13784-6 | D3: RISQUE CARE COBERTURA BRILHANTE BL8ML | E3: UN | F3: 6141C2 | G3: Z01 | H3: 83125 | I3: 82944 | J3: 46163 | K3: 46164 | L3: 0.14180556 | M3: 0.45916667 | O3: 46164 | P3: 46164 | Q3: 0.14180556 | R3: LIB IMPR CNPA CAPC CPRE DMNV FRNP LOAT* | S3: 46164
A4: L03 | B4: 1959760 | C4: 13788-7 | D4: RISQUE CARE COBERTURA BRILHANTE CL8ML | E4: UN | F4: 6142C1 | G4: Z01 | H4: 59375 | I4: 0 | J4: 46164 | K4: 46165 | L4: 0.45833333 | M4: 0.55163194 | Q4: 0 | R4: LIB IMPR CAPC CPRE DMNV LOAT NOLQ ORSL | S4: 46164
A5: L03 | B5: 1959761 | C5: 13788-7 | D5: RISQUE CARE COBERTURA BRILHANTE CL8ML | E5: UN | G5: Z01 | H5: 59375 | I5: 0 | J5: 46165 | K5: 46168 | L5: 0.59305556 | M5: 0.33913194 | Q5: 0 | R5: ABER CNAT DMNV NOLQ ORSL | S5: 46165
A6: L03 | B6: 1959762 | C6: 13788-7 | D6: RISQUE CARE COBERTURA BRILHANTE CL8ML | E6: UN | G6: Z01 | H6: 59375 | I6: 0 | J6: 46168 | K6: 46169 | L6: 0.38055556 | M6: 0.47385417 | Q6: 0 | R6: ABER CNAT DMNV NOLQ ORSL | S6: 46168
A7: L03 | B7: 1959763 | C7: 13788-7 | D7: RISQUE CARE COBERTURA BRILHANTE CL8ML | E7: UN | G7: Z01 | H7: 59375 | I7: 0 | J7: 46169 | K7: 46170 | L7: 0.51527778 | M7: 0.60857639 | Q7: 0 | R7: ABER CNAT DMNV NOLQ ORSL | S7: 46169
A8: L03 | B8: 1959764 | C8: 13788-7 | D8: RISQUE CARE COBERTURA BRILHANTE CL8ML | E8: UN | G8: Z01 | H8: 95000 | I8: 0 | J8: 46171 | K8: 46174 | L8: 0.27777778 | M8: 0.28815972 | Q8: 0 | R8: ABER CNAT DMNV NOLQ ORSL | S8: 46171
A9: L01 | B9: 1962872 | C9: 16214-3 | D9: RISQUE ESM CR CAPPUCCINO BL 8ML BI | E9: UN | F9: 6140C1 | G9: Z01 | H9: 95000 | I9: 94152 | J9: 46162 | K9: 46162 | L9: 0.35894676 | M9: 0.74704861 | O9: 46162 | P9: 46162 | Q9: 0.35894676 | R9: LIB IMPR CNPA CAPC CPRE DMNV FRNP LOAT* | S9: 46162
A10: L01 | B10: 1962871 | C10: 16220-4 | D10: RISQUE ESM CR BALI BL 8ML BI | E10: UN | G10: Z01 | H10: 95000 | I10: 0 | J10: 46176 | K10: 46177 | L10: 0.78611111 | M10: 0.20900463 | Q10: 0 | R10: ABER CNAT DMNV NOLQ ORSL | S10: 46176
A11: L01 | B11: 1962541 | C11: 17406-5 | D11: RISQUE ESM MET PSICO 8ML BL | E11: UN | F11: 6127C1 | G11: Z01 | H11: 71250 | I11: 0 | J11: 46150 | K11: 46151 | L11: 0.0076388889 | M11: 0.32481481 | Q11: 0 | R11: LIB IMPR CAPC CPRE DMNV LOAT MOME NOLQ* | S11: 46151
A12: L02 | B12: 1963553 | C12: 17435-3 | D12: RISQUE ESM MET OURO NUDE CL 8ML BI | E12: UN | G12: Z01 | H12: 47500 | I12: 0 | J12: 46177 | K12: 46177 | L12: 0.44861111 | M12: 0.65478009 | Q12: 0 | R12: ABER CNAT DMNV NOLQ ORSL | S12: 46177
A13: L01 | B13: 1963538 | C13: 19408-2 | D13: RISQUE ESM MET GOTA ANJOS BL 8ML BI | E13: UN | G13: Z01 | H13: 95000 | I13: 0 | J13: 46175 | K13: 46175 | L13: 0.45833333 | M13: 0.88122685 | Q13: 0 | R13: ABER CNAT DMNV NOLQ ORSL | S13: 46175
A14: L01 | B14: 1962870 | C14: 19409-2 | D14: RISQUE ESM CR GRAO ARROZ BL 8ML BI | E14: UN | G14: Z01 | H14: 47500 | I14: 0 | J14: 46176 | K14: 46176 | L14: 0.53333333 | M14: 0.74478009 | Q14: 0 | R14: ABER CNAT DMNV NOLQ ORSL | S14: 46176
A15: L01 | B15: 1963531 | C15: 19412-2 | D15: RISQUE ESM CR LAGRIMAS VENUS BL 8ML BI | E15: UN | G15: Z01 | H15: 47500 | I15: 0 | J15: 46176 | K15: 46176 | L15: 0.28055556 | M15: 0.49200231 | Q15: 0 | R15: ABER CNAT DMNV NOLQ ORSL | S15: 46176
A16: L02 | B16: 1963554 | C16: 19414-2 | D16: RISQUE ESM CR GRAO ARROZ CL 8ML BI | E16: UN | G16: Z01 | H16: 47500 | I16: 0 | J16: 46176 | K16: 46176 | L16: 0.64166667 | M16: 0.84783565 | Q16: 0 | R16: ABER CNAT DMNV NOLQ ORSL | S16: 46176
A17: L02 | B17: 1962827 | C17: 19417-2 | D17: RISQUE ESM CR LAGRIMAS VENUS CL 8ML BI | E17: UN | G17: Z01 | H17: 95000 | I17: 0 | J17: 46175 | K17: 46176 | L17: 0.87569444 | M17: 0.60052083 | Q17: 0 | R17: ABER CNAT DMNV NOLQ ORSL | S17: 46175
A18: L02 | B18: 1963555 | C18: 20236-2 | D18: RISQUE ESM CR BELA E PODEROSA CL 8ML BI | E18: UN | G18: Z01 | H18: 47500 | I18: 0 | J18: 46177 | K18: 46177 | L18: 0.69583333 | M18: 0.90200231 | Q18: 0 | R18: ABER CNAT DMNV NOLQ ORSL | S18: 46177
A19: L02 | B19: 1963556 | C19: 20264-2 | D19: RISQUE ESM CR MEUS SOUVENIRS CL 8ML BI | E19: UN | G19: Z01 | H19: 47500 | I19: 0 | J19: 46179 | K19: 46179 | L19: 0.525 | M19: 0.73116898 | Q19: 0 | R19: ABER CNAT DMNV NOLQ ORSL | S19: 46179
A20: L01 | B20: 1962877 | C20: 21949-2 | D20: RISQUE ESM EF GLIT MIL PURPURI BL 8ML BI | E20: UN | F20: 6140C1 | G20: Z01 | H20: 142500 | I20: 0 | J20: 46167 | K20: 46168 | L20: 0.60972222 | M20: 0.24407407 | Q20: 0 | R20: LIB MATF CAPC CPRE DMNV LOAT NOLQ ORSL | S20: 46167
A21: L01 | B21: 1962854 | C21: 21951-2 | D21: RISQUE ESM EF GLIT GRANUL ROSE BL 8ML BI | E21: UN | F21: 6139C1 | G21: Z01 | H21: 47500 | I21: 0 | J21: 46167 | K21: 46167 | L21: 0.35694444 | M21: 0.5683912 | Q21: 0 | R21: LIB IMPA CAPC CPRE DMNV LOAT NOLQ ORSL | S21: 46167
A22: L02 | B22: 1963740 | C22: 23229-1 | D22: RISQUE ESM CR VIOLETRAZ O NOVO CL 8ML BI | E22: UN | G22: Z01 | H22: 47500 | I22: 0 | J22: 46181 | K22: 46182 | L22: 0.88888889 | M22: 0.40755787 | Q22: 0 | R22: ABER CNAT DMNV NOLQ ORSL | S22: 46181
A23: L02 | B23: 1963557 | C23: 23243-1 | D23: RISQUE ESM CR LINDA LEVE NUDE CL 8ML BI | E23: UN | G23: Z01 | H23: 47500 | I23: 0 | J23: 46179 | K23: 46179 | L23: 0.27777778 | M23: 0.48394676 | Q23: 0 | R23: ABER CNAT DMNV NOLQ ORSL | S23: 46179
A24: L01 | B24: 1963543 | C24: 23248-1 | D24: RISQUE ESM CR LINDA LEVE NUDE BL 8ML BI | E24: UN | G24: Z01 | H24: 118750 | I24: 0 | J24: 46177 | K24: 46178 | L24: 0.75555556 | M24: 0.28417824 | Q24: 0 | R24: ABER CNAT DMNV NOLQ ORSL | S24: 46177
A25: L01 | B25: 1963544 | C25: 23248-1 | D25: RISQUE ESM CR LINDA LEVE NUDE BL 8ML BI | E25: UN | G25: Z01 | H25: 118750 | I25: 0 | J25: 46178 | K25: 46178 | L25: 0.32569444 | M25: 0.85431713 | Q25: 0 | R25: ABER CNAT DMNV NOLQ ORSL | S25: 46178
A26: L01 | B26: 1963530 | C26: 25418-1 | D26: RISQUE ESM CREM TODAS POR UMA BL 8ML NV | E26: UN | G26: Z01 | H26: 47500 | I26: 0 | J26: 46176 | K26: 46177 | L26: 0.25 | M26: 0.46144676 | Q26: 0 | R26: ABER CNAT DMNV NOLQ ORSL | S26: 46177
A27: L01 | B27: 1963527 | C27: 25443-0 | D27: RISQUE ESM CREM MOLETOM E SALTO BL 8ML | E27: UN | G27: Z01 | H27: 47500 | I27: 0 | J27: 46181 | K27: 46181 | L27: 0.74166667 | M27: 0.95311343 | Q27: 0 | R27: ABER CNAT DMNV NOLQ ORSL | S27: 46181
A28: L01 | B28: 1962855 | C28: 25444-0 | D28: RISQUE ESM CREM EUSOU ESS GLAM TDO BL8ML | E28: UN | G28: Z01 | H28: 47500 | I28: 0 | J28: 46181 | K28: 46182 | L28: 0.99444444 | M28: 0.2058912 | Q28: 0 | R28: ABER CNAT DMNV NOLQ ORSL | S28: 46181
A29: L02 | B29: 1959765 | C29: 25981-0 | D29: RISQUE CARE SECANTE EXPRESS CL 8ML | E29: UN | F29: 6132C1 | G29: Z01 | H29: 73302 | I29: 0 | J29: 46154 | K29: 46154 | L29: 0.40833333 | M29: 0.95217593 | Q29: 0 | R29: LIB IMPR CAPC CPRE LOAT MOME MatC NOLQ* | S29: 46154
A30: L01 | B30: 1959758 | C30: 25982-0 | D30: RISQUE CARE SECANTE EXPRESS BL 8ML | E30: UN | F30: 6140C2 | G30: Z01 | H30: 73302 | I30: 73758 | J30: 46162 | K30: 46163 | L30: 0.19722222 | M30: 0.52353009 | O30: 46163 | P30: 46163 | Q30: 0.32258102 | R30: LIB MATF IMPR CNPA FORN CAPC CPRE LOAT* | S30: 46163
A31: L01 | B31: 1963524 | C31: 26283-1 | D31: RISQUE ESM CREM CRIPTO ROSA BL8ML NV | E31: UN | G31: Z01 | H31: 47500 | I31: 0 | J31: 46179 | K31: 46179 | L31: 0.40138889 | M31: 0.61283565 | Q31: 0 | R31: ABER CNAT DMNV NOLQ ORSL | S31: 46179
A32: L02 | B32: 1963738 | C32: 26559-0 | D32: RISQUE ESM EF CAPRICHA NO GLOW 8 ML CL | E32: UN | G32: Z01 | H32: 47500 | I32: 0 | J32: 46182 | K32: 46183 | L32: 0.90208333 | M32: 0.42075231 | Q32: 0 | R32: ABER CNAT DMNV NOLQ ORSL | S32: 46182
A33: L02 | B33: 1963739 | C33: 26562-0 | D33: RISQUE ESM EF CHEGA E ARRASA 8ML CL | E33: UN | G33: Z01 | H33: 47500 | I33: 0 | J33: 46183 | K33: 46183 | L33: 0.46180556 | M33: 0.66797454 | Q33: 0 | R33: ABER CNAT DMNV NOLQ ORSL | S33: 46183
A34: L02 | B34: 1963558 | C34: 26604-0 | D34: RISQUE ESM CREM AMAR 8ML CL | E34: UN | G34: Z01 | H34: 47500 | I34: 0 | J34: 46181 | K34: 46181 | L34: 0.64166667 | M34: 0.84783565 | Q34: 0 | R34: ABER CNAT DMNV NOLQ ORSL | S34: 46181
A35: L02 | B35: 1963559 | C35: 26607-0 | D35: RISQUE ESM CREM ANTE SOL MAL ILUM 8ML CL | E35: UN | G35: Z01 | H35: 47500 | I35: 0 | J35: 46177 | K35: 46178 | L35: 0.94305556 | M35: 0.46172454 | Q35: 0 | R35: ABER CNAT DMNV NOLQ ORSL | S35: 46177
A36: L02 | B36: 1962823 | C36: 27842-0 | D36: RISQUE ESM MET LA VEM OUTRA PEROLA 8MLCL | E36: UN | G36: Z01 | H36: 47500 | I36: 0 | J36: 46167 | K36: 46168 | L36: 0.85833333 | M36: 0.064502315 | Q36: 0 | R36: ABER CNAT DMNV NOLQ ORSL | S36: 46167
A37: L02 | B37: 1961815 | C37: 27843-0 | D37: RISQUE ESM MET CHICLETE ME ESQUE 8ML CL | E37: UN | F37: 6142C1 | G37: Z01 | H37: 47500 | I37: 0 | J37: 46165 | K37: 46165 | L37: 0.45694444 | M37: 0.66311343 | Q37: 0 | R37: LIB IMPR CAPC CPRE LOAT MatC NOLQ ORSL | S37: 46165
A38: L01 | B38: 1963528 | C38: 28928-0 | D38: RISQUE ESM CREM ME DEIXA AMEIXA 8ML BL | E38: UN | G38: Z01 | H38: 47500 | I38: 0 | J38: 46178 | K38: 46179 | L38: 0.14861111 | M38: 0.36005787 | Q38: 0 | R38: ABER CNAT DMNV NOLQ ORSL | S38: 46179
A39: L01 | B39: 1963526 | C39: 28930-0 | D39: RISQUE ESM CREM CHOCOLIGHT 8ML BL | E39: UN | G39: Z01 | H39: 47500 | I39: 0 | J39: 46178 | K39: 46179 | L39: 0.89583333 | M39: 0.10728009 | Q39: 0 | R39: ABER CNAT DMNV NOLQ ORSL | S39: 46178
A40: L01 | B40: 1957046 | C40: 28932-0 | D40: RISQUE ESM CREM JUJUVA 8ML BL | E40: UN | F40: 6124C1 | G40: Z01 | H40: 47500 | I40: 55542 | J40: 46146 | K40: 46153 | L40: 0.275 | M40: 0.39144676 | O40: 46147 | P40: 46147 | Q40: 0.275 | R40: LIB IMPR CNPA FORN CAPC CPRE DMNV LOAT* | S40: 46147
A41: L02 | B41: 1963560 | C41: 28940-0 | D41: RISQUE ESM CREM CAIU DO CEU 8ML CL | E41: UN | G41: Z01 | H41: 47500 | I41: 0 | J41: 46178 | K41: 46178 | L41: 0.75 | M41: 0.95616898 | Q41: 0 | R41: ABER CNAT DMNV NOLQ ORSL | S41: 46178
A42: L02 | B42: 1962824 | C42: 28942-0 | D42: RISQUE ESM CREM CLIM TNS ENTRE ROS 8MLCL | E42: UN | G42: Z01 | H42: 47500 | I42: 0 | J42: 46178 | K42: 46178 | L42: 0.50277778 | M42: 0.70894676 | Q42: 0 | R42: ABER CNAT DMNV NOLQ ORSL | S42: 46178
A43: L03 | B43: 1956777 | C43: 28944-0 | D43: RISQUE ESM MET PRATA NA LATA 8ML CL | E43: UN | F43: 6090C1 | G43: Z01 | H43: 95000 | I43: 0 | J43: 46162 | K43: 46163 | L43: 0.38028935 | M43: 0.44539352 | Q43: 0 | R43: LIB IMPR CAPC CPRE DMNV LOAT MOME NOLQ* | S43: 46162
A44: L02 | B44: 1960646 | C44: 28944-0 | D44: RISQUE ESM MET PRATA NA LATA 8ML CL | E44: UN | G44: Z01 | H44: 118750 | I44: 0 | J44: 46179 | K44: 46181 | L44: 0.77222222 | M44: 0.60012731 | Q44: 0 | R44: ABER CNAT DMNV NOLQ ORSL | S44: 46179
A45: L02 | B45: 1960639 | C45: 28945-0 | D45: RISQUE ESM MET DOURA ME SE FOR CAP 8MLCL | E45: UN | G45: Z01 | H45: 47500 | I45: 0 | J45: 46165 | K45: 46165 | L45: 0.70416667 | M45: 0.91033565 | Q45: 0 | R45: ABER CNAT DMNV NOLQ ORSL | S45: 46165
A46: L05 | B46: 1958160 | C46: 29376-0 | D46: RISQUE DG BASE PRIMER FORT 9 5 ML | E46: UN | F46: 6120C1 | G46: Z01 | H46: 94734 | I46: 3192 | J46: 46149 | K46: 46150 | L46: 0.46054398 | M46: 0.94782407 | O46: 46149 | P46: 46149 | Q46: 0.48611111 | R46: LIB IMPR CNPA CAPC CPRE DMNV FRNP LOAT* | S46: 46149
A47: L05 | B47: 1962551 | C47: 29376-0 | D47: RISQUE DG BASE PRIMER FORT 9 5 ML | E47: UN | F47: 6120C1R | G47: Z01 | H47: 3192 | I47: 0 | J47: 46162 | K47: 46162 | L47: 0.27777778 | M47: 0.31736111 | Q47: 0 | R47: LIB IMPR CAPC CPRE DMNV LOAT NOLQ ORSL | S47: 46162
A48: L05 | B48: 1958169 | C48: 29376-0 | D48: RISQUE DG BASE PRIMER FORT 9 5 ML | E48: UN | G48: Z01 | H48: 199994 | I48: 0 | J48: 46176 | K48: 46181 | L48: 0.83472222 | M48: 0.56480324 | Q48: 0 | R48: ABER CNAT DMNV NOLQ ORSL | S48: 46176
A49: L05 | B49: 1960630 | C49: 29542-0 | D49: RISQUE ESM DGEL CREM MOCACCINO 9 5 ML | E49: UN | F49: 6134C1 | G49: Z01 | H49: 73682 | I49: 70668 | J49: 46156 | K49: 46160 | L49: 0.65971065 | M49: 0.4678125 | O49: 46156 | P49: 46157 | Q49: 0.65971065 | R49: LIB MATF IMPR CNPA CAPC CPRE DMNV FRNP* | S49: 46156
A50: TPM. | B50: 1958276 | C50: 29624-0 | D50: RISQUE DG SEC FAST DRY 9 ML | E50: UN | F50: 6132C1 | G50: Z01 | H50: 15000 | I50: 9840 | J50: 46163 | K50: 46163 | L50: 0 | M50: 0 | O50: 46160 | P50: 46160 | Q50: 0.4471875 | R50: LIB CNPA CAPC CPRE FRNP LOAT MOME MatC* | S50: 46163
A51: TPM. | B51: 1963042 | C51: 29624-0 | D51: RISQUE DG SEC FAST DRY 9 ML | E51: UN | G51: Z01 | H51: 45000 | I51: 0 | J51: 46203 | K51: 46203 | L51: 0 | M51: 0 | Q51: 0 | R51: ABER CNAT DMNV NOLQ ORSL | S51: 46203
A52: L05 | B52: 1949907 | C52: 29632-0 | D52: RISQUE ESM DGEL TC PIXELIZADO 9 5 ML | E52: UN | F52: 5352C1R | G52: Z01 | H52: 10224 | I52: 0 | J52: 46160 | K52: 46160 | L52: 0.72841435 | M52: 0.85217593 | Q52: 0 | R52: ABER MATF CAPC CPRE DMNV LOAT NOLQ ORSL | S52: 46160
A53: L05 | B53: 1962267 | C53: 29889-0 | D53: RISQUE COBE EFT ESTRADA PARA SERRA 9 ML | E53: UN | G53: Z01 | H53: 52630 | I53: 0 | J53: 46172 | K53: 46174 | L53: 0.34444444 | M53: 0.66890046 | Q53: 0 | R53: ABER CNAT DMNV NOLQ ORSL | S53: 46172
A54: L05 | B54: 1962268 | C54: 29889-0 | D54: RISQUE COBE EFT ESTRADA PARA SERRA 9 ML | E54: UN | G54: Z01 | H54: 42104 | I54: 0 | J54: 46174 | K54: 46175 | L54: 0.71041667 | M54: 0.83248843 | Q54: 0 | R54: ABER CNAT DMNV NOLQ ORSL | S54: 46174
A55: L05 | B55: 1962574 | C55: 29889-0 | D55: RISQUE COBE EFT ESTRADA PARA SERRA 9 ML | E55: UN | G55: Z01 | H55: 31578 | I55: 0 | J55: 46175 | K55: 46176 | L55: 0.87361111 | M55: 0.79328704 | Q55: 0 | R55: ABER CNAT DMNV NOLQ ORSL | S55: 46175
A56: L05 | B56: 1956518 | C56: 29890-0 | D56: RISQUE COBE EFT TEMPESTADE CRISTAL 9ML | E56: UN | F56: 6085C1 | G56: Z01 | H56: 52630 | I56: 0 | J56: 46162 | K56: 46163 | L56: 0.4552662 | M56: 0.40487269 | Q56: 0 | R56: LIB IMPR CAPC CANC CPRE DMNV LOAT MOME* | S56: 46162
A57: L05 | B57: 1962264 | C57: 29890-0 | D57: RISQUE COBE EFT TEMPESTADE CRISTAL 9ML | E57: UN | G57: Z01 | H57: 52630 | I57: 0 | J57: 46168 | K57: 46169 | L57: 0.54166667 | M57: 0.86612269 | Q57: 0 | R57: ABER CNAT DMNV NOLQ ORSL | S57: 46168
A58: L05 | B58: 1962265 | C58: 29890-0 | D58: RISQUE COBE EFT TEMPESTADE CRISTAL 9ML | E58: UN | G58: Z01 | H58: 42104 | I58: 0 | J58: 46169 | K58: 46171 | L58: 0.90763889 | M58: 0.34221065 | Q58: 0 | R58: ABER CNAT DMNV NOLQ ORSL | S58: 46169
A59: L05 | B59: 1962266 | C59: 29890-0 | D59: RISQUE COBE EFT TEMPESTADE CRISTAL 9ML | E59: UN | G59: Z01 | H59: 31578 | I59: 0 | J59: 46171 | K59: 46172 | L59: 0.38333333 | M59: 0.30300926 | Q59: 0 | R59: ABER CNAT DMNV NOLQ ORSL | S59: 46171
A60: L05 | B60: 1963576 | C60: 29892-0 | D60: RISQUE ESM MET LOOK INVERNAL 9 ML | E60: UN | F60: 6139C2 | G60: Z01 | H60: 84208 | I60: 85476 | J60: 46161 | K60: 46163 | L60: 0.64391204 | M60: 0.60027778 | O60: 46161 | P60: 46163 | Q60: 0.64391204 | R60: LIB MATF IMPR CNPA FORN CAPC CPRE DMNV* | S60: 46161
A61: L05 | B61: 1961930 | C61: 29893-0 | D61: RISQUE ESM MET GRANIZO 9ML | E61: UN | F61: 6140C1 | G61: Z01 | H61: 84208 | I61: 54534 | J61: 46163 | K61: 46165 | L61: 0.61204861 | M61: 0.41003472 | O61: 46163 | P61: 46164 | Q61: 0.61204861 | R61: LIB IMPR CNPA CAPC CPRE DMNV FRNP LOAT* | S61: 46163
A62: L05 | B62: 1955018 | C62: 29894-0 | D62: RISQUE ESM MET CALOR DA FOGUEIRA 9 ML | E62: UN | F62: 6014C1R | G62: Z01 | H62: 10090 | I62: 0 | J62: 46163 | K62: 46163 | L62: 0.27777778 | M62: 0.39991898 | Q62: 0 | R62: ABER CNAT DMNV LOAT NOLQ ORSL | S62: 46163
A63: L05 | B63: 1952748 | C63: 29894-0 | D63: RISQUE ESM MET CALOR DA FOGUEIRA 9 ML | E63: UN | F63: 6014C1R | G63: Z01 | H63: 8640 | I63: 0 | J63: 46164 | K63: 46164 | L63: 0.38104167 | M63: 0.48563657 | Q63: 0 | R63: LIB IMPR CAPC CPRE DMNV LOAT NOLQ ORSL | S63: 46164
A64: L05 | B64: 1961933 | C64: 29894-0 | D64: RISQUE ESM MET CALOR DA FOGUEIRA 9 ML | E64: UN | F64: 6142C1 | G64: Z01 | H64: 73682 | I64: 0 | J64: 46165 | K64: 46168 | L64: 0.45833333 | M64: 0.50008102 | Q64: 0 | R64: LIB CAPC CPRE DMNV LOAT NOLQ ORSL | S64: 46165
A65: L03 | B65: 1960767 | C65: 30155-0 | D65: RISQUE ESM MET CHOCO COSMICO 8ML CL | E65: UN | F65: 6117C1 | G65: Z01 | H65: 23750 | I65: 0 | J65: 46163 | K65: 46163 | L65: 0.8665162 | M65: 0.8665162 | Q65: 0 | R65: LIB IMPR CAPC CPRE DMNV LOAT MOME NOLQ* | S65: 46163
A66: L01 | B66: 1961785 | C66: 30159-0 | D66: RISQUE ESM CREM AMOR A PRIM MORDD 8ML BL | E66: UN | G66: Z01 | H66: 23750 | I66: 0 | J66: 46164 | K66: 46164 | L66: 0.27777778 | M66: 0.38350694 | Q66: 0 | R66: ABER CNAT DMNV NOLQ ORSL | S66: 46164
A67: L01 | B67: 1961780 | C67: 30160-0 | D67: RISQUE ESM MET O BREAK PFT EXISTE 8ML BL | E67: UN | G67: Z01 | H67: 23750 | I67: 0 | J67: 46164 | K67: 46164 | L67: 0.27777778 | M67: 0.38350694 | Q67: 0 | R67: ABER CNAT DMNV NOLQ ORSL | S67: 46164
A68: L01 | B68: 1961786 | C68: 30161-0 | D68: RISQUE ESM EFT EU MERECO ESSE GLOW 8MLBL | E68: UN | G68: Z01 | H68: 23750 | I68: 0 | J68: 46164 | K68: 46164 | L68: 0.27777778 | M68: 0.38350694 | Q68: 0 | R68: ABER CNAT DMNV NOLQ ORSL | S68: 46164
A69: L01 | B69: 1961781 | C69: 30162-0 | D69: RISQUE ESM CREM CROCANTE NA MEDIDA 8MLBL | E69: UN | G69: Z01 | H69: 23750 | I69: 0 | J69: 46165 | K69: 46165 | L69: 0.27777778 | M69: 0.38350694 | Q69: 0 | R69: ABER CNAT DMNV NOLQ ORSL | S69: 46165
A70: L01 | B70: 1961787 | C70: 30163-0 | D70: RISQUE ESM MET KITKAT MANIA 8ML BL | E70: UN | G70: Z01 | H70: 23750 | I70: 0 | J70: 46164 | K70: 46164 | L70: 0.27777778 | M70: 0.38350694 | Q70: 0 | R70: ABER CNAT DMNV NOLQ ORSL | S70: 46164
A71: L01 | B71: 1961779 | C71: 30164-0 | D71: RISQUE ESM MET CHOCO COSMICO 8ML BL | E71: UN | G71: Z01 | H71: 23750 | I71: 0 | J71: 46165 | K71: 46165 | L71: 0.27777778 | M71: 0.38350694 | Q71: 0 | R71: ABER CNAT DMNV NOLQ ORSL | S71: 46165
A72: L01 | B72: 1961782 | C72: 30165-0 | D72: RISQUE ESM MET MEU WAFERVORITO 8ML BL | E72: UN | G72: Z01 | H72: 23750 | I72: 0 | J72: 46167 | K72: 46167 | L72: 0.27777778 | M72: 0.38350694 | Q72: 0 | R72: ABER CNAT DMNV NOLQ ORSL | S72: 46167
A73: L01 | B73: 1961783 | C73: 30166-0 | D73: RISQUE ESM CREM SO MAIS UM PEDACIN 8MLBL | E73: UN | G73: Z01 | H73: 23750 | I73: 0 | J73: 46162 | K73: 46162 | L73: 0.27777778 | M73: 0.38350694 | Q73: 0 | R73: ABER CNAT DMNV NOLQ ORSL | S73: 46162
A74: L01 | B74: 1961784 | C74: 30167-0 | D74: RISQUE ESM CREM VEM KIT KERO 8ML BL | E74: UN | G74: Z01 | H74: 23750 | I74: 0 | J74: 46163 | K74: 46163 | L74: 0.27777778 | M74: 0.38350694 | Q74: 0 | R74: ABER CNAT DMNV NOLQ ORSL | S74: 46163
A75: TNQ | B75: 1935922 | C75: 407956 | D75: SA SOLUCAO ACIDO MALICO 10% | E75: KG | F75: T25J0760 | G75: Z01 | H75: 1 | I75: 0 | J75: 46162 | K75: 46162 | L75: 0.27777778 | M75: 0.27798611 | Q75: 0 | R75: LIB CAPC ERRD CPRE LOAT MatC NOLQ ORSL | S75: 46162
A76: TNQ | B76: 1935920 | C76: 407956 | D76: SA SOLUCAO ACIDO MALICO 10% | E76: KG | F76: T25J0758 | G76: Z01 | H76: 1 | I76: 0 | J76: 46164 | K76: 46164 | L76: 0.27777778 | M76: 0.27798611 | Q76: 0 | R76: LIB CAPC CPRE DMNV LOAT NOLQ ORSL | S76: 46164
A77: TNQ | B77: 1963501 | C77: 407956 | D77: SA SOLUCAO ACIDO MALICO 10% | E77: KG | F77: T26E0883 | G77: Z01 | H77: 1 | I77: 0 | J77: 46164 | K77: 46164 | L77: 0.57998843 | M77: 0.58019676 | Q77: 0 | R77: LIB CAPC CPRE DMNV LOAT NOLQ ORSL | S77: 46164
A78: TNQ | B78: 1935923 | C78: 407956 | D78: SA SOLUCAO ACIDO MALICO 10% | E78: KG | F78: T25J0761 | G78: Z01 | H78: 1 | I78: 0 | J78: 46192 | K78: 46192 | L78: 0.27777778 | M78: 0.27798611 | Q78: 0 | R78: LIB CAPC ERRD CPRE LOAT MatC NOLQ ORSL | S78: 46192
A79: TNQ | B79: 1963263 | C79: 432808 | D79: SA S.52 SOL PIG AMARELO CI 19140 15% STF | E79: KG | F79: T26E0790 | G79: Z01 | H79: 150 | I79: 0 | J79: 46167 | K79: 46167 | L79: 0.27777778 | M79: 0.31944444 | Q79: 0 | R79: LIB MATF IMPR CAPC CPRE DMNV LOAT MOME* | S79: 46167
A80: TNQ | B80: 1963565 | C80: 432816 | D80: SA S.60 SOL PIG CERISE CI 15865 15% STF | E80: KG | F80: T26E0919 | G80: Z01 | H80: 40 | I80: 0 | J80: 46169 | K80: 46169 | L80: 0.27777778 | M80: 0.28888889 | Q80: 0 | R80: LIB MATF CAPC CPRE DMNV LOAT NOLQ ORSL | S80: 46169
A81: TNQ | B81: 1960758 | C81: 432817 | D81: SA BASE GEL STF | E81: KG | F81: T26D1138 | G81: Z01 | H81: 3500 | I81: 3485 | J81: 46163 | K81: 46165 | L81: 0.40375 | M81: 0.27777778 | O81: 46163 | P81: 46163 | Q81: 0.40375 | R81: LIB IMPR CNPA CAPC CPRE DMNV FRNP LOAT* | S81: 46163
